Workbook
Name AMAZONAS: #REF!
Name AMAZONAS: #REF!
Name AMAZONAS: #REF!
Name AMAZONAS: #REF!
Name AMAZONAS: #REF!
Name AMAZONAS: #REF!
Name AMAZONAS: #REF!
Name AMAZONAS: #REF!
Name AMAZONAS: #REF!
Name AMAZONAS: #REF!
Name AMAZONAS: #REF!
Name AMAZONAS: #REF!
Name AMAZONAS: #REF!
Name AMAZONAS: #REF!
Name AMAZONAS: #REF!
Name AMAZONAS: #REF!
Name AMAZONAS: #REF!
Name AMAZONAS: #REF!
Name AMAZONAS: #REF!
Name AMAZONAS: #REF!
Name AMAZONAS: #REF!
Name AMAZONAS: #REF!
Name AMAZONAS: #REF!
Name AMAZONAS: #REF!
Name AMAZONAS: #REF!
Name AMAZONAS: #REF!
Name AMAZONAS: #REF!
Name AMAZONAS: #REF!
Name ANCASH: #REF!
Name ANCASH: #REF!
Name ANCASH: #REF!
Name ANCASH: #REF!
Name ANCASH: #REF!
Name ANCASH: #REF!
Name ANCASH: #REF!
Name ANCASH: #REF!
Name ANCASH: #REF!
Name ANCASH: #REF!
Name ANCASH: #REF!
Name ANCASH: #REF!
Name ANCASH: #REF!
Name ANCASH: #REF!
Name ANCASH: #REF!
Name ANCASH: #REF!
Name ANCASH: #REF!
Name ANCASH: #REF!
Name ANCASH: #REF!
Name ANCASH: #REF!
Name ANCASH: #REF!
Name ANCASH: #REF!
Name ANCASH: #REF!
Name ANCASH: #REF!
Name ANCASH: #REF!
Name ANCASH: #REF!
Name ANCASH: #REF!
Name ANCASH: #REF!
Name APURIMAC: #REF!
Name APURIMAC: #REF!
Name APURIMAC: #REF!
Name APURIMAC: #REF!

Sheet 3.1
A1: 3. GENERACIÓN DE ENERGÍA ELÉCTRICA
A3: 3.1. EMPRESAS QUE GENERAN ENERGÍA ELÉCTRICA
B5: 3.1.1. Empresas generadoras de energía eléctrica para el mercado eléctrico * | G5: Informa A | H5: Informante
G6: Tipo de Mercado A | H6: Mercado Eléctrico
B7: Las empresas generadoras de energía eléctrica para el mercado eléctrico, son aquellas empresas que comercializan la energía eléctrica. En el año 2024, se registraron 92 empresas pertenecientes a esta categoría. | G7: FILTRO | H7: (en blanco)
B9: Nº | C9: Nombre de la empresa | D9: Abreviatura | G9: Empresa Anuario | H9: ABREVIATURA
B10: 1 | C10: =+G10 -> Agro Industrial Paramonga S.A.A. | D10: =+H10 -> AIPSA | G10: Agro Industrial Paramonga S.A.A. | H10: AIPSA
B11: =+B10+1 -> 2 | C11: =+G11 -> Agroaurora S.A.C. | D11: =+H11 -> AGROAURORA | G11: Agroaurora S.A.C. | H11: AGROAURORA
B12: =+B11+1 -> 3 | C12: =+G12 -> Agroindustrias San Jacinto S.A.A. | D12: =+H12 -> SAN JACINTO | G12: Agroindustrias San Jacinto S.A.A. | H12: SAN JACINTO
B13: =+B12+1 -> 4 | C13: =+G13 -> Amazonas Energía Solar S.A.C. | D13: =+H13 -> AMAZONAS ENERGÍA | G13: Amazonas Energía Solar S.A.C. | H13: AMAZONAS ENERGÍA
B14: =+B13+1 -> 5 | C14: =+G14 -> Andean Power S.A.C. | D14: =+H14 -> ANDEAN POWER | G14: Andean Power S.A.C. | H14: ANDEAN POWER
B15: =+B14+1 -> 6 | C15: =+G15 -> Asociación Santa Lucia de Chacas | D15: =+H15 -> CHACAS | G15: Asociación Santa Lucia de Chacas | H15: CHACAS
B16: =+B15+1 -> 7 | C16: =+G16 -> Atria Energía S.A.C. | D16: =+H16 -> ATRIA ENERGIA | G16: Atria Energía S.A.C. | H16: ATRIA ENERGIA
B17: =+B16+1 -> 8 | C17: =+G17 -> Bioenergía del Chira S.A. | D17: =+H17 -> BIOCHIRA | G17: Bioenergía del Chira S.A. | H17: BIOCHIRA
B18: =+B17+1 -> 9 | C18: =+G18 -> Celepsa Renovables S.R.L. | D18: =+H18 -> CELEPSA RENOVABLES | G18: Celepsa Renovables S.R.L. | H18: CELEPSA RENOVABLES
B19: =+B18+1 -> 10 | C19: =+G19 -> Central Hidroeléctrica de Langui S.A. | D19: =+H19 -> LANGUI | G19: Central Hidroeléctrica de Langui S.A. | H19: LANGUI
B20: =+B19+1 -> 11 | C20: =+G20 -> Centrales Santa Rosa S.A.C. | D20: =+H20 -> CENT. SANTA ROSA | G20: Centrales Santa Rosa S.A.C. | H20: CENT. SANTA ROSA
B21: =+B20+1 -> 12 | C21: =+G21 -> Chinango S.A.C | D21: =+H21 -> CHINANGO | G21: Chinango S.A.C | H21: CHINANGO
B22: =+B21+1 -> 13 | C22: =+G22 -> Cía Hidroeléctrica San Hilarión S.A.C. | D22: =+H22 -> SAN HILARIÓN | G22: Cía Hidroeléctrica San Hilarión S.A.C. | H22: SAN HILARIÓN
... B101: =+B100+1 -> 92 | C101: =+G101 -> Termoselva S.R.L. | D101: =+H101 -> TERMOSELVA | G101: Termoselva S.R.L. | H101: TERMOSELVA
B102: (*) Sólo empresas que informan a la DGE del MINEM. Asimismo incluye información de empresas distribuidoras que cuentan con centrales de generación eléctrica. | G102: Total general
B103: (1) A partir de agosto de 2024, Enel Distribución Perú cambió de razon social a Pluz Energía Perú S.A.A.
B104: (2) A partir del mes agosto 2024, la empresa Enel Generación Perú cambia de razón social a Orygen Perú S.A.A.
B105: (3) A partir del mes de julio 2024, la C.T. Oquendo de la empresa Cogeneración Oquendo S.A.C. pasa a ser administrado por la empresa SDF Energía S.A.C.

Sheet 3.1.2
A1: 3.1.2. Empresas generadoras de energía eléctrica para uso propio * | F1: Informa A | G1: Informante
F2: Tipo de Mercado A | G2: Uso Propio
B3: Las empresas generadoras de energía eléctrica para uso propio, son aquellas empresas cuya actividad principal no es la generación de energía eléctrica; sin embargo, cuentan con centrales eléctricas. En el año 2024, se registraron 93 empresas pertenecientes a esta categoría. | F3: FILTRO | G3: (en blanco)
B5: Nº | C5: Nombre de la empresa | D5: Abreviatura | F5: Empresa Anuario | G5: ABREVIATURA
B6: 1 | C6: Agroindustrial Laredo S.A.A. | D6: =+G6 -> LAREDO | F6: Agroindustrial Laredo S.A.A. | G6: LAREDO
B7: =+B6+1 -> 2 | C7: Agrolmos S.A. (1) | D7: =+G7 -> AGROLMOS | F7: Agrolmos S.A. | G7: AGROLMOS
B8: =+B7+1 -> 3 | C8: Aguaytia Energy del Peru S.R.L. | D8: =+G8 -> AGUAYTÍA | F8: Aguaytia Energy del Peru S.R.L. | G8: AGUAYTÍA
B9: =+B8+1 -> 4 | C9: Ajeper S.A. | D9: =+G9 -> AJEPER | F9: Ajeper S.A. | G9: AJEPER
B10: =+B9+1 -> 5 | C10: Ajinomoto del Peru S.A. | D10: =+G10 -> AJINOM | F10: Ajinomoto del Peru S.A. | G10: AJINOM
B11: =+B10+1 -> 6 | C11: Alicorp S.A.A. | D11: =+G11 -> ALICORP | F11: Alicorp S.A.A. | G11: ALICORP
B12: =+B11+1 -> 7 | C12: Anabi S.A.C. | D12: =+G12 -> ANABI | F12: Anabi S.A.C. | G12: ANABI
B13: =+B12+1 -> 8 | C13: Anglo American Quellaveco S.A. | D13: =+G13 -> QUELLAVECO | F13: Anglo American Quellaveco S.A. | G13: QUELLAVECO
B14: =+B13+1 -> 9 | C14: APM Terminals Callao S.A. | D14: =+G14 -> APMTER | F14: APM Terminals Callao S.A. | G14: APMTER
B15: =+B14+1 -> 10 | C15: Apumayo S.A.C. | D15: =+G15 -> APUMAYO | F15: Apumayo S.A.C. | G15: APUMAYO
B16: =+B15+1 -> 11 | C16: Aris Indsutrial S.A. (1) | D16: =+G16 -> ARIS | F16: Aris Indsutrial S.A. | G16: ARIS
B17: =+B16+1 -> 12 | C17: Aruntani S.A.C. | D17: =+G17 -> ARUNTANI | F17: Aruntani S.A.C. | G17: ARUNTANI
B18: =+B17+1 -> 13 | C18: Austral Group S.A.A | D18: =+G18 -> AUSTRAL | F18: Austral Group S.A.A | G18: AUSTRAL
... B98: =+B97+1 -> 93 | C98: Yura S.A. | D98: =+G98 -> YURASA | F98: Yura S.A. | G98: YURASA
B99: (*) Sólo empresas que informan a la DGE del MINEM. | F99: Total general
B100: (1) Las empresas Agrolmos S.A., Aris Indsutrial S.A., Flesan Indutrial Power S.A.C y Progenere S.A.C. comenzaron a informar a la DGE del MINEM a partir del mes de enero 2024
B101: (2) La empresa OIG Perú S.A.C. empezó a informar a partir del mes de mayo 2024.

Sheet 3.2.1.1
A1: 3.2.1. Número de centrales y grupos eléctricos por empresas | AI1: Informa A | AJ1: Informante
AI2: Tipo de Mercado A | AJ2: Mercado Eléctrico | AN2: Informa A | AO2: Informante
B3: 3.2.1.1. Para el mercado eléctrico (*) | AI3: Nom Gru Anuario | AJ3: (Todas) | AN3: Tipo de Mercado A | AO3: Mercado Eléctrico
AI4: Variable | AJ4: Energía | AN4: Variable | AO4: Energía
D5: Número | E5: Número | F5: Hidráulicas | H5: Térmicas | M5: Solares | N5: Eólicas | X5: Cuenta de Nom Gru Anuario | Y5: Etiquetas de columna | AI5: FILTRO | AJ5: (en blanco) | AN5: FILTRO | AO5: (en blanco)
B6: Nº | C6: Principales empresas | D6: de | E6: de | F6: Nº | G6: Nº | H6: Nº | I6: Nº de Grupos | M6: Nº | N6: Nº | Q6: Cuenta de Central Anuario | R6: Etiquetas de columna | Y6: Hidráulico | Z6: Térmico | AD6: Solar | AE6: Eólico
D7: Centrales | E7: Grupos | F7: Centrales | G7: Grupos | H7: Centrales | I7: EL | J7: TG | K7: TV | L7: CC | M7: Centrales | N7: Centrales | Q7: Etiquetas de fila | R7: Hidráulico | S7: Térmico | T7: Solar | U7: Eólico | V7: Total general | X7: Etiquetas de fila | Y7: HI | Z7: CC | AA7: EL | AB7: TG | AC7: TV | AD7: HI | AE7: HI | AI7: Empresa Anuario | AJ7: Origen A | AK7: Central Anuario | AN7: Empresa Anuario | AO7: Central Anuario | AP7: Nom Gru Anuario | AQ7: Origen A | AR7: CTIPGRU
B8: 1 | C8: =+Q8 -> Agro Industrial Paramonga S.A.A. | D8: =+SUM(F8,H8,M8:N8) -> 1 | E8: =+SUM(G8,I8:L8) -> 1 | F8: =+IF(R8<>"",R8,"") | G8: =+IF(Y8<>"",Y8,"") | H8: =+IF(S8<>"",S8,"") -> 1 | I8: =+IF(AA8<>"",AA8,"") | J8: =+IF(AB8<>"",AB8,"") | K8: =+IF(AC8<>"",AC8,"") -> 1 | L8: =+IF(Z8<>"",Z8,"") | M8: =+IF(T8<>"",T8,"") | N8: =+IF(U8<>"",U8,"") | Q8: Agro Industrial Paramonga S.A.A. | S8: 1 | V8: 1 | X8: Agro Industrial Paramonga S.A.A. | AC8: 1 | AI8: Agro Industrial Paramonga S.A.A. | AJ8: Térmico | AK8: C.T. PARAMONGA | AN8: Agro Industrial Paramonga S.A.A. | AO8: C.T. PARAMONGA | AP8: TV01 | AQ8: Térmico | AR8: TV
B9: =+B8+1 -> 2 | C9: =+Q9 -> Agroaurora S.A.C. | D9: =+SUM(F9,H9,M9:N9) -> 1 | E9: =+SUM(G9,I9:L9) -> 1 | F9: =+IF(R9<>"",R9,"") | G9: =+IF(Y9<>"",Y9,"") | H9: =+IF(S9<>"",S9,"") -> 1 | I9: =+IF(AA9<>"",AA9,"") | J9: =+IF(AB9<>"",AB9,"") | K9: =+IF(AC9<>"",AC9,"") -> 1 | L9: =+IF(Z9<>"",Z9,"") | M9: =+IF(T9<>"",T9,"") | N9: =+IF(U9<>"",U9,"") | Q9: Agroaurora S.A.C. | S9: 1 | V9: 1 | X9: Agroaurora S.A.C. | AC9: 1 | AI9: Agroaurora S.A.C. | AJ9: Térmico | AK9: C.T. AGROAURORA | AN9: Agroaurora S.A.C. | AO9: C.T. AGROAURORA | AP9: G1 | AQ9: Térmico | AR9: TV
B10: =+B9+1 -> 3 | C10: =+Q10 -> Agroindustrias San Jacinto S.A.A. | D10: =+SUM(F10,H10,M10:N10) -> 1 | E10: =+SUM(G10,I10:L10) -> 1 | F10: =+IF(R10<>"",R10,"") | G10: =+IF(Y10<>"",Y10,"") | H10: =+IF(S10<>"",S10,"") -> 1 | I10: =+IF(AA10<>"",AA10,"") | J10: =+IF(AB10<>"",AB10,"") | K10: =+IF(AC10<>"",AC10,"") -> 1 | L10: =+IF(Z10<>"",Z10,"") | M10: =+IF(T10<>"",T10,"") | N10: =+IF(U10<>"",U10,"") | Q10: Agroindustrias San Jacinto S.A.A. | S10: 1 | V10: 1 | X10: Agroindustrias San Jacinto S.A.A. | AC10: 1 | AI10: Agroindustrias San Jacinto S.A.A. | AJ10: Térmico | AK10: C.T. SAN JACINTO | AN10: Agroindustrias San Jacinto S.A.A. | AO10: C.T. SAN JACINTO | AP10: TV1 | AQ10: Térmico | AR10: TV
B11: =+B10+1 -> 4 | C11: =+Q11 -> Amazonas Energía Solar S.A.C. | D11: =+SUM(F11,H11,M11:N11) -> 3 | E11: - | F11: =+IF(R11<>"",R11,"") | G11: =+IF(Y11<>"",Y11,"") | H11: =+IF(S11<>"",S11,"") | I11: =+IF(AA11<>"",AA11,"") | J11: =+IF(AB11<>"",AB11,"") | K11: =+IF(AC11<>"",AC11,"") | L11: =+IF(Z11<>"",Z11,"") | M11: =+IF(T11<>"",T11,"") -> 3 | N11: =+IF(U11<>"",U11,"") | Q11: Amazonas Energía Solar S.A.C. | T11: 3 | V11: 3 | X11: Amazonas Energía Solar S.A.C. | AD11: 3 | AI11: Amazonas Energía Solar S.A.C. | AJ11: Solar | AK11: C.S.F. SAN LORENZO | AN11: Amazonas Energía Solar S.A.C. | AO11: C.S.F. SAN LORENZO | AP11: Total Central | AQ11: Solar | AR11: HI
B12: =+B11+1 -> 5 | C12: =+Q12 -> Andean Power S.A.C. | D12: =+SUM(F12,H12,M12:N12) -> 1 | E12: =+SUM(G12,I12:L12) -> 2 | F12: =+IF(R12<>"",R12,"") -> 1 | G12: =+IF(Y12<>"",Y12,"") -> 2 | H12: =+IF(S12<>"",S12,"") | I12: =+IF(AA12<>"",AA12,"") | J12: =+IF(AB12<>"",AB12,"") | K12: =+IF(AC12<>"",AC12,"") | L12: =+IF(Z12<>"",Z12,"") | M12: =+IF(T12<>"",T12,"") | N12: =+IF(U12<>"",U12,"") | Q12: Andean Power S.A.C. | R12: 1 | V12: 1 | X12: Andean Power S.A.C. | Y12: 2 | AI12: Amazonas Energía Solar S.A.C. | AJ12: Solar | AK12: C.S.F. REQUENA | AN12: Amazonas Energía Solar S.A.C. | AO12: C.S.F. REQUENA | AP12: Total Central | AQ12: Solar | AR12: HI
B13: =+B12+1 -> 6 | C13: =+Q13 -> Asociación Santa Lucia de Chacas | D13: =+SUM(F13,H13,M13:N13) -> 1 | E13: =+SUM(G13,I13:L13) -> 1 | F13: =+IF(R13<>"",R13,"") -> 1 | G13: =+IF(Y13<>"",Y13,"") -> 1 | H13: =+IF(S13<>"",S13,"") | I13: =+IF(AA13<>"",AA13,"") | J13: =+IF(AB13<>"",AB13,"") | K13: =+IF(AC13<>"",AC13,"") | L13: =+IF(Z13<>"",Z13,"") | M13: =+IF(T13<>"",T13,"") | N13: =+IF(U13<>"",U13,"") | Q13: Asociación Santa Lucia de Chacas | R13: 1 | V13: 1 | X13: Asociación Santa Lucia de Chacas | Y13: 1 | AI13: Amazonas Energía Solar S.A.C. | AJ13: Solar | AK13: C.S.F TAMSHIYACU | AN13: Amazonas Energía Solar S.A.C. | AO13: C.S.F TAMSHIYACU | AP13: Total Central | AQ13: Solar | AR13: HI
B14: =+B13+1 -> 7 | C14: =+Q14 -> Atria Energía S.A.C. | D14: =+SUM(F14,H14,M14:N14) -> 1 | E14: =+SUM(G14,I14:L14) -> 1 | F14: =+IF(R14<>"",R14,"") -> 1 | G14: =+IF(Y14<>"",Y14,"") -> 1 | H14: =+IF(S14<>"",S14,"") | I14: =+IF(AA14<>"",AA14,"") | J14: =+IF(AB14<>"",AB14,"") | K14: =+IF(AC14<>"",AC14,"") | L14: =+IF(Z14<>"",Z14,"") | M14: =+IF(T14<>"",T14,"") | N14: =+IF(U14<>"",U14,"") | Q14: Atria Energía S.A.C. | R14: 1 | V14: 1 | X14: Atria Energía S.A.C. | Y14: 1 | AI14: Andean Power S.A.C. | AJ14: Hidráulico | AK14: C.H. CARHUAC | AN14: Andean Power S.A.C. | AO14: C.H. CARHUAC | AP14: G-01 | AQ14: Hidráulico | AR14: HI
B15: =+B14+1 -> 8 | C15: =+Q15 -> Bioenergía del Chira S.A. | D15: =+SUM(F15,H15,M15:N15) -> 1 | E15: =+SUM(G15,I15:L15) -> 2 | F15: =+IF(R15<>"",R15,"") | G15: =+IF(Y15<>"",Y15,"") | H15: =+IF(S15<>"",S15,"") -> 1 | I15: =+IF(AA15<>"",AA15,"") | J15: =+IF(AB15<>"",AB15,"") | K15: =+IF(AC15<>"",AC15,"") -> 2 | L15: =+IF(Z15<>"",Z15,"") | M15: =+IF(T15<>"",T15,"") | N15: =+IF(U15<>"",U15,"") | Q15: Bioenergía del Chira S.A. | S15: 1 | V15: 1 | X15: Bioenergía del Chira S.A. | AC15: 2 | AI15: Asociación Santa Lucia de Chacas | AJ15: Hidráulico | AK15: C.H. HUALLÍN I | AN15: Andean Power S.A.C. | AO15: C.H. CARHUAC | AP15: G-02 | AQ15: Hidráulico | AR15: HI
B16: =+B15+1 -> 9 | C16: =+Q16 -> Celepsa Renovables S.R.L. | D16: =+SUM(F16,H16,M16:N16) -> 1 | E16: =+SUM(G16,I16:L16) -> 3 | F16: =+IF(R16<>"",R16,"") -> 1 | G16: =+IF(Y16<>"",Y16,"") -> 3 | H16: =+IF(S16<>"",S16,"") | I16: =+IF(AA16<>"",AA16,"") | J16: =+IF(AB16<>"",AB16,"") | K16: =+IF(AC16<>"",AC16,"") | L16: =+IF(Z16<>"",Z16,"") | M16: =+IF(T16<>"",T16,"") | N16: =+IF(U16<>"",U16,"") | Q16: Celepsa Renovables S.R.L. | R16: 1 | V16: 1 | X16: Celepsa Renovables S.R.L. | Y16: 3 | AI16: Atria Energía S.A.C. | AJ16: Hidráulico | AK16: C.H. PURMACANA | AN16: Asociación Santa Lucia de Chacas | AO16: C.H. HUALLÍN I | AP16: G1 | AQ16: Hidráulico | AR16: HI
B17: =+B16+1 -> 10 | C17: =+Q17 -> Central Hidroeléctrica de Langui S.A. | D17: =+SUM(F17,H17,M17:N17) -> 1 | E17: =+SUM(G17,I17:L17) -> 3 | F17: =+IF(R17<>"",R17,"") -> 1 | G17: =+IF(Y17<>"",Y17,"") -> 3 | H17: =+IF(S17<>"",S17,"") | I17: =+IF(AA17<>"",AA17,"") | J17: =+IF(AB17<>"",AB17,"") | K17: =+IF(AC17<>"",AC17,"") | L17: =+IF(Z17<>"",Z17,"") | M17: =+IF(T17<>"",T17,"") | N17: =+IF(U17<>"",U17,"") | Q17: Central Hidroeléctrica de Langui S.A. | R17: 1 | V17: 1 | X17: Central Hidroeléctrica de Langui S.A. | Y17: 3 | AI17: Bioenergía del Chira S.A. | AJ17: Térmico | AK17: C.T. CAÑA BRAVA | AN17: Atria Energía S.A.C. | AO17: C.H. PURMACANA | AP17: G1 | AQ17: Hidráulico | AR17: HI
B18: =+B17+1 -> 11 | C18: =+Q18 -> Centrales Santa Rosa S.A.C. | D18: =+SUM(F18,H18,M18:N18) -> 2 | E18: =+SUM(G18,I18:L18) -> 2 | F18: =+IF(R18<>"",R18,"") -> 2 | G18: =+IF(Y18<>"",Y18,"") -> 2 | H18: =+IF(S18<>"",S18,"") | I18: =+IF(AA18<>"",AA18,"") | J18: =+IF(AB18<>"",AB18,"") | K18: =+IF(AC18<>"",AC18,"") | L18: =+IF(Z18<>"",Z18,"") | M18: =+IF(T18<>"",T18,"") | N18: =+IF(U18<>"",U18,"") | Q18: Centrales Santa Rosa S.A.C. | R18: 2 | V18: 2 | X18: Centrales Santa Rosa S.A.C. | Y18: 2 | AI18: Celepsa Renovables S.R.L. | AJ18: Hidráulico | AK18: C.H. MARAÑON | AN18: Bioenergía del Chira S.A. | AO18: C.T. CAÑA BRAVA | AP18: TM5000 | AQ18: Térmico | AR18: TV
B19: =+B18+1 -> 12 | C19: =+Q19 -> Chinango S.A.C | D19: =+SUM(F19,H19,M19:N19) -> 2 | E19: =+SUM(G19,I19:L19) -> 3 | F19: =+IF(R19<>"",R19,"") -> 2 | G19: =+IF(Y19<>"",Y19,"") -> 3 | H19: =+IF(S19<>"",S19,"") | I19: =+IF(AA19<>"",AA19,"") | J19: =+IF(AB19<>"",AB19,"") | K19: =+IF(AC19<>"",AC19,"") | L19: =+IF(Z19<>"",Z19,"") | M19: =+IF(T19<>"",T19,"") | N19: =+IF(U19<>"",U19,"") | Q19: Chinango S.A.C | R19: 2 | V19: 2 | X19: Chinango S.A.C | Y19: 3 | AI19: Central Hidroeléctrica de Langui S.A. | AJ19: Hidráulico | AK19: C.H. LANGUI | AN19: Bioenergía del Chira S.A. | AO19: C.T. CAÑA BRAVA | AP19: TMC5000 | AQ19: Térmico | AR19: TV
B20: =+B19+1 -> 13 | C20: =+Q20 -> Cía Hidroeléctrica San Hilarión S.A.C. | D20: =+SUM(F20,H20,M20:N20) -> 1 | E20: =+SUM(G20,I20:L20) -> 1 | F20: =+IF(R20<>"",R20,"") -> 1 | G20: =+IF(Y20<>"",Y20,"") -> 1 | H20: =+IF(S20<>"",S20,"") | I20: =+IF(AA20<>"",AA20,"") | J20: =+IF(AB20<>"",AB20,"") | K20: =+IF(AC20<>"",AC20,"") | L20: =+IF(Z20<>"",Z20,"") | M20: =+IF(T20<>"",T20,"") | N20: =+IF(U20<>"",U20,"") | Q20: Cía Hidroeléctrica San Hilarión S.A.C. | R20: 1 | V20: 1 | X20: Cía Hidroeléctrica San Hilarión S.A.C. | Y20: 1 | AI20: Centrales Santa Rosa S.A.C. | AJ20: Hidráulico | AK20: C.H. SANTA ROSA I | AN20: Celepsa Renovables S.R.L. | AO20: C.H. MARAÑON | AP20: FRANCIS 1 | AQ20: Hidráulico | AR20: HI
B21: =+B20+1 -> 14 | C21: =+Q21 -> Cogeneración Oquendo S.A.C. | D21: - | E21: - | F21: =+IF(R21<>"",R21,"") | G21: =+IF(Y21<>"",Y21,"") | H21: - | I21: =+IF(AA21<>"",AA21,"") | J21: - | K21: - | L21: =+IF(Z21<>"",Z21,"") | M21: =+IF(T21<>"",T21,"") | N21: =+IF(U21<>"",U21,"") | Q21: Cogeneración Oquendo S.A.C. | S21: 1 | V21: 1 | X21: Cogeneración Oquendo S.A.C. | AB21: 1 | AC21: 2 | AI21: Centrales Santa Rosa S.A.C. | AJ21: Hidráulico | AK21: C.H. SANTA ROSA II | AN21: Celepsa Renovables S.R.L. | AO21: C.H. MARAÑON | AP21: FRANCIS 2 | AQ21: Hidráulico | AR21: HI
B22: =+B21+1 -> 15 | C22: =+Q22 -> Colca Solar S.A.C. | D22: =+SUM(F22,H22,M22:N22) -> 1 | E22: - | F22: =+IF(R22<>"",R22,"") | G22: =+IF(Y22<>"",Y22,"") | H22: =+IF(S22<>"",S22,"") | I22: =+IF(AA22<>"",AA22,"") | J22: =+IF(AB22<>"",AB22,"") | K22: =+IF(AC22<>"",AC22,"") | L22: =+IF(Z22<>"",Z22,"") | M22: =+IF(T22<>"",T22,"") -> 1 | N22: =+IF(U22<>"",U22,"") | Q22: Colca Solar S.A.C. | T22: 1 | V22: 1 | X22: Colca Solar S.A.C. | AD22: 1 | AI22: Chinango S.A.C | AJ22: Hidráulico | AK22: C.H. CHIMAY | AN22: Celepsa Renovables S.R.L. | AO22: C.H. MARAÑON | AP22: FRANCIS 3 | AQ22: Hidráulico | AR22: HI
B23: =+B22+1 -> 16 | C23: =+Q23 -> Compañia Eléctrica El Platanal S.A. | D23: =+SUM(F23,H23,M23:N23) -> 1 | E23: =+SUM(G23,I23:L23) -> 2 | F23: =+IF(R23<>"",R23,"") -> 1 | G23: =+IF(Y23<>"",Y23,"") -> 2 | H23: =+IF(S23<>"",S23,"") | I23: =+IF(AA23<>"",AA23,"") | J23: =+IF(AB23<>"",AB23,"") | K23: =+IF(AC23<>"",AC23,"") | L23: =+IF(Z23<>"",Z23,"") | M23: =+IF(T23<>"",T23,"") | N23: =+IF(U23<>"",U23,"") | Q23: Compañia Eléctrica El Platanal S.A. | R23: 1 | V23: 1 | X23: Compañia Eléctrica El Platanal S.A. | Y23: 2 | AI23: Chinango S.A.C | AJ23: Hidráulico | AK23: C.H. YANANGO | AN23: Central Hidroeléctrica de Langui S.A. | AO23: C.H. LANGUI | AP23: GRUPO 1 | AQ23: Hidráulico | AR23: HI
B24: =+B23+1 -> 17 | C24: =+Q24 -> Compañia Hidroeléctrica Tingo S.A. | D24: =+SUM(F24,H24,M24:N24) -> 1 | E24: =+SUM(G24,I24:L24) -> 4 | F24: =+IF(R24<>"",R24,"") -> 1 | G24: 4 | H24: =+IF(S24<>"",S24,"") | I24: =+IF(AA24<>"",AA24,"") | J24: =+IF(AB24<>"",AB24,"") | K24: =+IF(AC24<>"",AC24,"") | L24: =+IF(Z24<>"",Z24,"") | M24: =+IF(T24<>"",T24,"") | N24: =+IF(U24<>"",U24,"") | Q24: Compañia Hidroeléctrica Tingo S.A. | R24: 1 | V24: 1 | X24: Compañia Hidroeléctrica Tingo S.A. | Y24: 1 | AI24: Cía Hidroeléctrica San Hilarión S.A.C. | AJ24: Hidráulico | AK24: C.H. SAN HILARION | AN24: Central Hidroeléctrica de Langui S.A. | AO24: C.H. LANGUI | AP24: Grupo 2 | AQ24: Hidráulico | AR24: HI
B25: =+B24+1 -> 18 | C25: =+Q25 -> Consorcio Eléctrico Villacurí S.A.C. | D25: =+SUM(F25,H25,M25:N25) -> 3 | E25: =+SUM(G25,I25:L25) -> 3 | F25: =+IF(R25<>"",R25,"") -> 1 | G25: =+IF(Y25<>"",Y25,"") -> 1 | H25: =+IF(S25<>"",S25,"") -> 2 | I25: =+IF(AA25<>"",AA25,"") -> 2 | J25: =+IF(AB25<>"",AB25,"") | K25: =+IF(AC25<>"",AC25,"") | L25: =+IF(Z25<>"",Z25,"") | M25: =+IF(T25<>"",T25,"") | N25: =+IF(U25<>"",U25,"") | Q25: Consorcio Eléctrico Villacurí S.A.C. | R25: 1 | S25: 2 | V25: 3 | X25: Consorcio Eléctrico Villacurí S.A.C. | Y25: 1 | AA25: 2 | AI25: Cogeneración Oquendo S.A.C. | AJ25: Térmico | AK25: C.T. OQUENDO | AN25: Central Hidroeléctrica de Langui S.A. | AO25: C.H. LANGUI | AP25: Grupo 3 | AQ25: Hidráulico | AR25: HI
B26: =+B25+1 -> 19 | C26: =+Q26 -> E.A.W. Muller S.A. | D26: =+SUM(F26,H26,M26:N26) -> 1 | E26: =+SUM(G26,I26:L26) -> 3 | F26: =+IF(R26<>"",R26,"") -> 1 | G26: =+IF(Y26<>"",Y26,"") -> 3 | H26: =+IF(S26<>"",S26,"") | I26: =+IF(AA26<>"",AA26,"") | J26: =+IF(AB26<>"",AB26,"") | K26: =+IF(AC26<>"",AC26,"") | L26: =+IF(Z26<>"",Z26,"") | M26: =+IF(T26<>"",T26,"") | N26: =+IF(U26<>"",U26,"") | Q26: E.A.W. Muller S.A. | R26: 1 | V26: 1 | X26: E.A.W. Muller S.A. | Y26: 3 | AI26: Colca Solar S.A.C. | AJ26: Solar | AK26: C.S. YARUCAYA | AN26: Centrales Santa Rosa S.A.C. | AO26: C.H. SANTA ROSA I | AP26: G-1 | AQ26: Hidráulico | AR26: HI
B27: =+B26+1 -> 20 | C27: =+Q27 -> Eléctrica Yanapampa S.A.C. | D27: =+SUM(F27,H27,M27:N27) -> 1 | E27: =+SUM(G27,I27:L27) -> 3 | F27: =+IF(R27<>"",R27,"") -> 1 | G27: =+IF(Y27<>"",Y27,"") -> 3 | H27: =+IF(S27<>"",S27,"") | I27: =+IF(AA27<>"",AA27,"") | J27: =+IF(AB27<>"",AB27,"") | K27: =+IF(AC27<>"",AC27,"") | L27: =+IF(Z27<>"",Z27,"") | M27: =+IF(T27<>"",T27,"") | N27: =+IF(U27<>"",U27,"") | Q27: Eléctrica Yanapampa S.A.C. | R27: 1 | V27: 1 | X27: Eléctrica Yanapampa S.A.C. | Y27: 3 | AI27: Compañia Eléctrica El Platanal S.A. | AJ27: Hidráulico | AK27: C.H. EL PLATANAL | AN27: Centrales Santa Rosa S.A.C. | AO27: C.H. SANTA ROSA II | AP27: G-1 | AQ27: Hidráulico | AR27: HI
B28: =+B27+1 -> 21 | C28: =+Q28 -> Electro Dunas S.A.A. | D28: =+SUM(F28,H28,M28:N28) -> 4 | E28: =+SUM(G28,I28:L28) -> 9 | F28: =+IF(R28<>"",R28,"") -> 1 | G28: =+IF(Y28<>"",Y28,"") -> 2 | H28: =+IF(S28<>"",S28,"") -> 3 | I28: =+IF(AA28<>"",AA28,"") -> 7 | J28: =+IF(AB28<>"",AB28,"") | K28: =+IF(AC28<>"",AC28,"") | L28: =+IF(Z28<>"",Z28,"") | M28: =+IF(T28<>"",T28,"") | N28: =+IF(U28<>"",U28,"") | Q28: Electro Dunas S.A.A. | R28: 1 | S28: 3 | V28: 4 | X28: Electro Dunas S.A.A. | Y28: 2 | AA28: 7 | AI28: Compañia Hidroeléctrica Tingo S.A. | AJ28: Hidráulico | AK28: C.H. TINGO | AN28: Chinango S.A.C | AO28: C.H. CHIMAY | AP28: GR-1 | AQ28: Hidráulico | AR28: HI
B29: =+B28+1 -> 22 | C29: =+Q29 -> Electro Oriente S. A. | D29: =+SUM(F29,H29,M29:N29) -> 35 | E29: =+SUM(G29,I29:L29) -> 131 | F29: =+IF(R29<>"",R29,"") -> 10 | G29: =+IF(Y29<>"",Y29,"") -> 21 | H29: =+IF(S29<>"",S29,"") -> 25 | I29: =+IF(AA29<>"",AA29,"") -> 110 | J29: =+IF(AB29<>"",AB29,"") | K29: =+IF(AC29<>"",AC29,"") | L29: =+IF(Z29<>"",Z29,"") | M29: =+IF(T29<>"",T29,"") | N29: =+IF(U29<>"",U29,"") | Q29: Electro Oriente S. A. | R29: 10 | S29: 25 | V29: 35 | X29: Electro Oriente S. A. | Y29: 21 | AA29: 110 | AI29: Consorcio Eléctrico Villacurí S.A.C. | AJ29: Hidráulico | AK29: C.H. COELVIHIDRO 1 - QUIPICO | AN29: Chinango S.A.C | AO29: C.H. CHIMAY | AP29: GR-2 | AQ29: Hidráulico | AR29: HI
B30: =+B29+1 -> 23 | C30: =+Q30 -> Electro Puno S.A.A. | D30: =+SUM(F30,H30,M30:N30) -> 3 | E30: =+SUM(G30,I30:L30) -> 4 | F30: =+IF(R30<>"",R30,"") -> 1 | G30: =+IF(Y30<>"",Y30,"") -> 3 | H30: =+IF(S30<>"",S30,"") -> 1 | I30: =+IF(AA30<>"",AA30,"") -> 1 | J30: =+IF(AB30<>"",AB30,"") | K30: =+IF(AC30<>"",AC30,"") | L30: =+IF(Z30<>"",Z30,"") | M30: =+IF(T30<>"",T30,"") -> 1 | N30: =+IF(U30<>"",U30,"") | Q30: Electro Puno S.A.A. | R30: 1 | S30: 1 | T30: 1 | V30: 3 | X30: Electro Puno S.A.A. | Y30: 3 | AA30: 1 | AD30: 1 | AI30: Consorcio Eléctrico Villacurí S.A.C. | AJ30: Térmico | AK30: C.T. SALAS | AN30: Chinango S.A.C | AO30: C.H. YANANGO | AP30: GR-1 | AQ30: Hidráulico | AR30: HI
B31: =+B30+1 -> 24 | C31: =+Q31 -> Electro Sur Este S.A.A. | D31: =+SUM(F31,H31,M31:N31) -> 10 | E31: =+SUM(G31,I31:L31) -> 20 | F31: =+IF(R31<>"",R31,"") -> 7 | G31: =+IF(Y31<>"",Y31,"") -> 17 | H31: =+IF(S31<>"",S31,"") -> 3 | I31: =+IF(AA31<>"",AA31,"") -> 3 | J31: =+IF(AB31<>"",AB31,"") | K31: =+IF(AC31<>"",AC31,"") | L31: =+IF(Z31<>"",Z31,"") | M31: =+IF(T31<>"",T31,"") | N31: =+IF(U31<>"",U31,"") | Q31: Electro Sur Este S.A.A. | R31: 7 | S31: 3 | V31: 10 | X31: Electro Sur Este S.A.A. | Y31: 17 | AA31: 3 | AI31: Consorcio Eléctrico Villacurí S.A.C. | AJ31: Térmico | AK31: C.T. VILLACURI | AN31: Cía Hidroeléctrica San Hilarión S.A.C. | AO31: C.H. SAN HILARION | AP31: G1 | AQ31: Hidráulico | AR31: HI
B32: =+B31+1 -> 25 | C32: =+Q32 -> Electro Ucayali S.A. | D32: =+SUM(F32,H32,M32:N32) -> 4 | E32: =+SUM(G32,I32:L32) -> 11 | F32: =+IF(R32<>"",R32,"") -> 1 | G32: =+IF(Y32<>"",Y32,"") -> 3 | H32: =+IF(S32<>"",S32,"") -> 2 | I32: =+IF(AA32<>"",AA32,"") -> 8 | J32: =+IF(AB32<>"",AB32,"") | K32: =+IF(AC32<>"",AC32,"") | L32: =+IF(Z32<>"",Z32,"") | M32: =+IF(T32<>"",T32,"") -> 1 | N32: =+IF(U32<>"",U32,"") | Q32: Electro Ucayali S.A. | R32: 1 | S32: 2 | T32: 1 | V32: 4 | X32: Electro Ucayali S.A. | Y32: 3 | AA32: 8 | AD32: 1 | AI32: E.A.W. Muller S.A. | AJ32: Hidráulico | AK32: C.H. LA ESPERANZA | AN32: Cogeneración Oquendo S.A.C. | AO32: C.T. OQUENDO | AP32: TG1 | AQ32: Térmico | AR32: TG
B33: =+B32+1 -> 26 | C33: =+Q33 -> Electro Zaña S.A.C. | D33: =+SUM(F33,H33,M33:N33) -> 1 | E33: =+SUM(G33,I33:L33) -> 2 | F33: =+IF(R33<>"",R33,"") -> 1 | G33: =+IF(Y33<>"",Y33,"") -> 2 | H33: =+IF(S33<>"",S33,"") | I33: =+IF(AA33<>"",AA33,"") | J33: =+IF(AB33<>"",AB33,"") | K33: =+IF(AC33<>"",AC33,"") | L33: =+IF(Z33<>"",Z33,"") | M33: =+IF(T33<>"",T33,"") | N33: =+IF(U33<>"",U33,"") | Q33: Electro Zaña S.A.C. | R33: 1 | V33: 1 | X33: Electro Zaña S.A.C. | Y33: 2 | AI33: Eléctrica Yanapampa S.A.C. | AJ33: Hidráulico | AK33: C.H. YANAPAMPA | AN33: Cogeneración Oquendo S.A.C. | AO33: C.T. OQUENDO | AP33: TV1 | AQ33: Térmico | AR33: TV
B34: =+B33+1 -> 27 | C34: =+Q34 -> Electrocentro S.A. | D34: =+SUM(F34,H34,M34:N34) -> 17 | E34: =+SUM(G34,I34:L34) -> 36 | F34: =+IF(R34<>"",R34,"") -> 14 | G34: =+IF(Y34<>"",Y34,"") -> 28 | H34: =+IF(S34<>"",S34,"") -> 3 | I34: =+IF(AA34<>"",AA34,"") -> 8 | J34: =+IF(AB34<>"",AB34,"") | K34: =+IF(AC34<>"",AC34,"") | L34: =+IF(Z34<>"",Z34,"") | M34: =+IF(T34<>"",T34,"") | N34: =+IF(U34<>"",U34,"") | Q34: Electrocentro S.A. | R34: 14 | S34: 3 | V34: 17 | X34: Electrocentro S.A. | Y34: 28 | AA34: 8 | AI34: Electro Dunas S.A.A. | AJ34: Hidráulico | AK34: C.H. LARAMATE | AN34: Cogeneración Oquendo S.A.C. | AO34: C.T. OQUENDO | AP34: TV2 | AQ34: Térmico | AR34: TV
B35: =+B34+1 -> 28 | C35: =+Q35 -> Electronoroeste S. A. | D35: =+SUM(F35,H35,M35:N35) -> 8 | E35: =+SUM(G35,I35:L35) -> 23 | F35: =+IF(R35<>"",R35,"") -> 4 | G35: =+IF(Y35<>"",Y35,"") -> 8 | H35: =+IF(S35<>"",S35,"") -> 4 | I35: =+IF(AA35<>"",AA35,"") -> 14 | J35: =+IF(AB35<>"",AB35,"") -> 1 | K35: =+IF(AC35<>"",AC35,"") | L35: =+IF(Z35<>"",Z35,"") | M35: =+IF(T35<>"",T35,"") | N35: =+IF(U35<>"",U35,"") | Q35: Electronoroeste S. A. | R35: 4 | S35: 4 | V35: 8 | X35: Electronoroeste S. A. | Y35: 8 | AA35: 14 | AB35: 1 | AI35: Electro Dunas S.A.A. | AJ35: Térmico | AK35: C.T. LUREN | AN35: Colca Solar S.A.C. | AO35: C.S. YARUCAYA | AP35: Circuito 1 | AQ35: Solar | AR35: HI
B36: =+B35+1 -> 29 | C36: =+Q36 -> Electronorte S.A. | D36: =+SUM(F36,H36,M36:N36) -> 9 | E36: =+SUM(G36,I36:L36) -> 15 | F36: =+IF(R36<>"",R36,"") -> 4 | G36: =+IF(Y36<>"",Y36,"") -> 9 | H36: =+IF(S36<>"",S36,"") -> 5 | I36: =+IF(AA36<>"",AA36,"") -> 6 | J36: =+IF(AB36<>"",AB36,"") | K36: =+IF(AC36<>"",AC36,"") | L36: =+IF(Z36<>"",Z36,"") | M36: =+IF(T36<>"",T36,"") | N36: =+IF(U36<>"",U36,"") | Q36: Electronorte S.A. | R36: 4 | S36: 5 | V36: 9 | X36: Electronorte S.A. | Y36: 9 | AA36: 6 | AI36: Electro Dunas S.A.A. | AJ36: Térmico | AK36: C.T. EL PEDREGAL | AN36: Compañia Eléctrica El Platanal S.A. | AO36: C.H. EL PLATANAL | AP36: PELTON 1 | AQ36: Hidráulico | AR36: HI
B37: =+B36+1 -> 30 | C37: =+Q37 -> Electroperú S. A. | D37: =+SUM(F37,H37,M37:N37) -> 3 | E37: =+SUM(G37,I37:L37) -> 12 | F37: =+IF(R37<>"",R37,"") -> 2 | G37: =+IF(Y37<>"",Y37,"") -> 10 | H37: =+IF(S37<>"",S37,"") -> 1 | I37: =+IF(AA37<>"",AA37,"") -> 2 | J37: =+IF(AB37<>"",AB37,"") | K37: =+IF(AC37<>"",AC37,"") | L37: =+IF(Z37<>"",Z37,"") | M37: =+IF(T37<>"",T37,"") | N37: =+IF(U37<>"",U37,"") | Q37: Electroperú S. A. | R37: 2 | S37: 1 | V37: 3 | X37: Electroperú S. A. | Y37: 10 | AA37: 2 | AI37: Electro Dunas S.A.A. | AJ37: Térmico | AK37: C.T. NASCA | AN37: Compañia Eléctrica El Platanal S.A. | AO37: C.H. EL PLATANAL | AP37: Pelton 2 | AQ37: Hidráulico | AR37: HI
B38: =+B37+1 -> 31 | C38: =+Q38 -> Emp. de Generación Eléctrica de Arequipa S. A. | D38: =+SUM(F38,H38,M38:N38) -> 8 | E38: =+SUM(G38,I38:L38) -> 20 | F38: =+IF(R38<>"",R38,"") -> 6 | G38: =+IF(Y38<>"",Y38,"") -> 14 | H38: =+IF(S38<>"",S38,"") -> 2 | I38: =+IF(AA38<>"",AA38,"") -> 5 | J38: =+IF(AB38<>"",AB38,"") | K38: =+IF(AC38<>"",AC38,"") | L38: =+IF(Z38<>"",Z38,"") -> 1 | M38: =+IF(T38<>"",T38,"") | N38: =+IF(U38<>"",U38,"") | Q38: Emp. de Generación Eléctrica de Arequipa S. A. | R38: 6 | S38: 2 | V38: 8 | X38: Emp. de Generación Eléctrica de Arequipa S. A. | Y38: 14 | Z38: 1 | AA38: 5 | AI38: Electro Oriente S. A. | AJ38: Hidráulico | AK38: C.H. CACLIC | AN38: Compañia Hidroeléctrica Tingo S.A. | AO38: C.H. TINGO | AP38: Allis Charner 1-4 | AQ38: Hidráulico | AR38: HI
B39: =+B38+1 -> 32 | C39: =+Q39 -> Emp. de Generación Eléctrica del Sur S. A. | D39: =+SUM(F39,H39,M39:N39) -> 3 | E39: =+SUM(G39,I39:L39) -> 7 | F39: =+IF(R39<>"",R39,"") -> 2 | G39: =+IF(Y39<>"",Y39,"") -> 3 | H39: =+IF(S39<>"",S39,"") -> 1 | I39: =+IF(AA39<>"",AA39,"") -> 4 | J39: =+IF(AB39<>"",AB39,"") | K39: =+IF(AC39<>"",AC39,"") | L39: =+IF(Z39<>"",Z39,"") | M39: =+IF(T39<>"",T39,"") | N39: =+IF(U39<>"",U39,"") | Q39: Emp. de Generación Eléctrica del Sur S. A. | R39: 2 | S39: 1 | V39: 3 | X39: Emp. de Generación Eléctrica del Sur S. A. | Y39: 3 | AA39: 4 | AI39: Electro Oriente S. A. | AJ39: Hidráulico | AK39: C.H. EL GERA | AN39: Consorcio Eléctrico Villacurí S.A.C. | AO39: C.H. COELVIHIDRO 1 - QUIPICO | AP39: G-1 | AQ39: Hidráulico | AR39: HI
B40: =+B39+1 -> 33 | C40: =+Q40 -> Emp. Gen y Comercializadora de Serv Pub de Elec. Pangoa | D40: =+SUM(F40,H40,M40:N40) -> 1 | E40: =+SUM(G40,I40:L40) -> 2 | F40: =+IF(R40<>"",R40,"") -> 1 | G40: =+IF(Y40<>"",Y40,"") -> 2 | H40: =+IF(S40<>"",S40,"") | I40: =+IF(AA40<>"",AA40,"") | J40: =+IF(AB40<>"",AB40,"") | K40: =+IF(AC40<>"",AC40,"") | L40: =+IF(Z40<>"",Z40,"") | M40: =+IF(T40<>"",T40,"") | N40: =+IF(U40<>"",U40,"") | Q40: Emp. Gen y Comercializadora de Serv Pub de Elec. Pangoa | R40: 1 | V40: 1 | X40: Emp. Gen y Comercializadora de Serv Pub de Elec. Pangoa | Y40: 2 | AI40: Electro Oriente S. A. | AJ40: Hidráulico | AK40: C.H. EL MUYO | AN40: Consorcio Eléctrico Villacurí S.A.C. | AO40: C.T. SALAS | AP40: G-1 | AQ40: Térmico | AR40: EL
B41: =+B40+1 -> 34 | C41: =+Q41 -> Empresa de Generación Eléctrica Canchayllo S.A.C. | D41: =+SUM(F41,H41,M41:N41) -> 1 | E41: =+SUM(G41,I41:L41) -> 1 | F41: =+IF(R41<>"",R41,"") -> 1 | G41: =+IF(Y41<>"",Y41,"") -> 1 | H41: =+IF(S41<>"",S41,"") | I41: =+IF(AA41<>"",AA41,"") | J41: =+IF(AB41<>"",AB41,"") | K41: =+IF(AC41<>"",AC41,"") | L41: =+IF(Z41<>"",Z41,"") | M41: =+IF(T41<>"",T41,"") | N41: =+IF(U41<>"",U41,"") | Q41: Empresa de Generación Eléctrica Canchayllo S.A.C. | R41: 1 | V41: 1 | X41: Empresa de Generación Eléctrica Canchayllo S.A.C. | Y41: 1 | AI41: Electro Oriente S. A. | AJ41: Hidráulico | AK41: C.H. LA PELOTA | AN41: Consorcio Eléctrico Villacurí S.A.C. | AO41: C.T. VILLACURI | AP41: G-1 | AQ41: Térmico | AR41: EL
B42: =+B41+1 -> 35 | C42: =+Q42 -> Empresa de Generación Eléctrica Junín S.A.C. | D42: =+SUM(F42,H42,M42:N42) -> 6 | E42: =+SUM(G42,I42:L42) -> 12 | F42: =+IF(R42<>"",R42,"") -> 6 | G42: =+IF(Y42<>"",Y42,"") -> 12 | H42: =+IF(S42<>"",S42,"") | I42: =+IF(AA42<>"",AA42,"") | J42: =+IF(AB42<>"",AB42,"") | K42: =+IF(AC42<>"",AC42,"") | L42: =+IF(Z42<>"",Z42,"") | M42: =+IF(T42<>"",T42,"") | N42: =+IF(U42<>"",U42,"") | Q42: Empresa de Generación Eléctrica Junín S.A.C. | R42: 6 | V42: 6 | X42: Empresa de Generación Eléctrica Junín S.A.C. | Y42: 12 | AI42: Electro Oriente S. A. | AJ42: Hidráulico | AK42: C.H. PUCARÁ | AN42: E.A.W. Muller S.A. | AO42: C.H. LA ESPERANZA | AP42: Planta 1 | AQ42: Hidráulico | AR42: HI
B43: =+B42+1 -> 36 | C43: =+Q43 -> Empresa de Generacion Electrica Machupicchu S.A. | D43: =+SUM(F43,H43,M43:N43) -> 2 | E43: =+SUM(G43,I43:L43) -> 11 | F43: =+IF(R43<>"",R43,"") -> 1 | G43: =+IF(Y43<>"",Y43,"") -> 4 | H43: =+IF(S43<>"",S43,"") -> 1 | I43: =+IF(AA43<>"",AA43,"") -> 7 | J43: =+IF(AB43<>"",AB43,"") | K43: =+IF(AC43<>"",AC43,"") | L43: =+IF(Z43<>"",Z43,"") | M43: =+IF(T43<>"",T43,"") | N43: =+IF(U43<>"",U43,"") | Q43: Empresa de Generacion Electrica Machupicchu S.A. | R43: 1 | S43: 1 | V43: 2 | X43: Empresa de Generacion Electrica Machupicchu S.A. | Y43: 4 | AA43: 7 | AI43: Electro Oriente S. A. | AJ43: Hidráulico | AK43: C.H. QUANDA | AN43: E.A.W. Muller S.A. | AO43: C.H. LA ESPERANZA | AP43: Planta 2 | AQ43: Hidráulico | AR43: HI
B44: =+B43+1 -> 37 | C44: =+Q44 -> Empresa de Generación Eléctrica Rio Baños S.A.C. | D44: =+SUM(F44,H44,M44:N44) -> 1 | E44: =+SUM(G44,I44:L44) -> 2 | F44: =+IF(R44<>"",R44,"") -> 1 | G44: =+IF(Y44<>"",Y44,"") -> 2 | H44: =+IF(S44<>"",S44,"") | I44: =+IF(AA44<>"",AA44,"") | J44: =+IF(AB44<>"",AB44,"") | K44: =+IF(AC44<>"",AC44,"") | L44: =+IF(Z44<>"",Z44,"") | M44: =+IF(T44<>"",T44,"") | N44: =+IF(U44<>"",U44,"") | Q44: Empresa de Generación Eléctrica Rio Baños S.A.C. | R44: 1 | V44: 1 | X44: Empresa de Generación Eléctrica Rio Baños S.A.C. | Y44: 2 | AI44: Electro Oriente S. A. | AJ44: Hidráulico | AK44: C.H. SHITARAYACU | AN44: E.A.W. Muller S.A. | AO44: C.H. LA ESPERANZA | AP44: Planta 3 | AQ44: Hidráulico | AR44: HI
B45: =+B44+1 -> 38 | C45: =+Q45 -> Empresa de Generación Eléctrica San Gabán S. A. | D45: =+SUM(F45,H45,M45:N45) -> 2 | E45: =+SUM(G45,I45:L45) -> 3 | F45: =+IF(R45<>"",R45,"") -> 2 | G45: =+IF(Y45<>"",Y45,"") -> 3 | H45: =+IF(S45<>"",S45,"") | I45: =+IF(AA45<>"",AA45,"") | J45: =+IF(AB45<>"",AB45,"") | K45: =+IF(AC45<>"",AC45,"") | L45: =+IF(Z45<>"",Z45,"") | M45: =+IF(T45<>"",T45,"") | N45: =+IF(U45<>"",U45,"") | Q45: Empresa de Generación Eléctrica San Gabán S. A. | R45: 2 | V45: 2 | X45: Empresa de Generación Eléctrica San Gabán S. A. | Y45: 3 | AI45: Electro Oriente S. A. | AJ45: Hidráulico | AK45: C.H. TABACONAS | AN45: Eléctrica Yanapampa S.A.C. | AO45: C.H. YANAPAMPA | AP45: GRUPO 1 | AQ45: Hidráulico | AR45: HI
B46: =+B45+1 -> 39 | C46: =+Q46 -> Empresa de Generación Eléctrica Santa Ana S.R.L. | D46: =+SUM(F46,H46,M46:N46) -> 1 | E46: =+SUM(G46,I46:L46) -> 1 | F46: =+IF(R46<>"",R46,"") -> 1 | G46: =+IF(Y46<>"",Y46,"") -> 1 | H46: =+IF(S46<>"",S46,"") | I46: =+IF(AA46<>"",AA46,"") | J46: =+IF(AB46<>"",AB46,"") | K46: =+IF(AC46<>"",AC46,"") | L46: =+IF(Z46<>"",Z46,"") | M46: =+IF(T46<>"",T46,"") | N46: =+IF(U46<>"",U46,"") | Q46: Empresa de Generación Eléctrica Santa Ana S.R.L. | R46: 1 | V46: 1 | X46: Empresa de Generación Eléctrica Santa Ana S.R.L. | Y46: 1 | AI46: Electro Oriente S. A. | AJ46: Hidráulico | AK46: C.H. POMAHUACA | AN46: Eléctrica Yanapampa S.A.C. | AO46: C.H. YANAPAMPA | AP46: Grupo 2 | AQ46: Hidráulico | AR46: HI
B47: =+B46+1 -> 40 | C47: =+Q47 -> Empresa de Generación Huallaga S.A. | D47: =+SUM(F47,H47,M47:N47) -> 1 | E47: =+SUM(G47,I47:L47) -> 3 | F47: =+IF(R47<>"",R47,"") -> 1 | G47: =+IF(Y47<>"",Y47,"") -> 3 | H47: =+IF(S47<>"",S47,"") | I47: =+IF(AA47<>"",AA47,"") | J47: =+IF(AB47<>"",AB47,"") | K47: =+IF(AC47<>"",AC47,"") | L47: =+IF(Z47<>"",Z47,"") | M47: =+IF(T47<>"",T47,"") | N47: =+IF(U47<>"",U47,"") | Q47: Empresa de Generación Huallaga S.A. | R47: 1 | V47: 1 | X47: Empresa de Generación Huallaga S.A. | Y47: 3 | AI47: Electro Oriente S. A. | AJ47: Hidráulico | AK47: C.H. LA PISUQUIA | AN47: Eléctrica Yanapampa S.A.C. | AO47: C.H. YANAPAMPA | AP47: Grupo 3 | AQ47: Hidráulico | AR47: HI
B48: =+B47+1 -> 41 | C48: =+Q48 -> Empresa de Generación Huanza S.A. | D48: =+SUM(F48,H48,M48:N48) -> 1 | E48: =+SUM(G48,I48:L48) -> 2 | F48: =+IF(R48<>"",R48,"") -> 1 | G48: =+IF(Y48<>"",Y48,"") -> 2 | H48: =+IF(S48<>"",S48,"") | I48: =+IF(AA48<>"",AA48,"") | J48: =+IF(AB48<>"",AB48,"") | K48: =+IF(AC48<>"",AC48,"") | L48: =+IF(Z48<>"",Z48,"") | M48: =+IF(T48<>"",T48,"") | N48: =+IF(U48<>"",U48,"") | Q48: Empresa de Generación Huanza S.A. | R48: 1 | V48: 1 | X48: Empresa de Generación Huanza S.A. | Y48: 2 | AI48: Electro Oriente S. A. | AJ48: Térmico | AK48: C.T. BAGUA GRANDE | AN48: Electro Dunas S.A.A. | AO48: C.H. LARAMATE | AP48: DRESS 1 | AQ48: Hidráulico | AR48: HI
B49: =+B48+1 -> 42 | C49: =+Q49 -> Empresa de Interés Local Hidroeléctrica S.A. de Chacas | D49: =+SUM(F49,H49,M49:N49) -> 2 | E49: =+SUM(G49,I49:L49) -> 3 | F49: =+IF(R49<>"",R49,"") -> 2 | G49: =+IF(Y49<>"",Y49,"") -> 3 | H49: =+IF(S49<>"",S49,"") | I49: =+IF(AA49<>"",AA49,"") | J49: =+IF(AB49<>"",AB49,"") | K49: =+IF(AC49<>"",AC49,"") | L49: =+IF(Z49<>"",Z49,"") | M49: =+IF(T49<>"",T49,"") | N49: =+IF(U49<>"",U49,"") | Q49: Empresa de Interés Local Hidroeléctrica S.A. de Chacas | R49: 2 | V49: 2 | X49: Empresa de Interés Local Hidroeléctrica S.A. de Chacas | Y49: 3 | AI49: Electro Oriente S. A. | AJ49: Térmico | AK49: C.T. BELLAVISTA | AN49: Electro Dunas S.A.A. | AO49: C.H. LARAMATE | AP49: DRESS 2 | AQ49: Hidráulico | AR49: HI
B50: =+B49+1 -> 43 | C50: =+Q50 -> Empresa Eléctrica Agua Azul S.A. | D50: =+SUM(F50,H50,M50:N50) -> 1 | E50: =+SUM(G50,I50:L50) -> 2 | F50: =+IF(R50<>"",R50,"") -> 1 | G50: =+IF(Y50<>"",Y50,"") -> 2 | H50: =+IF(S50<>"",S50,"") | I50: =+IF(AA50<>"",AA50,"") | J50: =+IF(AB50<>"",AB50,"") | K50: =+IF(AC50<>"",AC50,"") | L50: =+IF(Z50<>"",Z50,"") | M50: =+IF(T50<>"",T50,"") | N50: =+IF(U50<>"",U50,"") | Q50: Empresa Eléctrica Agua Azul S.A. | R50: 1 | V50: 1 | X50: Empresa Eléctrica Agua Azul S.A. | Y50: 2 | AI50: Electro Oriente S. A. | AJ50: Térmico | AK50: C.T. CABALLOCOCHA | AN50: Electro Dunas S.A.A. | AO50: C.T. LUREN | AP50: G1 | AQ50: Térmico | AR50: EL
B51: =+B50+1 -> 44 | C51: =+Q51 -> Empresa Eléctrica Rio Doble S.A. | D51: =+SUM(F51,H51,M51:N51) -> 2 | E51: =+SUM(G51,I51:L51) -> 3 | F51: =+IF(R51<>"",R51,"") -> 1 | G51: =+IF(Y51<>"",Y51,"") -> 2 | H51: =+IF(S51<>"",S51,"") -> 1 | I51: =+IF(AA51<>"",AA51,"") -> 1 | J51: =+IF(AB51<>"",AB51,"") | K51: =+IF(AC51<>"",AC51,"") | L51: =+IF(Z51<>"",Z51,"") | M51: =+IF(T51<>"",T51,"") | N51: =+IF(U51<>"",U51,"") | Q51: Empresa Eléctrica Rio Doble S.A. | R51: 1 | S51: 1 | V51: 2 | X51: Empresa Eléctrica Rio Doble S.A. | Y51: 2 | AA51: 1 | AI51: Electro Oriente S. A. | AJ51: Térmico | AK51: C.T. CONTAMANA | AN51: Electro Dunas S.A.A. | AO51: C.T. LUREN | AP51: G2 | AQ51: Térmico | AR51: EL
B52: =+B51+1 -> 45 | C52: =+Q52 -> Enel Distribución Perú S.A.A. | D52: =+SUM(F52,H52,M52:N52) -> 5 | E52: =+SUM(G52,I52:L52) -> 12 | F52: =+IF(R52<>"",R52,"") -> 4 | G52: =+IF(Y52<>"",Y52,"") -> 8 | H52: =+IF(S52<>"",S52,"") -> 1 | I52: =+IF(AA52<>"",AA52,"") -> 4 | J52: =+IF(AB52<>"",AB52,"") | K52: =+IF(AC52<>"",AC52,"") | L52: =+IF(Z52<>"",Z52,"") | M52: =+IF(T52<>"",T52,"") | N52: =+IF(U52<>"",U52,"") | Q52: Enel Distribución Perú S.A.A. | R52: 4 | S52: 1 | V52: 5 | X52: Enel Distribución Perú S.A.A. | Y52: 8 | AA52: 4 | AI52: Electro Oriente S. A. | AJ52: Térmico | AK52: C.T. EL ESTRECHO | AN52: Electro Dunas S.A.A. | AO52: C.T. EL PEDREGAL | AP52: G1 | AQ52: Térmico | AR52: EL
B53: =+B52+1 -> 46 | C53: =+Q53 -> Enel Generación Perú S.A.A. | D53: =+SUM(F53,H53,M53:N53) -> 12 | E53: =+SUM(G53,I53:L53) -> 27 | F53: =+IF(R53<>"",R53,"") -> 6 | G53: =+IF(Y53<>"",Y53,"") -> 17 | H53: =+IF(S53<>"",S53,"") -> 2 | I53: =+IF(AA53<>"",AA53,"") | J53: =+IF(AB53<>"",AB53,"") -> 9 | K53: =+IF(AC53<>"",AC53,"") -> 1 | L53: =+IF(Z53<>"",Z53,"") | M53: =+IF(T53<>"",T53,"") -> 2 | N53: =+IF(U53<>"",U53,"") -> 2 | Q53: Enel Generación Perú S.A.A. | R53: 6 | S53: 2 | T53: 2 | U53: 2 | V53: 12 | X53: Enel Generación Perú S.A.A. | Y53: 17 | AB53: 9 | AC53: 1 | AD53: 17 | AE53: 18 | AI53: Electro Oriente S. A. | AJ53: Térmico | AK53: C.T. GRAN PERÚ | AN53: Electro Dunas S.A.A. | AO53: C.T. EL PEDREGAL | AP53: G2 | AQ53: Térmico | AR53: EL
B54: =+B53+1 -> 47 | C54: =+Q54 -> Enel Generación Piura S.A. | D54: =+SUM(F54,H54,M54:N54) -> 3 | E54: =+SUM(G54,I54:L54) -> 3 | F54: =+IF(R54<>"",R54,"") | G54: =+IF(Y54<>"",Y54,"") | H54: =+IF(S54<>"",S54,"") -> 3 | I54: =+IF(AA54<>"",AA54,"") | J54: =+IF(AB54<>"",AB54,"") -> 3 | K54: =+IF(AC54<>"",AC54,"") | L54: =+IF(Z54<>"",Z54,"") | M54: =+IF(T54<>"",T54,"") | N54: =+IF(U54<>"",U54,"") | Q54: Enel Generación Piura S.A. | S54: 3 | V54: 3 | X54: Enel Generación Piura S.A. | AB54: 3 | AI54: Electro Oriente S. A. | AJ54: Térmico | AK54: C.T. INDIANA | AN54: Electro Dunas S.A.A. | AO54: C.T. NASCA | AP54: G1 | AQ54: Térmico | AR54: EL
B55: =+B54+1 -> 48 | C55: =+Q55 -> Energía Eólica S.A. | D55: =+SUM(F55,H55,M55:N55) -> 2 | E55: - | F55: =+IF(R55<>"",R55,"") | G55: =+IF(Y55<>"",Y55,"") | H55: =+IF(S55<>"",S55,"") | I55: =+IF(AA55<>"",AA55,"") | J55: =+IF(AB55<>"",AB55,"") | K55: =+IF(AC55<>"",AC55,"") | L55: =+IF(Z55<>"",Z55,"") | M55: =+IF(T55<>"",T55,"") | N55: =+IF(U55<>"",U55,"") -> 2 | Q55: Energía Eólica S.A. | U55: 2 | V55: 2 | X55: Energía Eólica S.A. | AE55: 2 | AI55: Electro Oriente S. A. | AJ55: Térmico | AK55: C.T. IQT. DIESEL - DIESEL | AN55: Electro Dunas S.A.A. | AO55: C.T. NASCA | AP55: G2 | AQ55: Térmico | AR55: EL
B56: =+B55+1 -> 49 | C56: =+Q56 -> Energía Renovable del Sur S.A. | D56: =+SUM(F56,H56,M56:N56) -> 1 | E56: - | F56: =+IF(R56<>"",R56,"") | G56: =+IF(Y56<>"",Y56,"") | H56: =+IF(S56<>"",S56,"") | I56: =+IF(AA56<>"",AA56,"") | J56: =+IF(AB56<>"",AB56,"") | K56: =+IF(AC56<>"",AC56,"") | L56: =+IF(Z56<>"",Z56,"") | M56: =+IF(T56<>"",T56,"") | N56: =+IF(U56<>"",U56,"") -> 1 | Q56: Energía Renovable del Sur S.A. | U56: 1 | V56: 1 | X56: Energía Renovable del Sur S.A. | AE56: 8 | AI56: Electro Oriente S. A. | AJ56: Térmico | AK56: C.T. IQUITOS DIESEL WARTSILA | AN56: Electro Dunas S.A.A. | AO56: C.T. NASCA | AP56: G3 | AQ56: Térmico | AR56: EL
B57: =+B56+1 -> 50 | C57: =+Q57 -> ENGIE EnergÍa Perú S.A. | D57: =+SUM(F57,H57,M57:N57) -> 7 | E57: =+SUM(G57,I57:L57) -> 17 | F57: =+IF(R57<>"",R57,"") -> 2 | G57: =+IF(Y57<>"",Y57,"") -> 5 | H57: =+IF(S57<>"",S57,"") -> 3 | I57: =+IF(AA57<>"",AA57,"") | J57: =+IF(AB57<>"",AB57,"") -> 10 | K57: =+IF(AC57<>"",AC57,"") -> 2 | L57: =+IF(Z57<>"",Z57,"") | M57: =+IF(T57<>"",T57,"") -> 1 | N57: =+IF(U57<>"",U57,"") -> 1 | Q57: ENGIE EnergÍa Perú S.A. | R57: 2 | S57: 3 | T57: 1 | U57: 1 | V57: 7 | X57: ENGIE EnergÍa Perú S.A. | Y57: 5 | AB57: 10 | AC57: 2 | AD57: 3 | AE57: 4 | AI57: Electro Oriente S. A. | AJ57: Térmico | AK57: C.T. JENARO HERRERA | AN57: Electro Oriente S. A. | AO57: C.H. CACLIC | AP57: Turbina 1 | AQ57: Hidráulico | AR57: HI
B58: =+B57+1 -> 51 | C58: =+Q58 -> Fénix Power Perú S.A. | D58: =+SUM(F58,H58,M58:N58) -> 1 | E58: =+SUM(G58,I58:L58) -> 3 | F58: =+IF(R58<>"",R58,"") | G58: =+IF(Y58<>"",Y58,"") | H58: =+IF(S58<>"",S58,"") -> 1 | I58: =+IF(AA58<>"",AA58,"") | J58: =+IF(AB58<>"",AB58,"") | K58: =+IF(AC58<>"",AC58,"") | L58: =+IF(Z58<>"",Z58,"") -> 3 | M58: =+IF(T58<>"",T58,"") | N58: =+IF(U58<>"",U58,"") | Q58: Fénix Power Perú S.A. | S58: 1 | V58: 1 | X58: Fénix Power Perú S.A. | Z58: 3 | AI58: Electro Oriente S. A. | AJ58: Térmico | AK58: C.T. LAGUNAS | AN58: Electro Oriente S. A. | AO58: C.H. CACLIC | AP58: Turbina 2 | AQ58: Hidráulico | AR58: HI
B59: =+B58+1 -> 52 | C59: =+Q59 -> Generación Andina S.A.C. | D59: =+SUM(F59,H59,M59:N59) -> 2 | E59: =+SUM(G59,I59:L59) -> 4 | F59: =+IF(R59<>"",R59,"") -> 2 | G59: =+IF(Y59<>"",Y59,"") -> 4 | H59: =+IF(S59<>"",S59,"") | I59: =+IF(AA59<>"",AA59,"") | J59: =+IF(AB59<>"",AB59,"") | K59: =+IF(AC59<>"",AC59,"") | L59: =+IF(Z59<>"",Z59,"") | M59: =+IF(T59<>"",T59,"") | N59: =+IF(U59<>"",U59,"") | Q59: Generación Andina S.A.C. | R59: 2 | V59: 2 | X59: Generación Andina S.A.C. | Y59: 4 | AI59: Electro Oriente S. A. | AJ59: Térmico | AK59: C.T. NAUTA | AN59: Electro Oriente S. A. | AO59: C.H. CACLIC | AP59: Turbina 3 | AQ59: Hidráulico | AR59: HI
B60: =+B59+1 -> 53 | C60: =+Q60 -> Generadora de Energía del Perú S.A. | D60: =+SUM(F60,H60,M60:N60) -> 4 | E60: =+SUM(G60,I60:L60) -> 8 | F60: =+IF(R60<>"",R60,"") -> 4 | G60: =+IF(Y60<>"",Y60,"") -> 8 | H60: =+IF(S60<>"",S60,"") | I60: =+IF(AA60<>"",AA60,"") | J60: =+IF(AB60<>"",AB60,"") | K60: =+IF(AC60<>"",AC60,"") | L60: =+IF(Z60<>"",Z60,"") | M60: =+IF(T60<>"",T60,"") | N60: =+IF(U60<>"",U60,"") | Q60: Generadora de Energía del Perú S.A. | R60: 4 | V60: 4 | X60: Generadora de Energía del Perú S.A. | Y60: 8 | AI60: Electro Oriente S. A. | AJ60: Térmico | AK60: C.T. ORELLANA | AN60: Electro Oriente S. A. | AO60: C.H. CACLIC | AP60: Turbina 4 | AQ60: Hidráulico | AR60: HI
B61: =+B60+1 -> 54 | C61: =+Q61 -> Genrent del Peru S.A.C. | D61: =+SUM(F61,H61,M61:N61) -> 1 | E61: =+SUM(G61,I61:L61) -> 7 | F61: =+IF(R61<>"",R61,"") | G61: =+IF(Y61<>"",Y61,"") | H61: =+IF(S61<>"",S61,"") -> 1 | I61: =+IF(AA61<>"",AA61,"") -> 7 | J61: =+IF(AB61<>"",AB61,"") | K61: =+IF(AC61<>"",AC61,"") | L61: =+IF(Z61<>"",Z61,"") | M61: =+IF(T61<>"",T61,"") | N61: =+IF(U61<>"",U61,"") | Q61: Genrent del Peru S.A.C. | S61: 1 | V61: 1 | X61: Genrent del Peru S.A.C. | AA61: 7 | AI61: Electro Oriente S. A. | AJ61: Térmico | AK61: C.T. PETROPOLIS | AN61: Electro Oriente S. A. | AO61: C.H. EL GERA | AP61: GRUPO 1 | AQ61: Hidráulico | AR61: HI
B62: =+B61+1 -> 55 | C62: =+Q62 -> GM Operaciones S.A.C. | D62: =+SUM(F62,H62,M62:N62) -> 1 | E62: =+SUM(G62,I62:L62) -> 2 | F62: =+IF(R62<>"",R62,"") | G62: =+IF(Y62<>"",Y62,"") | H62: =+IF(S62<>"",S62,"") -> 1 | I62: =+IF(AA62<>"",AA62,"") | J62: =+IF(AB62<>"",AB62,"") | K62: =+IF(AC62<>"",AC62,"") -> 2 | L62: =+IF(Z62<>"",Z62,"") | M62: =+IF(T62<>"",T62,"") | N62: =+IF(U62<>"",U62,"") | Q62: GM Operaciones S.A.C. | S62: 1 | V62: 1 | X62: GM Operaciones S.A.C. | AC62: 2 | AI62: Electro Oriente S. A. | AJ62: Térmico | AK62: C.T. REQUENA | AN62: Electro Oriente S. A. | AO62: C.H. EL GERA | AP62: Grupo 2 | AQ62: Hidráulico | AR62: HI
B63: =+B62+1 -> 56 | C63: =+Q63 -> GR Cortarrama S.A.C. | D63: =+SUM(F63,H63,M63:N63) -> 1 | E63: - | F63: =+IF(R63<>"",R63,"") | G63: =+IF(Y63<>"",Y63,"") | H63: =+IF(S63<>"",S63,"") | I63: =+IF(AA63<>"",AA63,"") | J63: =+IF(AB63<>"",AB63,"") | K63: =+IF(AC63<>"",AC63,"") | L63: =+IF(Z63<>"",Z63,"") | M63: =+IF(T63<>"",T63,"") -> 1 | N63: =+IF(U63<>"",U63,"") | Q63: GR Cortarrama S.A.C. | T63: 1 | V63: 1 | X63: GR Cortarrama S.A.C. | AD63: 1 | AI63: Electro Oriente S. A. | AJ63: Térmico | AK63: C.T. TAMSHIYACU | AN63: Electro Oriente S. A. | AO63: C.H. EL GERA | AP63: Grupo 3 | AQ63: Hidráulico | AR63: HI
B64: =+B63+1 -> 57 | C64: =+Q64 -> GR Paino S.A.C. | D64: =+SUM(F64,H64,M64:N64) -> 1 | E64: - | F64: =+IF(R64<>"",R64,"") | G64: =+IF(Y64<>"",Y64,"") | H64: =+IF(S64<>"",S64,"") | I64: =+IF(AA64<>"",AA64,"") | J64: =+IF(AB64<>"",AB64,"") | K64: =+IF(AC64<>"",AC64,"") | L64: =+IF(Z64<>"",Z64,"") | M64: =+IF(T64<>"",T64,"") | N64: =+IF(U64<>"",U64,"") -> 1 | Q64: GR Paino S.A.C. | U64: 1 | V64: 1 | X64: GR Paino S.A.C. | AE64: 1 | AI64: Electro Oriente S. A. | AJ64: Térmico | AK64: C.T. TARAPOTO | AN64: Electro Oriente S. A. | AO64: C.H. EL MUYO | AP64: Turbina 1 | AQ64: Hidráulico | AR64: HI
B65: =+B64+1 -> 58 | C65: =+Q65 -> GR Taruca S.A.C. | D65: =+SUM(F65,H65,M65:N65) -> 1 | E65: - | F65: =+IF(R65<>"",R65,"") | G65: =+IF(Y65<>"",Y65,"") | H65: =+IF(S65<>"",S65,"") | I65: =+IF(AA65<>"",AA65,"") | J65: =+IF(AB65<>"",AB65,"") | K65: =+IF(AC65<>"",AC65,"") | L65: =+IF(Z65<>"",Z65,"") | M65: =+IF(T65<>"",T65,"") | N65: =+IF(U65<>"",U65,"") -> 1 | Q65: GR Taruca S.A.C. | U65: 1 | V65: 1 | X65: GR Taruca S.A.C. | AE65: 1 | AI65: Electro Oriente S. A. | AJ65: Térmico | AK65: C.T. YURIMAGUAS | AN65: Electro Oriente S. A. | AO65: C.H. EL MUYO | AP65: Turbina 2 | AQ65: Hidráulico | AR65: HI
B66: =+B65+1 -> 59 | C66: =+Q66 -> Hidrandina S.A. | D66: =+SUM(F66,H66,M66:N66) -> 13 | E66: =+SUM(G66,I66:L66) -> 33 | F66: =+IF(R66<>"",R66,"") -> 11 | G66: =+IF(Y66<>"",Y66,"") -> 17 | H66: =+IF(S66<>"",S66,"") -> 2 | I66: 16 | J66: =+IF(AB66<>"",AB66,"") | K66: =+IF(AC66<>"",AC66,"") | L66: =+IF(Z66<>"",Z66,"") | M66: =+IF(T66<>"",T66,"") | N66: =+IF(U66<>"",U66,"") | Q66: Hidrandina S.A. | R66: 11 | S66: 2 | V66: 13 | X66: Hidrandina S.A. | Y66: 17 | AA66: 5 | AI66: Electro Oriente S. A. | AJ66: Térmico | AK66: C.T. JUAN VELAZCO ALVARADO | AN66: Electro Oriente S. A. | AO66: C.H. LA PELOTA | AP66: Turbina 1 | AQ66: Hidráulico | AR66: HI
B67: =+B66+1 -> 60 | C67: =+Q67 -> Hidrocañete S.A. | D67: =+SUM(F67,H67,M67:N67) -> 1 | E67: =+SUM(G67,I67:L67) -> 1 | F67: =+IF(R67<>"",R67,"") -> 1 | G67: =+IF(Y67<>"",Y67,"") -> 1 | H67: =+IF(S67<>"",S67,"") | I67: =+IF(AA67<>"",AA67,"") | J67: =+IF(AB67<>"",AB67,"") | K67: =+IF(AC67<>"",AC67,"") | L67: =+IF(Z67<>"",Z67,"") | M67: =+IF(T67<>"",T67,"") | N67: =+IF(U67<>"",U67,"") | Q67: Hidrocañete S.A. | R67: 1 | V67: 1 | X67: Hidrocañete S.A. | Y67: 1 | AI67: Electro Oriente S. A. | AJ67: Térmico | AK67: C.T. ISLA SANTA ROSA | AN67: Electro Oriente S. A. | AO67: C.H. LA PELOTA | AP67: Turbina 2 | AQ67: Hidráulico | AR67: HI
B68: =+B67+1 -> 61 | C68: =+Q68 -> Hidroeléctrica Huanchor S.A.C. | D68: =+SUM(F68,H68,M68:N68) -> 3 | E68: =+SUM(G68,I68:L68) -> 4 | F68: =+IF(R68<>"",R68,"") -> 3 | G68: =+IF(Y68<>"",Y68,"") -> 4 | H68: =+IF(S68<>"",S68,"") | I68: =+IF(AA68<>"",AA68,"") | J68: =+IF(AB68<>"",AB68,"") | K68: =+IF(AC68<>"",AC68,"") | L68: =+IF(Z68<>"",Z68,"") | M68: =+IF(T68<>"",T68,"") | N68: =+IF(U68<>"",U68,"") | Q68: Hidroeléctrica Huanchor S.A.C. | R68: 3 | V68: 3 | X68: Hidroeléctrica Huanchor S.A.C. | Y68: 4 | AI68: Electro Oriente S. A. | AJ68: Térmico | AK68: C.T. MAYORUNA | AN68: Electro Oriente S. A. | AO68: C.H. PUCARÁ | AP68: T-1 | AQ68: Hidráulico | AR68: HI
B69: =+B68+1 -> 62 | C69: =+Q69 -> Huaura Power Group S.A. | D69: =+SUM(F69,H69,M69:N69) -> 1 | E69: =+SUM(G69,I69:L69) -> 2 | F69: =+IF(R69<>"",R69,"") -> 1 | G69: =+IF(Y69<>"",Y69,"") -> 2 | H69: =+IF(S69<>"",S69,"") | I69: =+IF(AA69<>"",AA69,"") | J69: =+IF(AB69<>"",AB69,"") | K69: =+IF(AC69<>"",AC69,"") | L69: =+IF(Z69<>"",Z69,"") | M69: =+IF(T69<>"",T69,"") | N69: =+IF(U69<>"",U69,"") | Q69: Huaura Power Group S.A. | R69: 1 | V69: 1 | X69: Huaura Power Group S.A. | Y69: 2 | AI69: Electro Oriente S. A. | AJ69: Térmico | AK69: C.T. SAN FRANCISCO | AN69: Electro Oriente S. A. | AO69: C.H. PUCARÁ | AP69: T-2 | AQ69: Hidráulico | AR69: HI
B70: =+B69+1 -> 63 | C70: =+Q70 -> Hydro Pátapo S.A.C. | D70: =+SUM(F70,H70,M70:N70) -> 1 | E70: =+SUM(G70,I70:L70) -> 1 | F70: =+IF(R70<>"",R70,"") -> 1 | G70: =+IF(Y70<>"",Y70,"") -> 1 | H70: =+IF(S70<>"",S70,"") | I70: =+IF(AA70<>"",AA70,"") | J70: =+IF(AB70<>"",AB70,"") | K70: =+IF(AC70<>"",AC70,"") | L70: =+IF(Z70<>"",Z70,"") | M70: =+IF(T70<>"",T70,"") | N70: =+IF(U70<>"",U70,"") | Q70: Hydro Pátapo S.A.C. | R70: 1 | V70: 1 | X70: Hydro Pátapo S.A.C. | Y70: 1 | AI70: Electro Oriente S. A. | AJ70: Térmico | AK70: C.T. SAN IGNACIO | AN70: Electro Oriente S. A. | AO70: C.H. QUANDA | AP70: Turbina 1 | AQ70: Hidráulico | AR70: HI
B71: =+B70+1 -> 64 | C71: =+Q71 -> Infraestructuras y Energías del Perú S.A.C. | D71: =+SUM(F71,H71,M71:N71) -> 2 | E71: =+SUM(G71,I71:L71) -> 36 | F71: =+IF(R71<>"",R71,"") | G71: =+IF(Y71<>"",Y71,"") | H71: =+IF(S71<>"",S71,"") -> 2 | I71: =25+11 -> 36 | J71: =+IF(AB71<>"",AB71,"") | K71: =+IF(AC71<>"",AC71,"") | L71: =+IF(Z71<>"",Z71,"") | M71: =+IF(T71<>"",T71,"") | N71: =+IF(U71<>"",U71,"") | Q71: Infraestructuras y Energías del Perú S.A.C. | S71: 2 | V71: 2 | X71: Infraestructuras y Energías del Perú S.A.C. | AA71: 2 | AI71: Electro Oriente S. A. | AJ71: Térmico | AK71: C.T. ISLANDIA | AN71: Electro Oriente S. A. | AO71: C.H. QUANDA | AP71: Turbina 2 | AQ71: Hidráulico | AR71: HI
B72: =+B71+1 -> 65 | C72: =+Q72 -> Inland Energy S.A.C. | D72: =+SUM(F72,H72,M72:N72) -> 1 | E72: =+SUM(G72,I72:L72) -> 2 | F72: =+IF(R72<>"",R72,"") -> 1 | G72: =+IF(Y72<>"",Y72,"") -> 2 | H72: =+IF(S72<>"",S72,"") | I72: =+IF(AA72<>"",AA72,"") | J72: =+IF(AB72<>"",AB72,"") | K72: =+IF(AC72<>"",AC72,"") | L72: =+IF(Z72<>"",Z72,"") | M72: =+IF(T72<>"",T72,"") | N72: =+IF(U72<>"",U72,"") | Q72: Inland Energy S.A.C. | R72: 1 | V72: 1 | X72: Inland Energy S.A.C. | Y72: 2 | AI72: Electro Oriente S. A. | AJ72: Térmico | AK72: C.T. SAN LORENZO | AN72: Electro Oriente S. A. | AO72: C.H. SHITARAYACU | AP72: G1 | AQ72: Hidráulico | AR72: HI
B73: =+B72+1 -> 66 | C73: =+Q73 -> Kallpa Generación S.A. | D73: =+SUM(F73,H73,M73:N73) -> 3 | E73: =+SUM(G73,I73:L73) -> 10 | F73: =+IF(R73<>"",R73,"") -> 1 | G73: =+IF(Y73<>"",Y73,"") -> 4 | H73: =+IF(S73<>"",S73,"") -> 2 | I73: =+IF(AA73<>"",AA73,"") | J73: =+IF(AB73<>"",AB73,"") -> 4 | K73: =+IF(AC73<>"",AC73,"") -> 2 | L73: =+IF(Z73<>"",Z73,"") | M73: =+IF(T73<>"",T73,"") | N73: =+IF(U73<>"",U73,"") | Q73: Kallpa Generación S.A. | R73: 1 | S73: 2 | V73: 3 | X73: Kallpa Generación S.A. | Y73: 4 | AB73: 4 | AC73: 2 | AI73: Electro Puno S.A.A. | AJ73: Hidráulico | AK73: C.H. SANDIA | AN73: Electro Oriente S. A. | AO73: C.H. SHITARAYACU | AP73: G2 | AQ73: Hidráulico | AR73: HI
B74: =+B73+1 -> 67 | C74: =+Q74 -> Kondu S.A.C. | D74: =+SUM(F74,H74,M74:N74) -> 1 | E74: - | F74: =+IF(R74<>"",R74,"") | G74: =+IF(Y74<>"",Y74,"") | H74: =+IF(S74<>"",S74,"") | I74: =+IF(AA74<>"",AA74,"") | J74: =+IF(AB74<>"",AB74,"") | K74: =+IF(AC74<>"",AC74,"") | L74: =+IF(Z74<>"",Z74,"") | M74: =+IF(T74<>"",T74,"") -> 1 | N74: =+IF(U74<>"",U74,"") | Q74: Kondu S.A.C. | T74: 1 | V74: 1 | X74: Kondu S.A.C. | AD74: 1 | AI74: Electro Puno S.A.A. | AJ74: Solar | AK74: C.S. AMANTANÍ | AN74: Electro Oriente S. A. | AO74: C.H. TABACONAS | AP74: GRUPO 1 | AQ74: Hidráulico | AR74: HI
B75: =+B74+1 -> 68 | C75: =+Q75 -> La Virgen S.A.C. | D75: =+SUM(F75,H75,M75:N75) -> 1 | E75: =+SUM(G75,I75:L75) -> 3 | F75: =+IF(R75<>"",R75,"") -> 1 | G75: =+IF(Y75<>"",Y75,"") -> 3 | H75: =+IF(S75<>"",S75,"") | I75: =+IF(AA75<>"",AA75,"") | J75: =+IF(AB75<>"",AB75,"") | K75: =+IF(AC75<>"",AC75,"") | L75: =+IF(Z75<>"",Z75,"") | M75: =+IF(T75<>"",T75,"") | N75: =+IF(U75<>"",U75,"") | Q75: La Virgen S.A.C. | R75: 1 | V75: 1 | X75: La Virgen S.A.C. | Y75: 3 | AI75: Electro Puno S.A.A. | AJ75: Térmico | AK75: C.T. AMANTANÍ | AN75: Electro Oriente S. A. | AO75: C.H. TABACONAS | AP75: Grupo 2 | AQ75: Hidráulico | AR75: HI
B76: =+B75+1 -> 69 | C76: =+Q76 -> Maja Energía S.A.C. | D76: =+SUM(F76,H76,M76:N76) -> 1 | E76: =+SUM(G76,I76:L76) -> 2 | F76: =+IF(R76<>"",R76,"") -> 1 | G76: =+IF(Y76<>"",Y76,"") -> 2 | H76: =+IF(S76<>"",S76,"") | I76: =+IF(AA76<>"",AA76,"") | J76: =+IF(AB76<>"",AB76,"") | K76: =+IF(AC76<>"",AC76,"") | L76: =+IF(Z76<>"",Z76,"") | M76: =+IF(T76<>"",T76,"") | N76: =+IF(U76<>"",U76,"") | Q76: Maja Energía S.A.C. | R76: 1 | V76: 1 | X76: Maja Energía S.A.C. | Y76: 2 | AI76: Electro Sur Este S.A.A. | AJ76: Hidráulico | AK76: C.H. CHUMBAO | AN76: Electro Oriente S. A. | AO76: C.T. BAGUA GRANDE | AP76: Cat-1_3512 | AQ76: Térmico | AR76: EL
B77: =+B76+1 -> 70 | C77: =+Q77 -> Majes Arcus S.A.C. | D77: =+SUM(F77,H77,M77:N77) -> 1 | E77: - | F77: =+IF(R77<>"",R77,"") | G77: =+IF(Y77<>"",Y77,"") | H77: =+IF(S77<>"",S77,"") | I77: =+IF(AA77<>"",AA77,"") | J77: =+IF(AB77<>"",AB77,"") | K77: =+IF(AC77<>"",AC77,"") | L77: =+IF(Z77<>"",Z77,"") | M77: =+IF(T77<>"",T77,"") -> 1 | N77: =+IF(U77<>"",U77,"") | Q77: Majes Arcus S.A.C. | T77: 1 | V77: 1 | X77: Majes Arcus S.A.C. | AD77: 1 | AI77: Electro Sur Este S.A.A. | AJ77: Hidráulico | AK77: C.H. CHUYAPI | AN77: Electro Oriente S. A. | AO77: C.T. BAGUA GRANDE | AP77: Cat-2_3512 | AQ77: Térmico | AR77: EL
B78: =+B77+1 -> 71 | C78: =+Q78 -> Moquegua FV S.A.C. | D78: =+SUM(F78,H78,M78:N78) -> 1 | E78: - | F78: =+IF(R78<>"",R78,"") | G78: =+IF(Y78<>"",Y78,"") | H78: =+IF(S78<>"",S78,"") | I78: =+IF(AA78<>"",AA78,"") | J78: =+IF(AB78<>"",AB78,"") | K78: =+IF(AC78<>"",AC78,"") | L78: =+IF(Z78<>"",Z78,"") | M78: =+IF(T78<>"",T78,"") -> 1 | N78: =+IF(U78<>"",U78,"") | Q78: Moquegua FV S.A.C. | T78: 1 | V78: 1 | X78: Moquegua FV S.A.C. | AD78: 1 | AI78: Electro Sur Este S.A.A. | AJ78: Hidráulico | AK78: C.H. HERCCA | AN78: Electro Oriente S. A. | AO78: C.T. BAGUA GRANDE | AP78: DETROIT | AQ78: Térmico | AR78: EL
B79: =+B78+1 -> 72 | C79: =+Q79 -> Orazul Energy Perú S.A. | D79: =+SUM(F79,H79,M79:N79) -> 4 | E79: =+SUM(G79,I79:L79) -> 11 | F79: =+IF(R79<>"",R79,"") -> 4 | G79: =+IF(Y79<>"",Y79,"") -> 11 | H79: =+IF(S79<>"",S79,"") | I79: =+IF(AA79<>"",AA79,"") | J79: =+IF(AB79<>"",AB79,"") | K79: =+IF(AC79<>"",AC79,"") | L79: =+IF(Z79<>"",Z79,"") | M79: =+IF(T79<>"",T79,"") | N79: =+IF(U79<>"",U79,"") | Q79: Orazul Energy Perú S.A. | R79: 4 | V79: 4 | X79: Orazul Energy Perú S.A. | Y79: 11 | AI79: Electro Sur Este S.A.A. | AJ79: Hidráulico | AK79: C.H. HUANCARAY | AN79: Electro Oriente S. A. | AO79: C.T. BAGUA GRANDE | AP79: CAT3_3516 | AQ79: Térmico | AR79: EL
B80: =+B79+1 -> 73 | C80: =+Q80 -> Orygen Perú S.A.A. | D80: =+SUM(F80,H80,M80:N80) -> 12 | E80: =+SUM(G80,I80:L80) -> 27 | F80: =+IF(R80<>"",R80,"") -> 6 | G80: =+IF(Y80<>"",Y80,"") -> 17 | H80: =+IF(S80<>"",S80,"") -> 2 | I80: =+IF(AA80<>"",AA80,"") | J80: =+IF(AB80<>"",AB80,"") -> 9 | K80: =+IF(AC80<>"",AC80,"") -> 1 | L80: =+IF(Z80<>"",Z80,"") | M80: =+IF(T80<>"",T80,"") -> 2 | N80: =+IF(U80<>"",U80,"") -> 2 | Q80: Orygen Perú S.A.A. | R80: 6 | S80: 2 | T80: 2 | U80: 2 | V80: 12 | X80: Orygen Perú S.A.A. | Y80: 17 | AB80: 9 | AC80: 1 | AD80: 17 | AE80: 18 | AI80: Electro Sur Este S.A.A. | AJ80: Hidráulico | AK80: C.H. MANCAHUARA | AN80: Electro Oriente S. A. | AO80: C.T. BELLAVISTA | AP80: EMD | AQ80: Térmico | AR80: EL
B81: =+B80+1 -> 74 | C81: =+Q81 -> Panamericana Solar S.A.C. | D81: =+SUM(F81,H81,M81:N81) -> 1 | E81: - | F81: =+IF(R81<>"",R81,"") | G81: =+IF(Y81<>"",Y81,"") | H81: =+IF(S81<>"",S81,"") | I81: =+IF(AA81<>"",AA81,"") | J81: =+IF(AB81<>"",AB81,"") | K81: =+IF(AC81<>"",AC81,"") | L81: =+IF(Z81<>"",Z81,"") | M81: =+IF(T81<>"",T81,"") -> 1 | N81: =+IF(U81<>"",U81,"") | Q81: Panamericana Solar S.A.C. | T81: 1 | V81: 1 | X81: Panamericana Solar S.A.C. | AD81: 1 | AI81: Electro Sur Este S.A.A. | AJ81: Hidráulico | AK81: C.H. MATARÁ | AN81: Electro Oriente S. A. | AO81: C.T. CABALLOCOCHA | AP81: Cat 2. 3512 Dita | AQ81: Térmico | AR81: EL
B82: =+B81+1 -> 75 | C82: =+Q82 -> Parque Eolico Marcona S.A.C. | D82: =+SUM(F82,H82,M82:N82) -> 1 | E82: - | F82: =+IF(R82<>"",R82,"") | G82: =+IF(Y82<>"",Y82,"") | H82: =+IF(S82<>"",S82,"") | I82: =+IF(AA82<>"",AA82,"") | J82: =+IF(AB82<>"",AB82,"") | K82: =+IF(AC82<>"",AC82,"") | L82: =+IF(Z82<>"",Z82,"") | M82: =+IF(T82<>"",T82,"") | N82: =+IF(U82<>"",U82,"") -> 1 | Q82: Parque Eolico Marcona S.A.C. | U82: 1 | V82: 1 | X82: Parque Eolico Marcona S.A.C. | AE82: 1 | AI82: Electro Sur Este S.A.A. | AJ82: Hidráulico | AK82: C.H. VILCABAMBA | AN82: Electro Oriente S. A. | AO82: C.T. CABALLOCOCHA | AP82: Cat. 3512 Dito | AQ82: Térmico | AR82: EL
B83: =+B82+1 -> 76 | C83: =+Q83 -> Parque Eolico Tres Hermanas S.A.C. | D83: =+SUM(F83,H83,M83:N83) -> 1 | E83: - | F83: =+IF(R83<>"",R83,"") | G83: =+IF(Y83<>"",Y83,"") | H83: =+IF(S83<>"",S83,"") | I83: =+IF(AA83<>"",AA83,"") | J83: =+IF(AB83<>"",AB83,"") | K83: =+IF(AC83<>"",AC83,"") | L83: =+IF(Z83<>"",Z83,"") | M83: =+IF(T83<>"",T83,"") | N83: =+IF(U83<>"",U83,"") -> 1 | Q83: Parque Eolico Tres Hermanas S.A.C. | U83: 1 | V83: 1 | X83: Parque Eolico Tres Hermanas S.A.C. | AE83: 7 | AI83: Electro Sur Este S.A.A. | AJ83: Térmico | AK83: C.T. IBERIA | AN83: Electro Oriente S. A. | AO83: C.T. CABALLOCOCHA | AP83: Cat.4-3412-16878 | AQ83: Térmico | AR83: EL
B84: =+B83+1 -> 77 | C84: =+Q84 -> Peruana de Inversiones en Energía Renovables S.A. | D84: =+SUM(F84,H84,M84:N84) -> 1 | E84: =+SUM(G84,I84:L84) -> 2 | F84: =+IF(R84<>"",R84,"") -> 1 | G84: =+IF(Y84<>"",Y84,"") -> 2 | H84: =+IF(S84<>"",S84,"") | I84: =+IF(AA84<>"",AA84,"") | J84: =+IF(AB84<>"",AB84,"") | K84: =+IF(AC84<>"",AC84,"") | L84: =+IF(Z84<>"",Z84,"") | M84: =+IF(T84<>"",T84,"") | N84: =+IF(U84<>"",U84,"") | Q84: Peruana de Inversiones en Energía Renovables S.A. | R84: 1 | V84: 1 | X84: Peruana de Inversiones en Energía Renovables S.A. | Y84: 2 | AI84: Electro Sur Este S.A.A. | AJ84: Térmico | AK84: C.T. IÑAPARI | AN84: Electro Oriente S. A. | AO84: C.T. CABALLOCOCHA | AP84: Perkins 2500 | AQ84: Térmico | AR84: EL
B85: =+B84+1 -> 78 | C85: =+Q85 -> Petramas S.A.C. | D85: =+SUM(F85,H85,M85:N85) -> 4 | E85: =+SUM(G85,I85:L85) -> 9 | F85: =+IF(R85<>"",R85,"") | G85: =+IF(Y85<>"",Y85,"") | H85: =+IF(S85<>"",S85,"") -> 4 | I85: 9 | J85: =+IF(AB85<>"",AB85,"") | K85: =+IF(AC85<>"",AC85,"") | L85: =+IF(Z85<>"",Z85,"") | M85: =+IF(T85<>"",T85,"") | N85: =+IF(U85<>"",U85,"") | Q85: Petramas S.A.C. | S85: 4 | V85: 4 | X85: Petramas S.A.C. | AA85: 4 | AI85: Electro Sur Este S.A.A. | AJ85: Térmico | AK85: C.T. EMERGENCIA MOVIL | AN85: Electro Oriente S. A. | AO85: C.T. CABALLOCOCHA | AP85: Caterpillar C27 | AQ85: Térmico | AR85: EL
B86: =+B85+1 -> 79 | C86: =+Q86 -> Planta de Reserva Fría de Generación Éten S.A. | D86: =+SUM(F86,H86,M86:N86) -> 1 | E86: =+SUM(G86,I86:L86) -> 3 | F86: =+IF(R86<>"",R86,"") | G86: =+IF(Y86<>"",Y86,"") | H86: =+IF(S86<>"",S86,"") -> 1 | I86: =+IF(AA86<>"",AA86,"") -> 2 | J86: =+IF(AB86<>"",AB86,"") -> 1 | K86: =+IF(AC86<>"",AC86,"") | L86: =+IF(Z86<>"",Z86,"") | M86: =+IF(T86<>"",T86,"") | N86: =+IF(U86<>"",U86,"") | Q86: Planta de Reserva Fría de Generación Éten S.A. | S86: 1 | V86: 1 | X86: Planta de Reserva Fría de Generación Éten S.A. | AA86: 2 | AB86: 1 | AI86: Electro Ucayali S.A. | AJ86: Hidráulico | AK86: C.H. CANUJA | AN86: Electro Oriente S. A. | AO86: C.T. CABALLOCOCHA | AP86: AKSA1 Perk 8151G | AQ86: Térmico | AR86: EL
B87: =+B86+1 -> 80 | C87: =+Q87 -> Pluz Energía Perú S.A.A. | D87: =+SUM(F87,H87,M87:N87) -> 5 | E87: =+SUM(G87,I87:L87) -> 12 | F87: =+IF(R87<>"",R87,"") -> 4 | G87: =+IF(Y87<>"",Y87,"") -> 8 | H87: =+IF(S87<>"",S87,"") -> 1 | I87: =+IF(AA87<>"",AA87,"") -> 4 | J87: =+IF(AB87<>"",AB87,"") | K87: =+IF(AC87<>"",AC87,"") | L87: =+IF(Z87<>"",Z87,"") | M87: =+IF(T87<>"",T87,"") | N87: =+IF(U87<>"",U87,"") | Q87: Pluz Energía Perú S.A.A. | R87: 4 | S87: 1 | V87: 5 | X87: Pluz Energía Perú S.A.A. | Y87: 8 | AA87: 4 | AI87: Electro Ucayali S.A. | AJ87: Solar | AK87: C.S. PURUS | AN87: Electro Oriente S. A. | AO87: C.T. CABALLOCOCHA | AP87: AKSA2 Perk 8164G | AQ87: Térmico | AR87: EL
B88: =+B87+1 -> 81 | C88: =+Q88 -> Proyecto Especial Chavimochic | D88: =+SUM(F88,H88,M88:N88) -> 4 | E88: =+SUM(G88,I88:L88) -> 7 | F88: =+IF(R88<>"",R88,"") -> 3 | G88: =+IF(Y88<>"",Y88,"") -> 6 | H88: =+IF(S88<>"",S88,"") -> 1 | I88: =+IF(AA88<>"",AA88,"") -> 1 | J88: =+IF(AB88<>"",AB88,"") | K88: =+IF(AC88<>"",AC88,"") | L88: =+IF(Z88<>"",Z88,"") | M88: =+IF(T88<>"",T88,"") | N88: =+IF(U88<>"",U88,"") | Q88: Proyecto Especial Chavimochic | R88: 3 | S88: 1 | V88: 4 | X88: Proyecto Especial Chavimochic | Y88: 6 | AA88: 1 | AI88: Electro Ucayali S.A. | AJ88: Térmico | AK88: C.T. ATALAYA | AN88: Electro Oriente S. A. | AO88: C.T. CABALLOCOCHA | AP88: Perkins 1 2800 | AQ88: Térmico | AR88: EL
B89: =+B88+1 -> 82 | C89: =+Q89 -> Repartición Arcus S.A.C. | D89: =+SUM(F89,H89,M89:N89) -> 1 | E89: - | F89: =+IF(R89<>"",R89,"") | G89: =+IF(Y89<>"",Y89,"") | H89: =+IF(S89<>"",S89,"") | I89: =+IF(AA89<>"",AA89,"") | J89: =+IF(AB89<>"",AB89,"") | K89: =+IF(AC89<>"",AC89,"") | L89: =+IF(Z89<>"",Z89,"") | M89: =+IF(T89<>"",T89,"") -> 1 | N89: =+IF(U89<>"",U89,"") | Q89: Repartición Arcus S.A.C. | T89: 1 | V89: 1 | X89: Repartición Arcus S.A.C. | AD89: 1 | AI89: Electro Ucayali S.A. | AJ89: Térmico | AK89: C.T. PURUS | AN89: Electro Oriente S. A. | AO89: C.T. CABALLOCOCHA | AP89: Perkins 2 2800 | AQ89: Térmico | AR89: EL
B90: =+B89+1 -> 83 | C90: =+Q90 -> Samay I S.A. | D90: =+SUM(F90,H90,M90:N90) -> 1 | E90: =+SUM(G90,I90:L90) -> 4 | F90: =+IF(R90<>"",R90,"") | G90: =+IF(Y90<>"",Y90,"") | H90: =+IF(S90<>"",S90,"") -> 1 | I90: =+IF(AA90<>"",AA90,"") | J90: =+IF(AB90<>"",AB90,"") -> 4 | K90: =+IF(AC90<>"",AC90,"") | L90: =+IF(Z90<>"",Z90,"") | M90: =+IF(T90<>"",T90,"") | N90: =+IF(U90<>"",U90,"") | Q90: Samay I S.A. | S90: 1 | V90: 1 | X90: Samay I S.A. | AB90: 4 | AI90: Electro Zaña S.A.C. | AJ90: Hidráulico | AK90: C.H. ZAÑA | AN90: Electro Oriente S. A. | AO90: C.T. CONTAMANA | AP90: Cat.2.3512 Dita | AQ90: Térmico | AR90: EL
B91: =+B90+1 -> 84 | C91: =+Q91 -> SDF Energía S.A.C. | D91: =+SUM(F91,H91,M91:N91) -> 1 | E91: =+SUM(G91,I91:L91) -> 3 | F91: =+IF(R91<>"",R91,"") | G91: =+IF(Y91<>"",Y91,"") | H91: =+IF(S91<>"",S91,"") -> 1 | I91: =+IF(AA91<>"",AA91,"") | J91: =+IF(AB91<>"",AB91,"") -> 1 | K91: =+IF(AC91<>"",AC91,"") -> 2 | L91: =+IF(Z91<>"",Z91,"") | M91: =+IF(T91<>"",T91,"") | N91: =+IF(U91<>"",U91,"") | Q91: SDF Energía S.A.C. | S91: 1 | V91: 1 | X91: SDF Energía S.A.C. | AB91: 1 | AC91: 2 | AI91: Electrocentro S.A. | AJ91: Hidráulico | AK91: C.H. ACOBAMBA | AN91: Electro Oriente S. A. | AO91: C.T. CONTAMANA | AP91: Cat.3512 Dita | AQ91: Térmico | AR91: EL
B92: =+B91+1 -> 85 | C92: =+Q92 -> Shougang Generación Eléctrica S.A.A. | D92: =+SUM(F92,H92,M92:N92) -> 1 | E92: =+SUM(G92,I92:L92) -> 4 | F92: =+IF(R92<>"",R92,"") | G92: =+IF(Y92<>"",Y92,"") | H92: =+IF(S92<>"",S92,"") -> 1 | I92: =+IF(AA92<>"",AA92,"") -> 1 | J92: =+IF(AB92<>"",AB92,"") | K92: =+IF(AC92<>"",AC92,"") -> 3 | L92: =+IF(Z92<>"",Z92,"") | M92: =+IF(T92<>"",T92,"") | N92: =+IF(U92<>"",U92,"") | Q92: Shougang Generación Eléctrica S.A.A. | S92: 1 | V92: 1 | X92: Shougang Generación Eléctrica S.A.A. | AA92: 1 | AC92: 3 | AI92: Electrocentro S.A. | AJ92: Hidráulico | AK92: C.H. CHALHUAMAYO | AN92: Electro Oriente S. A. | AO92: C.T. CONTAMANA | AP92: Cat.5-C15-07183 | AQ92: Térmico | AR92: EL
B93: =+B92+1 -> 86 | C93: =+Q93 -> Sindicato Energético S.A. | D93: =+SUM(F93,H93,M93:N93) -> 4 | E93: =+SUM(G93,I93:L93) -> 8 | F93: =+IF(R93<>"",R93,"") -> 4 | G93: =+IF(Y93<>"",Y93,"") -> 8 | H93: =+IF(S93<>"",S93,"") | I93: =+IF(AA93<>"",AA93,"") | J93: =+IF(AB93<>"",AB93,"") | K93: =+IF(AC93<>"",AC93,"") | L93: =+IF(Z93<>"",Z93,"") | M93: =+IF(T93<>"",T93,"") | N93: =+IF(U93<>"",U93,"") | Q93: Sindicato Energético S.A. | R93: 4 | V93: 4 | X93: Sindicato Energético S.A. | Y93: 8 | AI93: Electrocentro S.A. | AJ93: Hidráulico | AK93: C.H. CHAMISERIA | AN93: Electro Oriente S. A. | AO93: C.T. CONTAMANA | AP93: Mitsubishi | AQ93: Térmico | AR93: EL
B94: =+B93+1 -> 87 | C94: =+Q94 -> Sociedad Eléctrica del Sur Oeste S.A. | D94: =+SUM(F94,H94,M94:N94) -> 11 | E94: =+SUM(G94,I94:L94) -> 32 | F94: =+IF(R94<>"",R94,"") -> 6 | G94: =+IF(Y94<>"",Y94,"") -> 11 | H94: =+IF(S94<>"",S94,"") -> 5 | I94: =+IF(AA94<>"",AA94,"") -> 21 | J94: =+IF(AB94<>"",AB94,"") | K94: =+IF(AC94<>"",AC94,"") | L94: =+IF(Z94<>"",Z94,"") | M94: =+IF(T94<>"",T94,"") | N94: =+IF(U94<>"",U94,"") | Q94: Sociedad Eléctrica del Sur Oeste S.A. | R94: 6 | S94: 5 | V94: 11 | X94: Sociedad Eléctrica del Sur Oeste S.A. | Y94: 11 | AA94: 21 | AI94: Electrocentro S.A. | AJ94: Hidráulico | AK94: C.H. CHANCHAMAYO | AN94: Electro Oriente S. A. | AO94: C.T. CONTAMANA | AP94: Cat.6 3516B 0141 | AQ94: Térmico | AR94: EL
B95: =+B94+1 -> 88 | C95: =+Q95 -> Sociedad Minera Cerro Verde S.A.A. | D95: =+SUM(F95,H95,M95:N95) -> 2 | E95: =+SUM(G95,I95:L95) -> 9 | F95: =+IF(R95<>"",R95,"") | G95: =+IF(Y95<>"",Y95,"") | H95: =+IF(S95<>"",S95,"") -> 2 | I95: =+IF(AA95<>"",AA95,"") -> 7 | J95: =+IF(AB95<>"",AB95,"") -> 2 | K95: =+IF(AC95<>"",AC95,"") | L95: =+IF(Z95<>"",Z95,"") | M95: =+IF(T95<>"",T95,"") | N95: =+IF(U95<>"",U95,"") | Q95: Sociedad Minera Cerro Verde S.A.A. | S95: 2 | V95: 2 | X95: Sociedad Minera Cerro Verde S.A.A. | AA95: 7 | AB95: 2 | AI95: Electrocentro S.A. | AJ95: Hidráulico | AK95: C.H. CONCEPCION | AN95: Electro Oriente S. A. | AO95: C.T. CONTAMANA | AP95: Cat83516BJYA00139 | AQ95: Térmico | AR95: EL
B96: =+B95+1 -> 89 | C96: =+Q96 -> Statkraft Perú S.A. | D96: =+SUM(F96,H96,M96:N96) -> 12 | E96: =+SUM(G96,I96:L96) -> 31 | F96: =+IF(R96<>"",R96,"") -> 12 | G96: =+IF(Y96<>"",Y96,"") -> 31 | H96: =+IF(S96<>"",S96,"") | I96: =+IF(AA96<>"",AA96,"") | J96: =+IF(AB96<>"",AB96,"") | K96: =+IF(AC96<>"",AC96,"") | L96: =+IF(Z96<>"",Z96,"") | M96: =+IF(T96<>"",T96,"") | N96: =+IF(U96<>"",U96,"") | Q96: Statkraft Perú S.A. | R96: 12 | V96: 12 | X96: Statkraft Perú S.A. | Y96: 31 | AI96: Electrocentro S.A. | AJ96: Hidráulico | AK96: C.H. INGENIO | AN96: Electro Oriente S. A. | AO96: C.T. CONTAMANA | AP96: Cat 09 3516 | AQ96: Térmico | AR96: EL
B97: =+B96+1 -> 90 | C97: =+Q97 -> Tacna Solar S.A.C. | D97: =+SUM(F97,H97,M97:N97) -> 1 | E97: - | F97: =+IF(R97<>"",R97,"") | G97: =+IF(Y97<>"",Y97,"") | H97: =+IF(S97<>"",S97,"") | I97: =+IF(AA97<>"",AA97,"") | J97: =+IF(AB97<>"",AB97,"") | K97: =+IF(AC97<>"",AC97,"") | L97: =+IF(Z97<>"",Z97,"") | M97: =+IF(T97<>"",T97,"") -> 1 | N97: =+IF(U97<>"",U97,"") | Q97: Tacna Solar S.A.C. | T97: 1 | V97: 1 | X97: Tacna Solar S.A.C. | AD97: 1 | AI97: Electrocentro S.A. | AJ97: Hidráulico | AK97: C.H. LLUSITA | AN97: Electro Oriente S. A. | AO97: C.T. EL ESTRECHO | AP97: Cat-1 3406 | AQ97: Térmico | AR97: EL
B98: =+B97+1 -> 91 | C98: =+Q98 -> Termochilca S.A. | D98: =+SUM(F98,H98,M98:N98) -> 1 | E98: =+SUM(G98,I98:L98) -> 1 | F98: =+IF(R98<>"",R98,"") | G98: =+IF(Y98<>"",Y98,"") | H98: =+IF(S98<>"",S98,"") -> 1 | I98: =+IF(AA98<>"",AA98,"") | J98: =+IF(AB98<>"",AB98,"") | K98: =+IF(AC98<>"",AC98,"") | L98: =+IF(Z98<>"",Z98,"") -> 1 | M98: =+IF(T98<>"",T98,"") | N98: =+IF(U98<>"",U98,"") | Q98: Termochilca S.A. | S98: 1 | V98: 1 | X98: Termochilca S.A. | Z98: 1 | AI98: Electrocentro S.A. | AJ98: Hidráulico | AK98: C.H. MACHU | AN98: Electro Oriente S. A. | AO98: C.T. EL ESTRECHO | AP98: Cat-2 3306 | AQ98: Térmico | AR98: EL
B99: =+B98+1 -> 92 | C99: =+Q99 -> Termoselva S.R.L. | D99: =+SUM(F99,H99,M99:N99) -> 1 | E99: =+SUM(G99,I99:L99) -> 2 | F99: =+IF(R99<>"",R99,"") | G99: =+IF(Y99<>"",Y99,"") | H99: =+IF(S99<>"",S99,"") -> 1 | I99: =+IF(AA99<>"",AA99,"") | J99: =+IF(AB99<>"",AB99,"") -> 2 | K99: =+IF(AC99<>"",AC99,"") | L99: =+IF(Z99<>"",Z99,"") | M99: =+IF(T99<>"",T99,"") | N99: =+IF(U99<>"",U99,"") | Q99: Termoselva S.R.L. | S99: 1 | V99: 1 | X99: Termoselva S.R.L. | AB99: 2 | AI99: Electrocentro S.A. | AJ99: Hidráulico | AK99: C.H. PACCHA | AN99: Electro Oriente S. A. | AO99: C.T. EL ESTRECHO | AP99: Volvo 03 | AQ99: Térmico | AR99: EL
B100: TOTAL MERCADO ELÉCTRICO | D100: =SUM(D8:D99) -> 293 | E100: =SUM(E8:E99) -> 713 | F100: =SUM(F8:F99) -> 166 | G100: =SUM(G8:G99) -> 358 | H100: =SUM(H8:H99) -> 97 | I100: =SUM(I8:I99) -> 286 | J100: =SUM(J8:J99) -> 46 | K100: =SUM(K8:K99) -> 18 | ... N100: =SUM(N8:N99) -> 12 | Q100: Total general | R100: 166 | S100: 98 | T100: 18 | U100: 12 | V100: 294 | X100: Total general | Y100: 355 | Z100: 5 | AA100: 236 | AB100: 47 | AC100: 20 | AD100: 50 | AE100: 60 | AI100: Electrocentro S.A. | AJ100: Hidráulico | AK100: C.H. PICHANAKI | AN100: Electro Oriente S. A. | AO100: C.T. EL ESTRECHO | AP100: Volvo 350 | AQ100: Térmico | AR100: EL
...

Sheet 3.2.1.2
A1: 3.2.1.2. Para uso propio (*) | U1: Informa A | V1: Informante
U2: Tipo de Mercado A | V2: Uso Propio
B3: N° | D3: Número | E3: Hidráulicas | F3: Térmicas | U3: Variable | V3: Energía
C4: Principales empresas | D4: total de | E4: Nº de | F4: Nº de centrales | N4: Cuenta de Central Anuario | O4: Etiquetas de columna | U4: FILTRO | V4: (en blanco)
D5: centrales | E5: centrales | F5: EL | G5: TG | H5: TV | J5: Etiquetas de fila | K5: Cuenta de Central Anuario | N5: Etiquetas de fila | O5: HI | P5: EL | Q5: TG | R5: TV | S5: Total general
B6: 1 | C6: =+J6 -> Agroindustrial Laredo S.A.A. | D6: =+K6 -> 6 | E6: =+IF(O6<>"",O6,"") | F6: =+IF(P6<>"",P6,"") | G6: =+IF(Q6<>"",Q6,"") | H6: =+IF(R6<>"",R6,"") -> 6 | J6: Agroindustrial Laredo S.A.A. | K6: 6 | N6: Agroindustrial Laredo S.A.A. | R6: 6 | S6: 6 | U6: Empresa Anuario | V6: Central Anuario | W6: CTIPGRU
B7: =+B6+1 -> 2 | C7: =+J7 -> Agrolmos S.A. | D7: =+K7 -> 1 | E7: =+IF(O7<>"",O7,"") | F7: =+IF(P7<>"",P7,"") | G7: =+IF(Q7<>"",Q7,"") | H7: =+IF(R7<>"",R7,"") -> 1 | J7: Agrolmos S.A. | K7: 1 | N7: Agrolmos S.A. | R7: 1 | S7: 1 | U7: Agroindustrial Laredo S.A.A. | V7: C.T. TURBO GENERADOR 1 | W7: TV
B8: =+B7+1 -> 3 | C8: =+J8 -> Aguaytia Energy del Peru S.R.L. | D8: =+K8 -> 1 | E8: =+IF(O8<>"",O8,"") | F8: =+IF(P8<>"",P8,"") | G8: =+IF(Q8<>"",Q8,"") -> 1 | H8: =+IF(R8<>"",R8,"") | J8: Aguaytia Energy del Peru S.R.L. | K8: 1 | N8: Aguaytia Energy del Peru S.R.L. | Q8: 1 | S8: 1 | U8: Agroindustrial Laredo S.A.A. | V8: C.T. TURBO GENERADOR 2 | W8: TV
B9: =+B8+1 -> 4 | C9: =+J9 -> Ajeper S.A. | D9: =+K9 -> 1 | E9: =+IF(O9<>"",O9,"") | F9: =+IF(P9<>"",P9,"") -> 1 | G9: =+IF(Q9<>"",Q9,"") | H9: =+IF(R9<>"",R9,"") | J9: Ajeper S.A. | K9: 1 | N9: Ajeper S.A. | P9: 1 | S9: 1 | U9: Agroindustrial Laredo S.A.A. | V9: C.T. TURBO GENERADOR 3 | W9: TV
B10: =+B9+1 -> 5 | C10: =+J10 -> Ajinomoto del Peru S.A. | D10: =+K10 -> 1 | E10: =+IF(O10<>"",O10,"") | F10: =+IF(P10<>"",P10,"") -> 1 | G10: =+IF(Q10<>"",Q10,"") | H10: =+IF(R10<>"",R10,"") | J10: Ajinomoto del Peru S.A. | K10: 1 | N10: Ajinomoto del Peru S.A. | P10: 1 | S10: 1 | U10: Agroindustrial Laredo S.A.A. | V10: C.T. TURBO GENERADOR 4 | W10: TV
B11: =+B10+1 -> 6 | C11: =+J11 -> Alicorp S.A.A. | D11: =+K11 -> 6 | E11: =+IF(O11<>"",O11,"") | F11: =+IF(P11<>"",P11,"") -> 6 | G11: =+IF(Q11<>"",Q11,"") | H11: =+IF(R11<>"",R11,"") | J11: Alicorp S.A.A. | K11: 6 | N11: Alicorp S.A.A. | P11: 6 | S11: 6 | U11: Agroindustrial Laredo S.A.A. | V11: C.T. TURBO GENERADOR 5 | W11: TV
B12: =+B11+1 -> 7 | C12: =+J12 -> Anabi S.A.C. | D12: =+K12 -> 2 | E12: =+IF(O12<>"",O12,"") | F12: =+IF(P12<>"",P12,"") -> 2 | G12: =+IF(Q12<>"",Q12,"") | H12: =+IF(R12<>"",R12,"") | J12: Anabi S.A.C. | K12: 2 | N12: Anabi S.A.C. | P12: 2 | S12: 2 | U12: Agroindustrial Laredo S.A.A. | V12: C.T. UNIDAD DIESEL | W12: TV
B13: =+B12+1 -> 8 | C13: =+J13 -> Anglo American Quellaveco S.A. | D13: =+K13 -> 4 | E13: =+IF(O13<>"",O13,"") | F13: =+IF(P13<>"",P13,"") -> 4 | G13: =+IF(Q13<>"",Q13,"") | H13: =+IF(R13<>"",R13,"") | J13: Anglo American Quellaveco S.A. | K13: 4 | N13: Anglo American Quellaveco S.A. | P13: 4 | S13: 4 | U13: Agrolmos S.A. | V13: C.T. AGROLMOS | W13: TV
B14: =+B13+1 -> 9 | C14: =+J14 -> APM Terminals Callao S.A. | D14: =+K14 -> 1 | E14: =+IF(O14<>"",O14,"") | F14: =+IF(P14<>"",P14,"") -> 1 | G14: =+IF(Q14<>"",Q14,"") | H14: =+IF(R14<>"",R14,"") | J14: APM Terminals Callao S.A. | K14: 1 | N14: APM Terminals Callao S.A. | P14: 1 | S14: 1 | U14: Aguaytia Energy del Peru S.R.L. | V14: C.T. GAS | W14: TG
B15: =+B14+1 -> 10 | C15: =+J15 -> Apumayo S.A.C. | D15: =+K15 -> 1 | E15: =+IF(O15<>"",O15,"") | F15: =+IF(P15<>"",P15,"") -> 1 | G15: =+IF(Q15<>"",Q15,"") | H15: =+IF(R15<>"",R15,"") | J15: Apumayo S.A.C. | K15: 1 | N15: Apumayo S.A.C. | P15: 1 | S15: 1 | U15: Ajeper S.A. | V15: C.T. AJE | W15: EL
B16: =+B15+1 -> 11 | C16: =+J16 -> Aris Indsutrial S.A. | D16: =+K16 -> 2 | E16: =+IF(O16<>"",O16,"") | F16: =+IF(P16<>"",P16,"") -> 2 | G16: =+IF(Q16<>"",Q16,"") | H16: =+IF(R16<>"",R16,"") | J16: Aris Indsutrial S.A. | K16: 2 | N16: Aris Indsutrial S.A. | P16: 2 | S16: 2 | U16: Ajinomoto del Peru S.A. | V16: C.T. AJINOMOTO | W16: EL
B17: =+B16+1 -> 12 | C17: =+J17 -> Aruntani S.A.C. | D17: =+K17 -> 2 | E17: =+IF(O17<>"",O17,"") | F17: =+IF(P17<>"",P17,"") -> 2 | G17: =+IF(Q17<>"",Q17,"") | H17: =+IF(R17<>"",R17,"") | J17: Aruntani S.A.C. | K17: 2 | N17: Aruntani S.A.C. | P17: 2 | S17: 2 | U17: Alicorp S.A.A. | V17: C.T. AREQUIPA | W17: EL
B18: =+B17+1 -> 13 | C18: =+J18 -> Austral Group S.A.A | D18: =+K18 -> 2 | E18: =+IF(O18<>"",O18,"") | F18: =+IF(P18<>"",P18,"") -> 2 | G18: =+IF(Q18<>"",Q18,"") | H18: =+IF(R18<>"",R18,"") | J18: Austral Group S.A.A | K18: 2 | N18: Austral Group S.A.A | P18: 2 | S18: 2 | U18: Alicorp S.A.A. | V18: C.T. FIDEERIA LIMA | W18: EL
B19: =+B18+1 -> 14 | C19: =+J19 -> Cálidda Energía S.A.C. | D19: =+K19 -> 1 | E19: =+IF(O19<>"",O19,"") | F19: =+IF(P19<>"",P19,"") -> 1 | G19: =+IF(Q19<>"",Q19,"") | H19: =+IF(R19<>"",R19,"") | J19: Cálidda Energía S.A.C. | K19: 1 | N19: Cálidda Energía S.A.C. | P19: 1 | S19: 1 | U19: Alicorp S.A.A. | V19: C.T. MOLINOS CALLAO | W19: EL
B20: =+B19+1 -> 15 | C20: =+J20 -> Cartavio S.A.A. | D20: =+K20 -> 1 | E20: =+IF(O20<>"",O20,"") | F20: =+IF(P20<>"",P20,"") | G20: =+IF(Q20<>"",Q20,"") | H20: =+IF(R20<>"",R20,"") -> 1 | J20: Cartavio S.A.A. | K20: 1 | N20: Cartavio S.A.A. | R20: 1 | S20: 1 | U20: Alicorp S.A.A. | V20: C.T. MOLINOS SANTA ROSA | W20: EL
B21: =+B20+1 -> 16 | C21: =+J21 -> Casa Grande S.A.A. | D21: =+K21 -> 1 | E21: =+IF(O21<>"",O21,"") | F21: =+IF(P21<>"",P21,"") | G21: =+IF(Q21<>"",Q21,"") | H21: =+IF(R21<>"",R21,"") -> 1 | J21: Casa Grande S.A.A. | K21: 1 | N21: Casa Grande S.A.A. | R21: 1 | S21: 1 | U21: Alicorp S.A.A. | V21: C.T. NICOVITA TRUJILLO | W21: EL
B22: =+B21+1 -> 17 | C22: =+J22 -> Cementos Pacasmayo S.A.A. | D22: =+K22 -> 1 | E22: =+IF(O22<>"",O22,"") | F22: =+IF(P22<>"",P22,"") | G22: =+IF(Q22<>"",Q22,"") | H22: =+IF(R22<>"",R22,"") -> 1 | J22: Cementos Pacasmayo S.A.A. | K22: 1 | N22: Cementos Pacasmayo S.A.A. | R22: 1 | S22: 1 | U22: Alicorp S.A.A. | V22: C.T. OLEAGINOSA CALLAO | W22: EL
B23: =+B22+1 -> 18 | C23: =+J23 -> Cementos Selva S.A. | D23: =+K23 -> 1 | E23: =+IF(O23<>"",O23,"") | F23: =+IF(P23<>"",P23,"") -> 1 | G23: =+IF(Q23<>"",Q23,"") | H23: =+IF(R23<>"",R23,"") | J23: Cementos Selva S.A. | K23: 1 | N23: Cementos Selva S.A. | P23: 1 | S23: 1 | U23: Anabi S.A.C. | V23: C.T. ANABI | W23: EL
B24: =+B23+1 -> 19 | C24: =+J24 -> Cerámica Lima S.A. | D24: =+K24 -> 2 | E24: =+IF(O24<>"",O24,"") | F24: =+IF(P24<>"",P24,"") -> 2 | G24: =+IF(Q24<>"",Q24,"") | H24: =+IF(R24<>"",R24,"") | J24: Cerámica Lima S.A. | K24: 2 | N24: Cerámica Lima S.A. | P24: 2 | S24: 2 | U24: Anabi S.A.C. | V24: C.T. ANAMA | W24: EL
B25: =+B24+1 -> 20 | C25: =+J25 -> Cervecería San Juan S.A. | D25: =+K25 -> 1 | E25: =+IF(O25<>"",O25,"") | F25: =+IF(P25<>"",P25,"") -> 1 | G25: =+IF(Q25<>"",Q25,"") | H25: =+IF(R25<>"",R25,"") | J25: Cervecería San Juan S.A. | K25: 1 | N25: Cervecería San Juan S.A. | P25: 1 | S25: 1 | U25: Anglo American Quellaveco S.A. | V25: C.T. CORTADERA | W25: EL
B26: =+B25+1 -> 21 | C26: =+J26 -> Cia Minera Agregados Calcáreos S.A. | D26: =+K26 -> 1 | E26: =+IF(O26<>"",O26,"") | F26: =+IF(P26<>"",P26,"") -> 1 | G26: =+IF(Q26<>"",Q26,"") | H26: =+IF(R26<>"",R26,"") | J26: Cia Minera Agregados Calcáreos S.A. | K26: 1 | N26: Cia Minera Agregados Calcáreos S.A. | P26: 1 | S26: 1 | U26: Anglo American Quellaveco S.A. | V26: C.T. SALVIANI | W26: EL
B27: =+B26+1 -> 22 | C27: =+J27 -> Cia Minera Poderosa S.A. | D27: =+K27 -> 3 | E27: =+IF(O27<>"",O27,"") -> 1 | F27: =+IF(P27<>"",P27,"") -> 2 | G27: =+IF(Q27<>"",Q27,"") | H27: =+IF(R27<>"",R27,"") | J27: Cia Minera Poderosa S.A. | K27: 3 | N27: Cia Minera Poderosa S.A. | O27: 1 | P27: 2 | S27: 3 | U27: Anglo American Quellaveco S.A. | V27: C.T. DRENAJE SECTOR MINA | W27: EL
B28: =+B27+1 -> 23 | C28: =+J28 -> Cia Minera Raura S.A. | D28: =+K28 -> 1 | E28: =+IF(O28<>"",O28,"") -> 1 | F28: =+IF(P28<>"",P28,"") | G28: =+IF(Q28<>"",Q28,"") | H28: =+IF(R28<>"",R28,"") | J28: Cia Minera Raura S.A. | K28: 1 | N28: Cia Minera Raura S.A. | O28: 1 | S28: 1 | U28: Anglo American Quellaveco S.A. | V28: C.T. PLANTA PAPUJUNE | W28: EL
B29: =+B28+1 -> 24 | C29: =+J29 -> Cia Minera Santa Luisa S.A. | D29: =+K29 -> 5 | E29: =+IF(O29<>"",O29,"") -> 2 | F29: =+IF(P29<>"",P29,"") -> 3 | G29: =+IF(Q29<>"",Q29,"") | H29: =+IF(R29<>"",R29,"") | J29: Cia Minera Santa Luisa S.A. | K29: 5 | N29: Cia Minera Santa Luisa S.A. | O29: 2 | P29: 3 | S29: 5 | U29: APM Terminals Callao S.A. | V29: C.T. PUERTO CALLAO | W29: EL
B30: =+B29+1 -> 25 | C30: =+J30 -> CNPC Perú S.A. | D30: =+K30 -> 1 | E30: =+IF(O30<>"",O30,"") | F30: =+IF(P30<>"",P30,"") -> 1 | G30: =+IF(Q30<>"",Q30,"") | H30: =+IF(R30<>"",R30,"") | J30: CNPC Perú S.A. | K30: 1 | N30: CNPC Perú S.A. | P30: 1 | S30: 1 | U30: Apumayo S.A.C. | V30: C.T. APUMAYO | W30: EL
B31: =+B30+1 -> 26 | C31: =+J31 -> Compañía Minera Antapaccay S.A. | D31: =+K31 -> 1 | E31: =+IF(O31<>"",O31,"") | F31: =+IF(P31<>"",P31,"") -> 1 | G31: =+IF(Q31<>"",Q31,"") | H31: =+IF(R31<>"",R31,"") | J31: Compañía Minera Antapaccay S.A. | K31: 1 | N31: Compañía Minera Antapaccay S.A. | P31: 1 | S31: 1 | U31: Aris Indsutrial S.A. | V31: C.T. ARIS LIMA | W31: EL
B32: =+B31+1 -> 27 | C32: =+J32 -> Compañía Minera Ares S.A.C. | D32: =+K32 -> 6 | E32: =+IF(O32<>"",O32,"") | F32: =+IF(P32<>"",P32,"") -> 6 | G32: =+IF(Q32<>"",Q32,"") | H32: =+IF(R32<>"",R32,"") | J32: Compañía Minera Ares S.A.C. | K32: 6 | N32: Compañía Minera Ares S.A.C. | P32: 6 | S32: 6 | U32: Aris Indsutrial S.A. | V32: C.T. ARIS LURIN | W32: EL
B33: =+B32+1 -> 28 | C33: =+J33 -> Compañía Minera Caraveli S.A.C. | D33: =+K33 -> 2 | E33: =+IF(O33<>"",O33,"") | F33: =+IF(P33<>"",P33,"") -> 2 | G33: =+IF(Q33<>"",Q33,"") | H33: =+IF(R33<>"",R33,"") | J33: Compañía Minera Caraveli S.A.C. | K33: 2 | N33: Compañía Minera Caraveli S.A.C. | P33: 2 | S33: 2 | U33: Aruntani S.A.C. | V33: C.T. JESICA | W33: EL
B34: =+B33+1 -> 29 | C34: =+J34 -> Compañía Minera Chungar S.A.C. | D34: =+K34 -> 14 | E34: =+IF(O34<>"",O34,"") -> 11 | F34: =+IF(P34<>"",P34,"") -> 3 | G34: =+IF(Q34<>"",Q34,"") | H34: =+IF(R34<>"",R34,"") | J34: Compañía Minera Chungar S.A.C. | K34: 14 | N34: Compañía Minera Chungar S.A.C. | O34: 11 | P34: 3 | S34: 14 | U34: Aruntani S.A.C. | V34: C.T. TUCARI | W34: EL
B35: =+B34+1 -> 30 | C35: =+J35 -> Compañia Minera Kolpa S.A. | D35: =+K35 -> 1 | E35: =+IF(O35<>"",O35,"") | F35: =+IF(P35<>"",P35,"") -> 1 | G35: =+IF(Q35<>"",Q35,"") | H35: =+IF(R35<>"",R35,"") | J35: Compañia Minera Kolpa S.A. | K35: 1 | N35: Compañia Minera Kolpa S.A. | P35: 1 | S35: 1 | U35: Austral Group S.A.A | V35: C.T. PLANTA CHANCAY | W35: EL
B36: =+B35+1 -> 31 | C36: =+J36 -> Compañía Minera San Ignacio de Morococha S.A.A. | D36: =+K36 -> 2 | E36: =+IF(O36<>"",O36,"") -> 1 | F36: =+IF(P36<>"",P36,"") -> 1 | G36: =+IF(Q36<>"",Q36,"") | H36: =+IF(R36<>"",R36,"") | J36: Compañía Minera San Ignacio de Morococha S.A.A. | K36: 2 | N36: Compañía Minera San Ignacio de Morococha S.A.A. | O36: 1 | P36: 1 | S36: 2 | U36: Austral Group S.A.A | V36: C.T. PLANTA PISCO | W36: EL
B37: =+B36+1 -> 32 | C37: =+J37 -> Compañía Minera San Valentin S.A. | D37: =+K37 -> 1 | E37: =+IF(O37<>"",O37,"") -> 1 | F37: =+IF(P37<>"",P37,"") | G37: =+IF(Q37<>"",Q37,"") | H37: =+IF(R37<>"",R37,"") | J37: Compañía Minera San Valentin S.A. | K37: 1 | N37: Compañía Minera San Valentin S.A. | O37: 1 | S37: 1 | U37: Cálidda Energía S.A.C. | V37: C.T. PURUCHUCO | W37: EL
B38: =+B37+1 -> 33 | C38: =+J38 -> Compañía Pesquera del Pacifico Centro S.A. | D38: =+K38 -> 1 | E38: =+IF(O38<>"",O38,"") | F38: =+IF(P38<>"",P38,"") -> 1 | G38: =+IF(Q38<>"",Q38,"") | H38: =+IF(R38<>"",R38,"") | J38: Compañía Pesquera del Pacifico Centro S.A. | K38: 1 | N38: Compañía Pesquera del Pacifico Centro S.A. | P38: 1 | S38: 1 | U38: Cartavio S.A.A. | V38: C.T. CARTAVIO | W38: TV
B39: =+B38+1 -> 34 | C39: =+J39 -> Compañia Quimica S.A. | D39: =+K39 -> 1 | E39: =+IF(O39<>"",O39,"") | F39: =+IF(P39<>"",P39,"") -> 1 | G39: =+IF(Q39<>"",Q39,"") | H39: =+IF(R39<>"",R39,"") | J39: Compañia Quimica S.A. | K39: 1 | N39: Compañia Quimica S.A. | P39: 1 | S39: 1 | U39: Casa Grande S.A.A. | V39: C.T. CASA GRANDE | W39: TV
B40: =+B39+1 -> 35 | C40: =+J40 -> Consorcio Minero Horizonte S.A. | D40: =+K40 -> 2 | E40: =+IF(O40<>"",O40,"") -> 1 | F40: =+IF(P40<>"",P40,"") -> 1 | G40: =+IF(Q40<>"",Q40,"") | H40: =+IF(R40<>"",R40,"") | J40: Consorcio Minero Horizonte S.A. | K40: 2 | N40: Consorcio Minero Horizonte S.A. | O40: 1 | P40: 1 | S40: 2 | U40: Cementos Pacasmayo S.A.A. | V40: C.T. PACASMAYO | W40: TV
B41: =+B40+1 -> 36 | C41: =+J41 -> Corporación Aceros Arequipa S.A. | D41: =+K41 -> 1 | E41: =+IF(O41<>"",O41,"") | F41: =+IF(P41<>"",P41,"") -> 1 | G41: =+IF(Q41<>"",Q41,"") | H41: =+IF(R41<>"",R41,"") | J41: Corporación Aceros Arequipa S.A. | K41: 1 | N41: Corporación Aceros Arequipa S.A. | P41: 1 | S41: 1 | U41: Cementos Selva S.A. | V41: C.T. CEMENTOS RIOJA | W41: EL
B42: =+B41+1 -> 37 | C42: =+J42 -> Corporación Pesquera Inca S.A.C. | D42: =+K42 -> 2 | E42: =+IF(O42<>"",O42,"") | F42: =+IF(P42<>"",P42,"") -> 2 | G42: =+IF(Q42<>"",Q42,"") | H42: =+IF(R42<>"",R42,"") | J42: Corporación Pesquera Inca S.A.C. | K42: 2 | N42: Corporación Pesquera Inca S.A.C. | P42: 2 | S42: 2 | U42: Cerámica Lima S.A. | V42: C.T. CELIMA 01 | W42: EL
B43: =+B42+1 -> 38 | C43: =+J43 -> Empresa Agroindustrial Pomalca S.A.A. | D43: =+K43 -> 2 | E43: =+IF(O43<>"",O43,"") | F43: =+IF(P43<>"",P43,"") -> 1 | G43: =+IF(Q43<>"",Q43,"") | H43: =+IF(R43<>"",R43,"") -> 1 | J43: Empresa Agroindustrial Pomalca S.A.A. | K43: 2 | N43: Empresa Agroindustrial Pomalca S.A.A. | P43: 1 | R43: 1 | S43: 2 | U43: Cerámica Lima S.A. | V43: C.T. CELIMA 02 | W43: EL
B44: =+B43+1 -> 39 | C44: =+J44 -> Empresa Explotadora de Vinchos Ltda S.A.C. | D44: =+K44 -> 1 | E44: =+IF(O44<>"",O44,"") | F44: =+IF(P44<>"",P44,"") -> 1 | G44: =+IF(Q44<>"",Q44,"") | H44: =+IF(R44<>"",R44,"") | J44: Empresa Explotadora de Vinchos Ltda S.A.C. | K44: 1 | N44: Empresa Explotadora de Vinchos Ltda S.A.C. | P44: 1 | S44: 1 | U44: Cervecería San Juan S.A. | V44: C.T. SAN JUAN | W44: EL
B45: =+B44+1 -> 40 | C45: =+J45 -> Empresa Minera los Quenuales S.A. | D45: =+K45 -> 3 | E45: =+IF(O45<>"",O45,"") -> 1 | F45: =+IF(P45<>"",P45,"") -> 2 | G45: =+IF(Q45<>"",Q45,"") | H45: =+IF(R45<>"",R45,"") | J45: Empresa Minera los Quenuales S.A. | K45: 3 | N45: Empresa Minera los Quenuales S.A. | O45: 1 | P45: 2 | S45: 3 | U45: Cia Minera Agregados Calcáreos S.A. | V45: C.T. CALCAREOS | W45: EL
B46: =+B45+1 -> 41 | C46: =+J46 -> Flesan Indutrial Power S.A.C | D46: =+K46 -> 1 | E46: =+IF(O46<>"",O46,"") | F46: =+IF(P46<>"",P46,"") -> 1 | G46: =+IF(Q46<>"",Q46,"") | H46: =+IF(R46<>"",R46,"") | J46: Flesan Indutrial Power S.A.C | K46: 1 | N46: Flesan Indutrial Power S.A.C | P46: 1 | S46: 1 | U46: Cia Minera Poderosa S.A. | V46: C.H. EL TINGO | W46: HI
B47: =+B46+1 -> 42 | C47: =+J47 -> Freno S.A. | D47: =+K47 -> 1 | E47: =+IF(O47<>"",O47,"") | F47: =+IF(P47<>"",P47,"") -> 1 | G47: =+IF(Q47<>"",Q47,"") | H47: =+IF(R47<>"",R47,"") | J47: Freno S.A. | K47: 1 | N47: Freno S.A. | P47: 1 | S47: 1 | U47: Cia Minera Poderosa S.A. | V47: C.T. J.A. SAMANIEGO ALC | W47: EL
B48: =+B47+1 -> 43 | C48: =+J48 -> Hotelera Costa del Pacifico S. A. | D48: =+K48 -> 1 | E48: =+IF(O48<>"",O48,"") | F48: =+IF(P48<>"",P48,"") -> 1 | G48: =+IF(Q48<>"",Q48,"") | H48: =+IF(R48<>"",R48,"") | J48: Hotelera Costa del Pacifico S. A. | K48: 1 | N48: Hotelera Costa del Pacifico S. A. | P48: 1 | S48: 1 | U48: Cia Minera Poderosa S.A. | V48: C.T. PATAZ | W48: EL
B49: =+B48+1 -> 44 | C49: =+J49 -> ICM Pachapaqui S.A.C. | D49: =+K49 -> 2 | E49: =+IF(O49<>"",O49,"") -> 2 | F49: =+IF(P49<>"",P49,"") | G49: =+IF(Q49<>"",Q49,"") | H49: =+IF(R49<>"",R49,"") | J49: ICM Pachapaqui S.A.C. | K49: 2 | N49: ICM Pachapaqui S.A.C. | O49: 2 | S49: 2 | U49: Cia Minera Raura S.A. | V49: C.H. CASHAUCRO | W49: HI
B50: =+B49+1 -> 45 | C50: =+J50 -> Illapu Energy S.A. | D50: =+K50 -> 1 | E50: =+IF(O50<>"",O50,"") | F50: =+IF(P50<>"",P50,"") | G50: =+IF(Q50<>"",Q50,"") -> 1 | H50: =+IF(R50<>"",R50,"") | J50: Illapu Energy S.A. | K50: 1 | N50: Illapu Energy S.A. | Q50: 1 | S50: 1 | U50: Cia Minera Santa Luisa S.A. | V50: C.H. HUALLANCA NUEVA | W50: HI
B51: =+B50+1 -> 46 | C51: =+J51 -> Inca Tops S.A. | D51: =+K51 -> 4 | E51: =+IF(O51<>"",O51,"") | F51: =+IF(P51<>"",P51,"") -> 4 | G51: =+IF(Q51<>"",Q51,"") | H51: =+IF(R51<>"",R51,"") | J51: Inca Tops S.A. | K51: 4 | N51: Inca Tops S.A. | P51: 4 | S51: 4 | U51: Cia Minera Santa Luisa S.A. | V51: C.H. PALLCA | W51: HI
B52: =+B51+1 -> 47 | C52: =+J52 -> Indeco S.A. | D52: =+K52 -> 1 | E52: =+IF(O52<>"",O52,"") | F52: =+IF(P52<>"",P52,"") -> 1 | G52: =+IF(Q52<>"",Q52,"") | H52: =+IF(R52<>"",R52,"") | J52: Indeco S.A. | K52: 1 | N52: Indeco S.A. | P52: 1 | S52: 1 | U52: Cia Minera Santa Luisa S.A. | V52: C.T. ATALAYA | W52: EL
B53: =+B52+1 -> 48 | C53: =+J53 -> Industrias Electroquimicas S. A. | D53: =+K53 -> 1 | E53: =+IF(O53<>"",O53,"") | F53: =+IF(P53<>"",P53,"") -> 1 | G53: =+IF(Q53<>"",Q53,"") | H53: =+IF(R53<>"",R53,"") | J53: Industrias Electroquimicas S. A. | K53: 1 | N53: Industrias Electroquimicas S. A. | P53: 1 | S53: 1 | U53: Cia Minera Santa Luisa S.A. | V53: C.T. HUANZALÁ | W53: EL
B54: =+B53+1 -> 49 | C54: =+J54 -> Inkabor S.A.C. | D54: =+K54 -> 2 | E54: =+IF(O54<>"",O54,"") | F54: =+IF(P54<>"",P54,"") -> 2 | G54: =+IF(Q54<>"",Q54,"") | H54: =+IF(R54<>"",R54,"") | J54: Inkabor S.A.C. | K54: 2 | N54: Inkabor S.A.C. | P54: 2 | S54: 2 | U54: Cia Minera Santa Luisa S.A. | V54: C.T. PALLCA | W54: EL
B55: =+B54+1 -> 50 | C55: =+J55 -> Inversiones San Borja S.A. | D55: =+K55 -> 1 | E55: =+IF(O55<>"",O55,"") | F55: =+IF(P55<>"",P55,"") -> 1 | G55: =+IF(Q55<>"",Q55,"") | H55: =+IF(R55<>"",R55,"") | J55: Inversiones San Borja S.A. | K55: 1 | N55: Inversiones San Borja S.A. | P55: 1 | S55: 1 | U55: CNPC Perú S.A. | V55: C.T. LOTE X | W55: EL
B56: =+B55+1 -> 51 | C56: =+J56 -> Kimberly Clark S.R.L. | D56: =+K56 -> 2 | E56: =+IF(O56<>"",O56,"") | F56: =+IF(P56<>"",P56,"") -> 2 | G56: =+IF(Q56<>"",Q56,"") | H56: =+IF(R56<>"",R56,"") | J56: Kimberly Clark S.R.L. | K56: 2 | N56: Kimberly Clark S.R.L. | P56: 2 | S56: 2 | U56: Compañía Minera Antapaccay S.A. | V56: C.T. TINTAYA | W56: EL
B57: =+B56+1 -> 52 | C57: =+J57 -> Leche Gloria S.A. | D57: =+K57 -> 1 | E57: =+IF(O57<>"",O57,"") | F57: =+IF(P57<>"",P57,"") -> 1 | G57: =+IF(Q57<>"",Q57,"") | H57: =+IF(R57<>"",R57,"") | J57: Leche Gloria S.A. | K57: 1 | N57: Leche Gloria S.A. | P57: 1 | S57: 1 | U57: Compañía Minera Ares S.A.C. | V57: C.T. ARCATA | W57: EL
B58: =+B57+1 -> 53 | C58: =+J58 -> Minera Aurífera Retamas S.A. | D58: =+K58 -> 1 | E58: =+IF(O58<>"",O58,"") | F58: =+IF(P58<>"",P58,"") -> 1 | G58: =+IF(Q58<>"",Q58,"") | H58: =+IF(R58<>"",R58,"") | J58: Minera Aurífera Retamas S.A. | K58: 1 | N58: Minera Aurífera Retamas S.A. | P58: 1 | S58: 1 | U58: Compañía Minera Ares S.A.C. | V58: C.T. ARES | W58: EL
B59: =+B58+1 -> 54 | C59: =+J59 -> Minera Bateas S.A.C. | D59: =+K59 -> 1 | E59: =+IF(O59<>"",O59,"") | F59: =+IF(P59<>"",P59,"") -> 1 | G59: =+IF(Q59<>"",Q59,"") | H59: =+IF(R59<>"",R59,"") | J59: Minera Bateas S.A.C. | K59: 1 | N59: Minera Bateas S.A.C. | P59: 1 | S59: 1 | U59: Compañía Minera Ares S.A.C. | V59: C.T. PALLANCATA | W59: EL
B60: =+B59+1 -> 55 | C60: =+J60 -> Minera Boroo Misquichilca S.A. | D60: =+K60 -> 1 | E60: =+IF(O60<>"",O60,"") | F60: =+IF(P60<>"",P60,"") -> 1 | G60: =+IF(Q60<>"",Q60,"") | H60: =+IF(R60<>"",R60,"") | J60: Minera Boroo Misquichilca S.A. | K60: 1 | N60: Minera Boroo Misquichilca S.A. | P60: 1 | S60: 1 | U60: Compañía Minera Ares S.A.C. | V60: C.T. SELENE | W60: EL
B61: =+B60+1 -> 56 | C61: =+J61 -> Minera Colquisiri S.A. | D61: =+K61 -> 1 | E61: =+IF(O61<>"",O61,"") | F61: =+IF(P61<>"",P61,"") -> 1 | G61: =+IF(Q61<>"",Q61,"") | H61: =+IF(R61<>"",R61,"") | J61: Minera Colquisiri S.A. | K61: 1 | N61: Minera Colquisiri S.A. | P61: 1 | S61: 1 | U61: Compañía Minera Ares S.A.C. | V61: C.T. SIPÁN | W61: EL
B62: =+B61+1 -> 57 | C62: =+J62 -> Minera La Zanja S.R.L. | D62: =+K62 -> 1 | E62: =+IF(O62<>"",O62,"") | F62: =+IF(P62<>"",P62,"") -> 1 | G62: =+IF(Q62<>"",Q62,"") | H62: =+IF(R62<>"",R62,"") | J62: Minera La Zanja S.R.L. | K62: 1 | N62: Minera La Zanja S.R.L. | P62: 1 | S62: 1 | U62: Compañía Minera Ares S.A.C. | V62: C.T. INMACULADA | W62: EL
... B67: =+B66+1 -> 62 | C67: =+J67 -> Mondelez Peru S.A. | D67: =+K67 -> 1 | E67: =+IF(O67<>"",O67,"") | F67: =+IF(P67<>"",P67,"") -> 1 | G67: =+IF(Q67<>"",Q67,"") | H67: =+IF(R67<>"",R67,"") | J67: Mondelez Peru S.A. | K67: 1 | N67: Mondelez Peru S.A. | P67: 1 | S67: 1 | U67: Compañía Minera Chungar S.A.C. | V67: C.H. BAÑOS III | W67: HI
B68: =+B67+1 -> 63 | C68: =+J68 -> Nexa Resources Atacocha S.A.A. | D68: =+K68 -> 2 | E68: =+IF(O68<>"",O68,"") -> 2 | F68: =+IF(P68<>"",P68,"") | G68: =+IF(Q68<>"",Q68,"") | H68: =+IF(R68<>"",R68,"") | J68: Nexa Resources Atacocha S.A.A. | K68: 2 | N68: Nexa Resources Atacocha S.A.A. | O68: 2 | S68: 2 | U68: Compañía Minera Chungar S.A.C. | V68: C.H. BAÑOS IV | W68: HI
B69: =+B68+1 -> 64 | C69: =+J69 -> Nexa Resources Cajamarquilla S.A. | D69: =+K69 -> 6 | E69: =+IF(O69<>"",O69,"") | F69: =+IF(P69<>"",P69,"") -> 4 | G69: =+IF(Q69<>"",Q69,"") | H69: =+IF(R69<>"",R69,"") -> 2 | J69: Nexa Resources Cajamarquilla S.A. | K69: 6 | N69: Nexa Resources Cajamarquilla S.A. | P69: 4 | R69: 2 | S69: 6 | U69: Compañía Minera Chungar S.A.C. | V69: C.H. BAÑOS V | W69: HI
B70: =+B69+1 -> 65 | C70: =+J70 -> Nexa Resources el Porvenir S.A.A. | D70: =+K70 -> 2 | E70: =+IF(O70<>"",O70,"") -> 1 | F70: =+IF(P70<>"",P70,"") -> 1 | G70: =+IF(Q70<>"",Q70,"") | H70: =+IF(R70<>"",R70,"") | J70: Nexa Resources el Porvenir S.A.A. | K70: 2 | N70: Nexa Resources el Porvenir S.A.A. | O70: 1 | P70: 1 | S70: 2 | U70: Compañía Minera Chungar S.A.C. | V70: C.H. CACRAY | W70: HI
B71: =+B70+1 -> 66 | C71: =+J71 -> OIG Perú S.A.C. | D71: =+K71 -> 2 | E71: =+IF(O71<>"",O71,"") | F71: =+IF(P71<>"",P71,"") -> 2 | G71: =+IF(Q71<>"",Q71,"") | H71: =+IF(R71<>"",R71,"") | J71: OIG Perú S.A.C. | K71: 2 | N71: OIG Perú S.A.C. | P71: 2 | S71: 2 | U71: Compañía Minera Chungar S.A.C. | V71: C.H. FRANCOIS | W71: HI
B72: =+B71+1 -> 67 | C72: =+J72 -> Oxido de Pasco S.A.C. | D72: =+K72 -> 1 | E72: =+IF(O72<>"",O72,"") | F72: =+IF(P72<>"",P72,"") -> 1 | G72: =+IF(Q72<>"",Q72,"") | H72: =+IF(R72<>"",R72,"") | J72: Oxido de Pasco S.A.C. | K72: 1 | N72: Oxido de Pasco S.A.C. | P72: 1 | S72: 1 | U72: Compañía Minera Chungar S.A.C. | V72: C.H. HUANCHAY | W72: HI
B73: =+B72+1 -> 68 | C73: =+J73 -> Peru LNG S.R.L. | D73: =+K73 -> 1 | E73: =+IF(O73<>"",O73,"") | F73: =+IF(P73<>"",P73,"") | G73: =+IF(Q73<>"",Q73,"") -> 1 | H73: =+IF(R73<>"",R73,"") | J73: Peru LNG S.R.L. | K73: 1 | N73: Peru LNG S.R.L. | Q73: 1 | S73: 1 | U73: Compañía Minera Chungar S.A.C. | V73: C.H. SAN JOSÉ | W73: HI
B74: =+B73+1 -> 69 | C74: =+J74 -> Pesquera Diamante S.A. | D74: =+K74 -> 5 | E74: =+IF(O74<>"",O74,"") | F74: =+IF(P74<>"",P74,"") -> 5 | G74: =+IF(Q74<>"",Q74,"") | H74: =+IF(R74<>"",R74,"") | J74: Pesquera Diamante S.A. | K74: 5 | N74: Pesquera Diamante S.A. | P74: 5 | S74: 5 | U74: Compañía Minera Chungar S.A.C. | V74: C.H. SHAGUA | W74: HI
B75: =+B74+1 -> 70 | C75: =+J75 -> Pesquera Pelayo S.A.C. | D75: =+K75 -> 1 | E75: =+IF(O75<>"",O75,"") | F75: =+IF(P75<>"",P75,"") -> 1 | G75: =+IF(Q75<>"",Q75,"") | H75: =+IF(R75<>"",R75,"") | J75: Pesquera Pelayo S.A.C. | K75: 1 | N75: Pesquera Pelayo S.A.C. | P75: 1 | S75: 1 | U75: Compañía Minera Chungar S.A.C. | V75: C.H. YANAHUIN | W75: HI
B76: =+B75+1 -> 71 | C76: =+J76 -> Petroleos del Peru PETROPERU S.A. | D76: =+K76 -> 11 | E76: =+IF(O76<>"",O76,"") | F76: =+IF(P76<>"",P76,"") -> 11 | G76: =+IF(Q76<>"",Q76,"") | H76: =+IF(R76<>"",R76,"") | J76: Petroleos del Peru PETROPERU S.A. | K76: 11 | N76: Petroleos del Peru PETROPERU S.A. | P76: 11 | S76: 11 | U76: Compañía Minera Chungar S.A.C. | V76: C.T. ESPERANZA | W76: EL
B77: =+B76+1 -> 72 | C77: =+J77 -> Pluspetrol Norte S.A. | D77: =+K77 -> 9 | E77: =+IF(O77<>"",O77,"") | F77: =+IF(P77<>"",P77,"") -> 9 | G77: =+IF(Q77<>"",Q77,"") | H77: =+IF(R77<>"",R77,"") | J77: Pluspetrol Norte S.A. | K77: 9 | N77: Pluspetrol Norte S.A. | P77: 9 | S77: 9 | U77: Compañía Minera Chungar S.A.C. | V77: C.T. PLANTA CONCENTRADORA | W77: EL
B78: =+B77+1 -> 73 | C78: =+J78 -> Pluspetrol Perú Corporation S.A. | D78: =+K78 -> 2 | E78: =+IF(O78<>"",O78,"") | F78: =+IF(P78<>"",P78,"") | G78: =+IF(Q78<>"",Q78,"") -> 2 | H78: =+IF(R78<>"",R78,"") | J78: Pluspetrol Perú Corporation S.A. | K78: 2 | N78: Pluspetrol Perú Corporation S.A. | Q78: 2 | S78: 2 | U78: Compañía Minera Chungar S.A.C. | V78: C.T. TAJO DON PABLO | W78: EL
B79: =+B78+1 -> 74 | C79: =+J79 -> Precotex S.A. | D79: =+K79 -> 1 | E79: =+IF(O79<>"",O79,"") | F79: =+IF(P79<>"",P79,"") -> 1 | G79: =+IF(Q79<>"",Q79,"") | H79: =+IF(R79<>"",R79,"") | J79: Precotex S.A. | K79: 1 | N79: Precotex S.A. | P79: 1 | S79: 1 | U79: Compañia Minera Kolpa S.A. | V79: C.T. KOLPA | W79: EL
B80: =+B79+1 -> 75 | C80: =+J80 -> Procesadora Industrial Rio Seco S.A. | D80: =+K80 -> 2 | E80: =+IF(O80<>"",O80,"") | F80: =+IF(P80<>"",P80,"") -> 1 | G80: =+IF(Q80<>"",Q80,"") | H80: =+IF(R80<>"",R80,"") -> 1 | J80: Procesadora Industrial Rio Seco S.A. | K80: 2 | N80: Procesadora Industrial Rio Seco S.A. | P80: 1 | R80: 1 | S80: 2 | U80: Compañía Minera San Ignacio de Morococha S.A.A. | V80: C.H. MONOBAMBA | W80: HI
B81: =+B80+1 -> 76 | C81: =+J81 -> Progenere S.A.C. | D81: =+K81 -> 1 | E81: =+IF(O81<>"",O81,"") | F81: =+IF(P81<>"",P81,"") -> 1 | G81: =+IF(Q81<>"",Q81,"") | H81: =+IF(R81<>"",R81,"") | J81: Progenere S.A.C. | K81: 1 | N81: Progenere S.A.C. | P81: 1 | S81: 1 | U81: Compañía Minera San Ignacio de Morococha S.A.A. | V81: C.T. SAN VICENTE | W81: EL
B82: =+B81+1 -> 77 | C82: =+J82 -> Quimpac S.A. | D82: =+K82 -> 1 | E82: =+IF(O82<>"",O82,"") | F82: =+IF(P82<>"",P82,"") | G82: =+IF(Q82<>"",Q82,"") | H82: =+IF(R82<>"",R82,"") -> 1 | J82: Quimpac S.A. | K82: 1 | N82: Quimpac S.A. | R82: 1 | S82: 1 | U82: Compañía Minera San Valentin S.A. | V82: C.H. LLAPAY | W82: HI
B83: =+B82+1 -> 78 | C83: =+J83 -> Refinería La Pampilla S.A. | D83: =+K83 -> 1 | E83: =+IF(O83<>"",O83,"") | F83: =+IF(P83<>"",P83,"") | G83: =+IF(Q83<>"",Q83,"") -> 1 | H83: =+IF(R83<>"",R83,"") | J83: Refinería La Pampilla S.A. | K83: 1 | N83: Refinería La Pampilla S.A. | Q83: 1 | S83: 1 | U83: Compañía Pesquera del Pacifico Centro S.A. | V83: C.T. PLANTA CHIMBOTE | W83: EL
B84: =+B83+1 -> 79 | C84: =+J84 -> San Fernando S.A. | D84: =+K84 -> 3 | E84: =+IF(O84<>"",O84,"") | F84: =+IF(P84<>"",P84,"") -> 3 | G84: =+IF(Q84<>"",Q84,"") | H84: =+IF(R84<>"",R84,"") | J84: San Fernando S.A. | K84: 3 | N84: San Fernando S.A. | P84: 3 | S84: 3 | U84: Compañia Quimica S.A. | V84: C.T. COMPAÑÍA QUIMICA | W84: EL
B85: =+B84+1 -> 80 | C85: =+J85 -> Snacks América Latina S.R.L. | D85: =+K85 -> 1 | E85: =+IF(O85<>"",O85,"") | F85: =+IF(P85<>"",P85,"") -> 1 | G85: =+IF(Q85<>"",Q85,"") | H85: =+IF(R85<>"",R85,"") | J85: Snacks América Latina S.R.L. | K85: 1 | N85: Snacks América Latina S.R.L. | P85: 1 | S85: 1 | U85: Consorcio Minero Horizonte S.A. | V85: C.H. PÍAS 1 | W85: HI
B86: =+B85+1 -> 81 | C86: =+J86 -> Sobreandes S.A.C. | D86: =+K86 -> 1 | E86: =+IF(O86<>"",O86,"") | F86: =+IF(P86<>"",P86,"") -> 1 | G86: =+IF(Q86<>"",Q86,"") | H86: =+IF(R86<>"",R86,"") | J86: Sobreandes S.A.C. | K86: 1 | N86: Sobreandes S.A.C. | P86: 1 | S86: 1 | U86: Consorcio Minero Horizonte S.A. | V86: C.T. PARCOY | W86: EL
B87: =+B86+1 -> 82 | C87: =+J87 -> Soc. Minera el Brocal S.A. | D87: =+K87 -> 4 | E87: =+IF(O87<>"",O87,"") -> 4 | F87: =+IF(P87<>"",P87,"") | G87: =+IF(Q87<>"",Q87,"") | H87: =+IF(R87<>"",R87,"") | J87: Soc. Minera el Brocal S.A. | K87: 4 | N87: Soc. Minera el Brocal S.A. | O87: 4 | S87: 4 | U87: Corporación Aceros Arequipa S.A. | V87: C.T. ACEROS | W87: EL
B88: =+B87+1 -> 83 | C88: =+J88 -> Socosani S.A. | D88: =+K88 -> 1 | E88: =+IF(O88<>"",O88,"") | F88: =+IF(P88<>"",P88,"") -> 1 | G88: =+IF(Q88<>"",Q88,"") | H88: =+IF(R88<>"",R88,"") | J88: Socosani S.A. | K88: 1 | N88: Socosani S.A. | P88: 1 | S88: 1 | U88: Corporación Pesquera Inca S.A.C. | V88: C.T. COPEINCA CHANCAY | W88: EL
B89: =+B88+1 -> 84 | C89: =+J89 -> Southern Perú Cooper Corporation Sucursal del Peru | D89: =+K89 -> 4 | E89: =+IF(O89<>"",O89,"") -> 1 | F89: =+IF(P89<>"",P89,"") -> 3 | G89: =+IF(Q89<>"",Q89,"") | H89: =+IF(R89<>"",R89,"") | J89: Southern Perú Cooper Corporation Sucursal del Peru | K89: 4 | N89: Southern Perú Cooper Corporation Sucursal del Peru | O89: 1 | P89: 3 | S89: 4 | U89: Corporación Pesquera Inca S.A.C. | V89: C.T. COPEINCA SUPE | W89: EL
B90: =+B89+1 -> 85 | C90: =+J90 -> Sudamericana de Fibras S.A. | D90: =+K90 -> 1 | E90: =+IF(O90<>"",O90,"") | F90: =+IF(P90<>"",P90,"") -> 1 | G90: =+IF(Q90<>"",Q90,"") | H90: =+IF(R90<>"",R90,"") | J90: Sudamericana de Fibras S.A. | K90: 1 | N90: Sudamericana de Fibras S.A. | P90: 1 | S90: 1 | U90: Empresa Agroindustrial Pomalca S.A.A. | V90: C.T. POMALCA TV | W90: TV
B91: =+B90+1 -> 86 | C91: =+J91 -> Surpack S.A. | D91: =+K91 -> 1 | E91: =+IF(O91<>"",O91,"") | F91: =+IF(P91<>"",P91,"") -> 1 | G91: =+IF(Q91<>"",Q91,"") | H91: =+IF(R91<>"",R91,"") | J91: Surpack S.A. | K91: 1 | N91: Surpack S.A. | P91: 1 | S91: 1 | U91: Empresa Agroindustrial Pomalca S.A.A. | V91: C.T. POMALCA EL | W91: EL
B92: =+B91+1 -> 87 | C92: =+J92 -> Tecnológica de Alimentos S.A. | D92: =+K92 -> 8 | E92: =+IF(O92<>"",O92,"") | F92: =+IF(P92<>"",P92,"") -> 8 | G92: =+IF(Q92<>"",Q92,"") | H92: =+IF(R92<>"",R92,"") | J92: Tecnológica de Alimentos S.A. | K92: 8 | N92: Tecnológica de Alimentos S.A. | P92: 8 | S92: 8 | U92: Empresa Explotadora de Vinchos Ltda S.A.C. | V92: C.T. VINCHOS | W92: EL
B93: =+B92+1 -> 88 | C93: =+J93 -> Terminal Internacional del Sur S.A. | D93: =+K93 -> 1 | E93: =+IF(O93<>"",O93,"") | F93: =+IF(P93<>"",P93,"") -> 1 | G93: =+IF(Q93<>"",Q93,"") | H93: =+IF(R93<>"",R93,"") | J93: Terminal Internacional del Sur S.A. | K93: 1 | N93: Terminal Internacional del Sur S.A. | P93: 1 | S93: 1 | U93: Empresa Minera los Quenuales S.A. | V93: C.T. ISCAYCRUZ | W93: EL
B94: =+B93+1 -> 89 | C94: =+J94 -> Trupal S.A. | D94: =+K94 -> 1 | E94: =+IF(O94<>"",O94,"") | F94: =+IF(P94<>"",P94,"") | G94: =+IF(Q94<>"",Q94,"") | H94: =+IF(R94<>"",R94,"") -> 1 | J94: Trupal S.A. | K94: 1 | N94: Trupal S.A. | R94: 1 | S94: 1 | U94: Empresa Minera los Quenuales S.A. | V94: C.H. RAPAZ II | W94: HI
B95: =+B94+1 -> 90 | C95: =+J95 -> Unacem Peru S.A. | D95: =+K95 -> 6 | E95: =+IF(O95<>"",O95,"") -> 3 | F95: =+IF(P95<>"",P95,"") -> 2 | G95: =+IF(Q95<>"",Q95,"") -> 1 | H95: =+IF(R95<>"",R95,"") | J95: Unacem Peru S.A. | K95: 6 | N95: Unacem Peru S.A. | O95: 3 | P95: 2 | Q95: 1 | S95: 6 | U95: Empresa Minera los Quenuales S.A. | V95: C.T. LAGSAURA | W95: EL
B96: =+B95+1 -> 91 | C96: =+J96 -> Unión de Cervecerías Peruanas Backus y Johnston S.A.A. | D96: =+K96 -> 5 | E96: =+IF(O96<>"",O96,"") | F96: =+IF(P96<>"",P96,"") -> 5 | G96: =+IF(Q96<>"",Q96,"") | H96: =+IF(R96<>"",R96,"") | J96: Unión de Cervecerías Peruanas Backus y Johnston S.A.A. | K96: 5 | N96: Unión de Cervecerías Peruanas Backus y Johnston S.A.A. | P96: 5 | S96: 5 | U96: Flesan Indutrial Power S.A.C | V96: C.T. INDUSTRIAS SAN MIGUEL PET | W96: EL
B97: =+B96+1 -> 92 | C97: =+J97 -> Volcan Compañia Minera S.A.A. | D97: =+K97 -> 6 | E97: =+IF(O97<>"",O97,"") | F97: =+IF(P97<>"",P97,"") -> 6 | G97: =+IF(Q97<>"",Q97,"") | H97: =+IF(R97<>"",R97,"") | J97: Volcan Compañia Minera S.A.A. | K97: 6 | N97: Volcan Compañia Minera S.A.A. | P97: 6 | S97: 6 | U97: Freno S.A. | V97: C.T. FRENOSA | W97: EL
B98: =+B97+1 -> 93 | C98: =+J98 -> Yura S.A. | D98: =+K98 -> 1 | E98: =+IF(O98<>"",O98,"") | F98: =+IF(P98<>"",P98,"") -> 1 | G98: =+IF(Q98<>"",Q98,"") | H98: =+IF(R98<>"",R98,"") | J98: Yura S.A. | K98: 1 | N98: Yura S.A. | P98: 1 | S98: 1 | U98: Hotelera Costa del Pacifico S. A. | V98: C.T. COSTA DEL PACÍFICO | W98: EL
B99: TOTAL USO PROPIO * | D99: =SUM(D6:D98) -> 219 | E99: =SUM(E6:E98) -> 32 | F99: =SUM(F6:F98) -> 164 | G99: =SUM(G6:G98) -> 7 | H99: =SUM(H6:H98) -> 16 | J99: Total general | K99: 219 | N99: Total general | O99: 32 | P99: 164 | Q99: 7 | R99: 16 | S99: 219 | U99: ICM Pachapaqui S.A.C. | V99: C.H. SAN JUDAS TADEO | W99: HI
B100: (*) Empresas informantes a diciembre 2024. | U100: ICM Pachapaqui S.A.C. | V100: C.H. SAN MARTÍN DE PORRES | W100: HI
U101: Illapu Energy S.A. | V101: C.T. PLANTA HUACHIPA | W101: TG
U102: Inca Tops S.A. | V102: C.T. PLANTA 1 | W102: EL
B103: 3.2.1.3. Total de centrales eléctricas para el mercado eléctrico y uso propio | U103: Inca Tops S.A. | V103: C.T. PLANTA 2 | W103: EL
U104: Inca Tops S.A. | V104: C.T. PLANTA 04-1 | W104: EL
...

Sheet 3.2.2.1
B1: 3.2.2 Centrales eléctricas representativas por tipo de generación | J1: P.I. TOTAL | K1: 16530.989 | L1: PRODUCC. TOT | M1: 63794.884
K2: Tipo de Mercado A | L2: Mercado Eléctrico
B3: 3.2.2.1 Centrales Hidráulicas | K3: Informa A | L3: Informante
K4: Origen A | L4: Hidráulico
B5: Empresa | C5: Central | D5: Potencia Instalada | F5: Producción | K5: FILTRO | L5: (en blanco)
D6: (MW) | E6: % P.I. | F6: GWh | G6: % P.B.
K7: Empresa Anuario | L7: Central Anuario | M7: Suma de PI OK | N7: Suma de Energia (GWh)
B8: Electroperú S. A. | C8: C.H. ANTUNEZ DE MAYOLO | D8: 798 | E8: 4.8272974 | F8: 5261.7876 | G8: 8.2479774 | K8: Electroperú S. A. | L8: C.H. ANTUNEZ DE MAYOLO | M8: 798 | N8: 5261.7876
B9: Electroperú S. A. | C9: C.H. RESTITUCION | D9: 210.36 | E9: 1.2725191 | F9: 1681.6239 | G9: 2.6359856 | K9: Electroperú S. A. | L9: C.H. RESTITUCION | M9: 210.36 | N9: 1681.6239
K10: Total Electroperú S. A. | M10: 1008.36 | N10: 6943.4116
B11: Kallpa Generación S.A. | C11: C.H. CERRO DEL AGUILA | D11: 524.6 | E11: 3.1734338 | F11: 3480.832 | G11: 5.4562871 | K11: Kallpa Generación S.A. | L11: C.H. CERRO DEL AGUILA | M11: 524.6 | N11: 3480.832
K12: Total Kallpa Generación S.A. | M12: 524.6 | N12: 3480.832
B13: Empresa de Generación Huallaga S.A. | C13: C.H. CHAGLLA | D13: 467.785 | E13: 2.829746 | F13: 2064.6622 | G13: 3.2364072 | K13: Empresa de Generación Huallaga S.A. | L13: C.H. CHAGLLA | M13: 467.785 | N13: 2064.6622
K14: Total Empresa de Generación Huallaga S.A. | M14: 467.785 | N14: 2064.6622
B15: Emp. de Generación Eléctrica de Arequipa S. A. | C15: C.H. CHARCANI V | D15: 146.86 | E15: 0.8883921 | F15: 697.39646 | G15: 1.0931856 | K15: Emp. de Generación Eléctrica de Arequipa S. A. | L15: C.H. CHARCANI V | M15: 146.86 | N15: 697.39646 | P15: Tipo de Mercado A | Q15: Mercado Eléctrico
K16: Total Emp. de Generación Eléctrica de Arequipa S. A. | M16: 146.86 | N16: 697.39646 | P16: Informa A | Q16: Informante
B17: Emp. de Generación Eléctrica Machu Picchu S. A. | C17: C.H. MACHUPICCHU | D17: 192.45 | E17: 1.1641772 | F17: 1252.2207 | G17: 1.9628857 | K17: Empresa de Generacion Electrica Machupicchu S.A. | L17: C.H. MACHUPICCHU | M17: 192.45 | N17: 1252.2207 | P17: Origen A | Q17: Hidráulico
K18: Total Empresa de Generacion Electrica Machupicchu S.A. | M18: 192.45 | N18: 1252.2207 | P18: FILTRO | Q18: (en blanco)
B19: Empresa de Generación Eléctrica San Gabán S. A. | C19: C.H. SAN GABAN II | D19: 114 | E19: 0.68961391 | F19: 764.19523 | G19: 1.1978942 | K19: Empresa de Generación Eléctrica San Gabán S. A. | L19: C.H. SAN GABAN II | M19: 114 | N19: 764.19523
K20: Total Empresa de Generación Eléctrica San Gabán S. A. | M20: 114 | N20: 764.19523 | P20: Empresa Anuario | Q20: Central Anuario | R20: Suma de PI OK | S20: Suma de Energia (GWh)
B21: Enel Generación Perú S.A.A. | C21: C.H. HUINCO | D21: 258.4 | E21: 1.5631249 | F21: 1297.6523 | G21: 2.0341008 | K21: Orygen Perú S.A.A. | L21: C.H. HUINCO | M21: 258.4 | N21: 481.80661 | P21: Enel Generación Perú S.A.A. | Q21: C.H. HUINCO | R21: 0 | S21: 815.84566
B22: Enel Generación Perú S.A.A. | C22: C.H. MATUCANA | D22: 120 | E22: 0.72590938 | F22: 922.15217 | G22: 1.4454955 | K22: Orygen Perú S.A.A. | L22: C.H. MATUCANA | M22: 120 | N22: 353.97133 | P22: Enel Generación Perú S.A.A. | Q22: C.H. MATUCANA | R22: 0 | S22: 568.18084
K23: Total Orygen Perú S.A.A. | M23: 378.4 | N23: 835.77794 | P23: Total Enel Generación Perú S.A.A. | R23: 0 | S23: 1384.0265
B24: ENGIE EnergÍa Perú S.A. | C24: C.H. YUNCÁN | D24: 136.759 | E24: 0.82728868 | F24: 789.10095 | G24: 1.2369345 | K24: ENGIE EnergÍa Perú S.A. | L24: C.H. YUNCÁN | M24: 136.759 | N24: 789.10095 | P24: Total general | R24: 0 | S24: 1384.0265
B25: ENGIE EnergÍa Perú S.A. | C25: C.H. QUITARACSA | D25: 111 | E25: 0.67146618 | F25: 457.3347 | G25: 0.71688303 | K25: ENGIE EnergÍa Perú S.A. | L25: C.H. QUITARACSA | M25: 111 | N25: 457.3347
K26: Total ENGIE EnergÍa Perú S.A. | M26: 247.759 | N26: 1246.4357
B27: Luz del Sur S.A. | C27: C.H. SANTA TERESA | D27: 100 | E27: 0.60492448 | F27: 617.27995 | G27: 0.96760101 | K27: Inland Energy S.A.C. | L27: C.H. SANTA TERESA | M27: 100 | N27: 617.27995
K28: Total Inland Energy S.A.C. | M28: 100 | N28: 617.27995
B29: Orazul Energy Perú S.A. | C29: C.H. CAÑON DEL PATO | D29: 246.582 | E29: 1.4916349 | F29: 1528.3387 | G29: 2.3957073 | K29: Orazul Energy Perú S.A. | L29: C.H. CAÑON DEL PATO | M29: 246.582 | N29: 1528.3387
K30: Total Orazul Energy Perú S.A. | M30: 246.582 | N30: 1528.3387
B31: Chinango S.A.C | C31: C.H. CHIMAY | D31: 153 | E31: 0.92553446 | F31: 770.18096 | G31: 1.207277 | K31: Chinango S.A.C | L31: C.H. CHIMAY | M31: 153 | N31: 770.18096
K32: Total Chinango S.A.C | M32: 153 | N32: 770.18096
B33: Compañia Eléctrica El Platanal S.A. | C33: C.H. EL PLATANAL | D33: 220 | E33: 1.3308339 | F33: 1188.4125 | G33: 1.8628648 | K33: Compañia Eléctrica El Platanal S.A. | L33: C.H. EL PLATANAL | M33: 220 | N33: 1188.4125
K34: Total Compañia Eléctrica El Platanal S.A. | M34: 220 | N34: 1188.4125
B35: Statkraft Perú S.A. | C35: C.H. CHEVES | D35: 171.68 | E35: 1.0385344 | F35: 885.0034 | G35: 1.3872639 | K35: Statkraft Perú S.A. | L35: C.H. CHEVES | M35: 171.68 | N35: 885.0034
B36: Statkraft Perú S.A. | C36: C.H. YAUPI | D36: 113.686 | E36: 0.68771445 | F36: 784.51438 | G36: 1.229745 | K36: Statkraft Perú S.A. | L36: C.H. YAUPI | M36: 113.686 | N36: 784.51438
K37: Total general | M37: 4085.162 | N37: 23058.662
B39: % P.I. : Es el porcentaje respecto a la potencia instalada total 2024
B40: % P.B. : Es el porcentaje respecto a la producción de energía total 2024 | K40: Tipo de Mercado A | L40: Mercado Eléctrico
K41: Informa A | L41: Informante
B42: 3.2.2.2 Centrales Térmicas | K42: Origen A | L42: Térmico
K43: Tip Grup Dep | L43: CC
K44: Variable | L44: Energía
B45: Empresa | C45: Central | D45: Potencia Instalada | F45: Producción
D46: (MW) | E46: % P.I. | F46: GWh | G46: % P.B. | K46: Empresa Anuario | L46: Central Anuario | M46: Suma de PI OK | N46: Suma de Energia (GWh)
B47: De Ciclo Combinado | K47: Kallpa Generación S.A. | L47: C.T. KALLPA | M47: 979 | N47: 5970.9022
L48: C.T. LAS FLORES | M48: 306.6 | N48: 2220.1287
B49: Kallpa Generación S.A. | C49: C.T. KALLPA | D49: 979 | E49: 5.9222107 | F49: 5970.9022 | G49: 9.3595313 | K49: Total Kallpa Generación S.A. | M49: 1285.6 | N49: 8191.0309
C50: C.T. LAS FLORES | D50: 306.6 | E50: 1.8546985 | F50: 2220.1287 | G50: 3.4801046 | K50: ENGIE EnergÍa Perú S.A. | L50: C.T. CHILCA | M50: 972.2 | N50: 5800.4876
K51: Total ENGIE EnergÍa Perú S.A. | M51: 972.2 | N51: 5800.4876
B52: ENGIE EnergÍa Perú S.A. | C52: C.T. CHILCA | D52: 972.2 | E52: 5.8810758 | F52: 5800.4876 | G52: 9.0924024 | K52: Fénix Power Perú S.A. | L52: C.T. FENIX | M52: 578.8 | N52: 3805.4219
K53: Total Fénix Power Perú S.A. | M53: 578.8 | N53: 3805.4219
B54: Fénix Power Perú S.A. | C54: C.T. FENIX | D54: 578.8 | E54: 3.5013029 | F54: 3805.4219 | G54: 5.9650895 | K54: Enel Generación Perú S.A.A. | L54: C.T. VENTANILLA | M54: 0 | N54: 1519.1931
K55: Total Enel Generación Perú S.A.A. | M55: 0 | N55: 1519.1931
B56: Orygen Perú S.A.A. | C56: C.T. VENTANILLA | D56: 524 | E56: 3.1698043 | F56: 2908.7342 | G56: 4.5595101 | K56: Termochilca S.A. | L56: C.T. STO. DOMINGO DE LOS OLLEROS | M56: 300 | N56: 1323.1562
K57: Total Termochilca S.A. | M57: 300 | N57: 1323.1562
B58: Termochilca S.A. | C58: C.T. STO. DOMINGO DE LOS OLLEROS | D58: 300 | E58: 1.8147735 | F58: 1323.1562 | G58: 2.0740788 | K58: Emp. de Generación Eléctrica de Arequipa S. A. | L58: C.T. CHILINA | M58: 20.35 | N58: 0.134149
K59: Total Emp. de Generación Eléctrica de Arequipa S. A. | M59: 20.35 | N59: 0.134149
B60: Emp. de Generación Eléctrica de Arequipa S. A. | C60: C.T. CHILINA | D60: 20.35 | E60: 0.12310213 | F60: 0.134149 | G60: 0.00021028175 | K60: Orygen Perú S.A.A. | L60: C.T. VENTANILLA | M60: 524 | N60: 1389.5411
K61: Total Orygen Perú S.A.A. | M61: 524 | N61: 1389.5411
B62: De Ciclo Convencional | K62: Total general | M62: 3680.95 | N62: 22028.965
B64: Samay I S.A. | C64: C.T. PUERTO BRAVO | D64: 726 | E64: 4.3917518 | F64: 21.588949 | G64: 0.033841191
K65: Tipo de Mercado A | L65: Mercado Eléctrico
B66: ENGIE EnergÍa Perú S.A. | C66: C.T. NEPI | D66: 719.01 | E66: 4.3494675 | F66: 14.995401 | G66: 0.023505648 | K66: Informa A | L66: Informante
K67: Origen A | L67: Térmico
B68: Enel Generación Perú S.A.A. | C68: C.T. SANTA ROSA | D68: 446.7 | E68: 2.7021977 | F68: 423.03067 | G68: 0.66311064 | K68: Tip Grup Dep | L68: (Varios elementos)
K69: Variable | L69: Energía
B70: Termoselva S.R.L. | C70: C.T. AGUAYTÍA | D70: 202.64 | E70: 1.225819 | F70: 203.24829 | G70: 0.31859654
K71: Empresa Anuario | L71: Central Anuario | M71: Suma de PI OK | N71: Suma de Energia (GWh)
B72: Sociedad Minera Cerro Verde S.A.A. | C72: C.T. RECKA | D72: 181.3 | E72: 1.0967281 | F72: 6.45148 | G72: 0.010112848 | K72: Samay I S.A. | L72: C.T. PUERTO BRAVO | M72: 726 | N72: 21.588949
K73: Total Samay I S.A. | M73: 726 | N73: 21.588949
B74: GM Operaciones S.A.C. | C74: C.T. REFINERIA TALARA | D74: 102.34 | E74: 0.61907972 | F74: 383.41676 | G74: 0.6010149 | K74: ENGIE EnergÍa Perú S.A. | L74: C.T. NEPI | M74: 719.01 | N74: 14.995401
K75: Total ENGIE EnergÍa Perú S.A. | M75: 719.01 | N75: 14.995401
B76: Enel Generación Piura S.A. | C76: C.T. MALACAS 2 | D76: 101.3 | E76: 0.6127885 | F76: 42.446525 | G76: 0.066535938 | K76: Enel Generación Perú S.A.A. | L76: C.T. SANTA ROSA | M76: 0 | N76: 290.12721
K77: Total Enel Generación Perú S.A.A. | M77: 0 | N77: 290.12721
B78: De Reserva Fría | K78: Termoselva S.R.L. | L78: C.T. AGUAYTÍA | M78: 202.64 | N78: 203.24829
K79: Total Termoselva S.R.L. | M79: 202.64 | N79: 203.24829
B80: ENGIE EnergÍa Perú S.A. | C80: C.T. R.F. ILO | D80: 568.65 | E80: 3.4399031 | F80: 5.727714 | G80: 0.008978328 | K80: Sociedad Minera Cerro Verde S.A.A. | L80: C.T. RECKA | M80: 181.3 | N80: 6.45148
K81: Total Sociedad Minera Cerro Verde S.A.A. | M81: 181.3 | N81: 6.45148
B82: Planta de Reserva Fría de Generación Éten S.A. | C82: C.T. R.F. DE GENERACION ETEN | D82: 235.63 | E82: 1.4253836 | F82: 2.523366 | G82: 0.0039554363 | K82: GM Operaciones S.A.C. | L82: C.T. REFINERIA TALARA | M82: 102.34 | N82: 383.41676
K83: Total GM Operaciones S.A.C. | M83: 102.34 | N83: 383.41676
B84: Enel Generación Piura S.A. | C84: C.T. R.F. MALACAS 3 | D84: 177.65 | E84: 1.0746483 | F84: 15.270995 | G84: 0.023937648 | K84: Enel Generación Piura S.A. | L84: C.T. MALACAS 2 | M84: 101.3 | N84: 42.446525
K85: Total Enel Generación Piura S.A. | M85: 101.3 | N85: 42.446525
B86: Genrent del Peru S.A.C. | C86: C.T. R.F. IQUITOS NUEVA | D86: 81.2 | E86: 0.49119868 | F86: 401.6018 | G86: 0.62952037 | K86: Orygen Perú S.A.A. | L86: C.T. SANTA ROSA | M86: 446.7 | N86: 132.90346
K87: Total Orygen Perú S.A.A. | M87: 446.7 | N87: 132.90346
B88: Infraestructuras y Energías del Perú S.A.C. | C88: C.T. RF PUCALLPA | D88: 45.63 | E88: 0.27602704 | F88: 1.42131 | G88: 0.0022279373 | K88: Total general | M88: 2479.29 | N88: 1095.1781
C89: C.T. RF PUERTO MALDONADO | D89: 20.08 | E89: 0.12146884 | F89: 1.02106 | G89: 0.0016005359
B91: % P.I. : Es el porcentaje respecto a la potencia instalada total 2024 | K91: Tipo de Mercado A | L91: Mercado Eléctrico
B92: % P.B. : Es el porcentaje respecto a la producción de energía total 2024 | K92: Informa A | L92: Informante
K93: Origen A | L93: Térmico
K94: Tip Grup Dep | L94: (Varios elementos)
K95: Variable | L95: Energía
K97: Empresa Anuario | L97: Central Anuario | M97: Suma de PI OK | N97: Suma de Energia (GWh)
K98: ENGIE EnergÍa Perú S.A. | L98: C.T. RESERVA FRIA ILO | M98: 568.65 | N98: 5.727714
K99: Total ENGIE EnergÍa Perú S.A. | M99: 568.65 | N99: 5.727714
K100: Planta de Reserva Fría de Generación Éten S.A. | L100: C.T. R.F. DE GENERACION ETEN | M100: 235.63 | N100: 2.523366
K101: Total Planta de Reserva Fría de Generación Éten S.A. | M101: 235.63 | N101: 2.523366
K102: Enel Generación Piura S.A. | L102: C.T. R.F. MALACAS 3 | M102: 177.65 | N102: 15.270995
K103: Total Enel Generación Piura S.A. | M103: 177.65 | N103: 15.270995
K104: Genrent del Peru S.A.C. | L104: C.T. R.F. IQUITOS NUEVA | M104: 81.2 | N104: 401.6018
...

Sheet 3.2.2.3
A1: 3.2.2.3. Centrales del mercado electrico con Recursos Energéticos Renovables (RER*) | K1: Tipo de Mercado A | L1: Mercado Eléctrico
K2: Informa A | L2: Informante
B3: Empresa | C3: Central | D3: N° de Subasta RER | E3: Integrante | F3: Recurso | G3: PI | H3: PE | I3: Producción | K3: RER | L3: RER
G4: (MW) | H4: (MW) | I4: GWh
B5: Hidráulicas | K5: Origen A | L5: Empresa Anuario | M5: Central Anuario | N5: N° de Subasta RER | O5: Tipo de Integrante A | P5: Tipo de Recurso | Q5: Suma de PI OK | R5: Suma de PE OK | S5: Suma de Energia (GWh)
B6: =IF(L6<>"",L6,"") -> Andean Power S.A.C. | C6: =IF(M6<>"",M6,"") -> C.H. CARHUAC | D6: =IF(N6<>"",N6,"") -> TERCERA | E6: =IF(O6<>"",O6,"") -> COES | G6: =+Q6 -> 20 | H6: =+R6 -> 20 | I6: =+S6 -> 126.51936 | K6: Hidráulico | L6: Andean Power S.A.C. | M6: C.H. CARHUAC | N6: TERCERA | O6: COES | P6: Agua | Q6: 20 | R6: 20 | S6: 126.51936
B7: =IF(L7<>"",L7,"") -> Atria Energía S.A.C. | C7: =IF(M7<>"",M7,"") -> C.H. PURMACANA | D7: =IF(N7<>"",N7,"") -> PRIMERA | E7: =IF(O7<>"",O7,"") -> COES | G7: =+Q7 -> 1.8 | H7: =+R7 -> 1.79 | I7: =+S7 -> 2.082686 | L7: Atria Energía S.A.C. | M7: C.H. PURMACANA | N7: PRIMERA | O7: COES | P7: Agua | Q7: 1.8 | R7: 1.79 | S7: 2.082686
B8: =IF(L8<>"",L8,"") -> Eléctrica Yanapampa S.A.C. | C8: =IF(M8<>"",M8,"") -> C.H. YANAPAMPA | D8: =IF(N8<>"",N8,"") -> PRIMERA | E8: =IF(O8<>"",O8,"") -> COES | G8: =+Q8 -> 4.155 | H8: =+R8 -> 3.91 | I8: =+S8 -> 24.716961 | L8: Eléctrica Yanapampa S.A.C. | M8: C.H. YANAPAMPA | N8: PRIMERA | O8: COES | P8: Agua | Q8: 4.155 | R8: 3.91 | S8: 24.716961
B9: =IF(L9<>"",L9,"") -> Electro Oriente S. A. | C9: =IF(M9<>"",M9,"") -> C.H. QUANDA | D9: =IF(N9<>"",N9,"") -> - | E9: =IF(O9<>"",O9,"") -> NO COES | G9: =+Q9 -> 2.876 | H9: =+R9 -> 2.8 | I9: =+S9 -> 8.377812 | L9: Electro Oriente S. A. | M9: C.H. QUANDA | N9: - | O9: NO COES | P9: Agua | Q9: 2.876 | R9: 2.8 | S9: 8.377812
B10: =IF(L10<>"",L10,"") -> Electro Zaña S.A.C. | C10: =IF(M10<>"",M10,"") -> C.H. ZAÑA | D10: =IF(N10<>"",N10,"") -> TERCERA | E10: =IF(O10<>"",O10,"") -> NO COES | G10: =+Q10 -> 13.2 | H10: =+R10 -> 13.167 | I10: =+S10 -> 78.10708 | L10: Electro Zaña S.A.C. | M10: C.H. ZAÑA | N10: TERCERA | O10: NO COES | P10: Agua | Q10: 13.2 | R10: 13.167 | S10: 78.10708
B11: =IF(L11<>"",L11,"") -> Empresa de Generación Eléctrica Canchayllo S.A.C. | C11: =IF(M11<>"",M11,"") -> C.H. CANCHAYLLO | D11: =IF(N11<>"",N11,"") -> SEGUNDA | E11: =IF(O11<>"",O11,"") -> COES | G11: =+Q11 -> 5 | H11: =+R11 -> 5 | I11: =+S11 -> 31.368687 | L11: Empresa de Generación Eléctrica Canchayllo S.A.C. | M11: C.H. CANCHAYLLO | N11: SEGUNDA | O11: COES | P11: Agua | Q11: 5 | R11: 5 | S11: 31.368687
B12: =IF(L12<>"",L12,"") -> Empresa de Generación Eléctrica Junín S.A.C. | C12: =IF(M12<>"",M12,"") -> C.H. HUASAHUASI I | D12: =IF(N12<>"",N12,"") -> PRIMERA | E12: =IF(O12<>"",O12,"") -> COES | G12: =+Q12 -> 9.85 | H12: =+R12 -> 9.85 | I12: =+S12 -> 45.039692 | L12: Empresa de Generación Eléctrica Junín S.A.C. | M12: C.H. HUASAHUASI I | N12: PRIMERA | O12: COES | P12: Agua | Q12: 9.85 | R12: 9.85 | S12: 45.039692
B13: =IF(L13<>"",L13,"") | C13: =IF(M13<>"",M13,"") -> C.H. HUASAHUASI II | D13: =IF(N13<>"",N13,"") -> PRIMERA | E13: =IF(O13<>"",O13,"") -> COES | G13: =+Q13 -> 9.964 | H13: =+R13 -> 9.964 | I13: =+S13 -> 48.092614 | M13: C.H. HUASAHUASI II | N13: PRIMERA | O13: COES | P13: Agua | Q13: 9.964 | R13: 9.964 | S13: 48.092614
B14: =IF(L14<>"",L14,"") | C14: =IF(M14<>"",M14,"") -> C.H. RUNATULLO II | D14: =IF(N14<>"",N14,"") -> TERCERA | E14: =IF(O14<>"",O14,"") -> COES | G14: =+Q14 -> 19.968 | H14: =+R14 -> 19.968 | I14: =+S14 -> 96.77889 | M14: C.H. RUNATULLO II | N14: TERCERA | O14: COES | P14: Agua | Q14: 19.968 | R14: 19.968 | S14: 96.77889
B15: =IF(L15<>"",L15,"") | C15: =IF(M15<>"",M15,"") -> C.H. RUNATULLO III | D15: =IF(N15<>"",N15,"") -> SEGUNDA | E15: =IF(O15<>"",O15,"") -> COES | G15: =+Q15 -> 19.966 | H15: =+R15 -> 19.966 | I15: =+S15 -> 109.73273 | M15: C.H. RUNATULLO III | N15: SEGUNDA | O15: COES | P15: Agua | Q15: 19.966 | R15: 19.966 | S15: 109.73273
B16: =IF(L16<>"",L16,"") | C16: =IF(M16<>"",M16,"") -> C.H. SANTA CRUZ I | D16: =IF(N16<>"",N16,"") -> PRIMERA | E16: =IF(O16<>"",O16,"") -> COES | G16: =+Q16 -> 6.636 | H16: =+R16 -> 6.636 | I16: =+S16 -> 37.481772 | M16: C.H. SANTA CRUZ I | N16: PRIMERA | O16: COES | P16: Agua | Q16: 6.636 | R16: 6.636 | S16: 37.481772
B17: =IF(L17<>"",L17,"") | C17: =IF(M17<>"",M17,"") -> C.H. SANTA CRUZ II | D17: =IF(N17<>"",N17,"") -> PRIMERA | E17: =IF(O17<>"",O17,"") -> COES | G17: =+Q17 -> 6.502 | H17: =+R17 -> 6.502 | I17: =+S17 -> 39.230236 | M17: C.H. SANTA CRUZ II | N17: PRIMERA | O17: COES | P17: Agua | Q17: 6.502 | R17: 6.502 | S17: 39.230236
B18: =IF(L18<>"",L18,"") -> Empresa de Generación Eléctrica Rio Baños S.A.C. | C18: =IF(M18<>"",M18,"") -> C.H. RUCUY | D18: =IF(N18<>"",N18,"") -> CUARTA | E18: =IF(O18<>"",O18,"") -> COES | G18: =+Q18 -> 20 | H18: =+R18 -> 20 | I18: =+S18 -> 132.80746 | L18: Empresa de Generación Eléctrica Rio Baños S.A.C. | M18: C.H. RUCUY | N18: CUARTA | O18: COES | P18: Agua | Q18: 20 | R18: 20 | S18: 132.80746
B19: =IF(L19<>"",L19,"") -> Empresa de Generación Eléctrica Santa Ana S.R.L. | C19: =IF(M19<>"",M19,"") -> C.H. RENOVANDES | D19: =IF(N19<>"",N19,"") -> SEGUNDA | E19: =IF(O19<>"",O19,"") -> COES | G19: =+Q19 -> 20.862 | H19: =+R19 -> 20.862 | I19: =+S19 -> 163.10162 | L19: Empresa de Generación Eléctrica Santa Ana S.R.L. | M19: C.H. RENOVANDES | N19: SEGUNDA | O19: COES | P19: Agua | Q19: 20.862 | R19: 20.862 | S19: 163.10162
B20: =IF(L20<>"",L20,"") -> Empresa Eléctrica Agua Azul S.A. | C20: =IF(M20<>"",M20,"") -> C.H. POTRERO | D20: =IF(N20<>"",N20,"") -> TERCERA | E20: =IF(O20<>"",O20,"") -> COES | G20: =+Q20 -> 19.9 | H20: =+R20 -> 19.9 | I20: =+S20 -> 97.253144 | L20: Empresa Eléctrica Agua Azul S.A. | M20: C.H. POTRERO | N20: TERCERA | O20: COES | P20: Agua | Q20: 19.9 | R20: 19.9 | S20: 97.253144
B21: =IF(L21<>"",L21,"") -> Empresa Eléctrica Rio Doble S.A. | C21: =IF(M21<>"",M21,"") -> C.H. LAS PIZARRAS | D21: =IF(N21<>"",N21,"") -> PRIMERA | E21: =IF(O21<>"",O21,"") -> COES | G21: =+Q21 -> 20 | H21: =+R21 -> 19.19 | I21: =+S21 -> 85.293915 | L21: Empresa Eléctrica Rio Doble S.A. | M21: C.H. LAS PIZARRAS | N21: PRIMERA | O21: COES | P21: Agua | Q21: 20 | R21: 19.19 | S21: 85.293915
B22: =IF(L22<>"",L22,"") -> Generación Andina S.A.C. | C22: =IF(M22<>"",M22,"") -> C.H. 8 DE AGOSTO | D22: =IF(N22<>"",N22,"") -> SEGUNDA | E22: =IF(O22<>"",O22,"") -> COES | G22: =+Q22+Q39 -> 21.28 | H22: =+R22+R39 -> 21.28 | I22: =+S22+S39 -> 110.6015 | L22: Generación Andina S.A.C. | M22: C.H. 8 DE AGOSTO | N22: SEGUNDA | O22: COES | P22: Agua | Q22: 21.28 | R22: 21.28 | S22: 108.20387
B23: =IF(L23<>"",L23,"") | C23: =IF(M23<>"",M23,"") -> C.H. EL CARMEN | D23: =IF(N23<>"",N23,"") -> SEGUNDA | E23: =IF(O23<>"",O23,"") -> COES | G23: =+Q23 -> 8.4 | H23: =+R23 -> 8.4 | I23: =+S23 -> 43.202421 | M23: C.H. EL CARMEN | N23: SEGUNDA | O23: COES | P23: Agua | Q23: 8.4 | R23: 8.4 | S23: 43.202421
B24: =IF(L24<>"",L24,"") -> Generadora de Energía del Perú S.A. | C24: =IF(M24<>"",M24,"") -> C.H. LA JOYA | D24: =IF(N24<>"",N24,"") -> PRIMERA | E24: =IF(O24<>"",O24,"") -> COES | G24: =+Q24 -> 10.4 | H24: =+R24 -> 10.2 | I24: =+S24 -> 48.995694 | L24: Generadora de Energía del Perú S.A. | M24: C.H. LA JOYA | N24: PRIMERA | O24: COES | P24: Agua | Q24: 10.4 | R24: 10.2 | S24: 48.995694
B25: =IF(L25<>"",L25,"") | C25: =IF(M25<>"",M25,"") -> C.H. ANGEL I | D25: =IF(N25<>"",N25,"") -> PRIMERA | E25: =IF(O25<>"",O25,"") -> COES | G25: =+Q25 -> 20 | H25: =+R25 -> 20.05 | I25: =+S25 -> 99.472449 | M25: C.H. ANGEL I | N25: PRIMERA | O25: COES | P25: Agua | Q25: 20 | R25: 20.05 | S25: 99.472449
B26: =IF(L26<>"",L26,"") | C26: =IF(M26<>"",M26,"") -> C.H. ANGEL II | D26: =IF(N26<>"",N26,"") -> PRIMERA | E26: =IF(O26<>"",O26,"") -> COES | G26: =+Q26 -> 20 | H26: =+R26 -> 19.99 | I26: =+S26 -> 105.62399 | M26: C.H. ANGEL II | N26: PRIMERA | O26: COES | P26: Agua | Q26: 20 | R26: 19.99 | S26: 105.62399
B27: =IF(L27<>"",L27,"") | C27: =IF(M27<>"",M27,"") -> C.H. ANGEL III | D27: =IF(N27<>"",N27,"") -> PRIMERA | E27: =IF(O27<>"",O27,"") -> COES | G27: =+Q27 -> 20 | H27: =+R27 -> 20.08 | I27: =+S27 -> 104.57288 | M27: C.H. ANGEL III | N27: PRIMERA | O27: COES | P27: Agua | Q27: 20 | R27: 20.08 | S27: 104.57288
B28: =IF(L28<>"",L28,"") -> Hidrocañete S.A. | C28: =IF(M28<>"",M28,"") -> C.H. NUEVO IMPERIAL | D28: =IF(N28<>"",N28,"") -> PRIMERA | E28: =IF(O28<>"",O28,"") -> COES | G28: =+Q28 -> 3.97 | H28: =+R28 -> 3.97 | I28: =+S28 -> 27.9163 | L28: Hidrocañete S.A. | M28: C.H. NUEVO IMPERIAL | N28: PRIMERA | O28: COES | P28: Agua | Q28: 3.97 | R28: 3.97 | S28: 27.9163
B29: =IF(L29<>"",L29,"") -> Hidroeléctrica Huanchor S.A.C. | C29: =IF(M29<>"",M29,"") -> C.H. HUANCHOR | D29: =IF(N29<>"",N29,"") -> - | E29: =IF(O29<>"",O29,"") -> COES | G29: =+Q29 -> 20 | H29: =+R29 -> 19.768 | I29: =+S29 -> 157.45968 | L29: Hidroeléctrica Huanchor S.A.C. | M29: C.H. HUANCHOR | N29: - | O29: COES | P29: Agua | Q29: 20 | R29: 19.768 | S29: 157.45968
B30: =IF(L30<>"",L30,"") -> Huaura Power Group S.A. | C30: =IF(M30<>"",M30,"") -> C.H. YARUCAYA | D30: =IF(N30<>"",N30,"") -> TERCERA | E30: =IF(O30<>"",O30,"") -> COES | G30: =+Q30 -> 19.2 | H30: =+R30 -> 18.43 | I30: =+S30 -> 137.5036 | L30: Huaura Power Group S.A. | M30: C.H. YARUCAYA | N30: TERCERA | O30: COES | P30: Agua | Q30: 19.2 | R30: 18.43 | S30: 137.5036
B31: =IF(L31<>"",L31,"") -> Maja Energía S.A.C. | C31: =IF(M31<>"",M31,"") -> C.H. RONCADOR | D31: =IF(N31<>"",N31,"") -> PRIMERA | E31: =IF(O31<>"",O31,"") -> COES | G31: =+Q31 -> 3.8 | H31: =+R31 -> 3.684 | I31: =+S31 -> 23.799409 | L31: Maja Energía S.A.C. | M31: C.H. RONCADOR | N31: PRIMERA | O31: COES | P31: Agua | Q31: 3.8 | R31: 3.684 | S31: 23.799409
B32: =IF(L32<>"",L32,"") -> Orazul Energy Perú S.A. | C32: =IF(M32<>"",M32,"") -> C.H. CAÑA BRAVA | D32: =IF(N32<>"",N32,"") -> PRIMERA | E32: =IF(O32<>"",O32,"") -> COES | G32: =+Q32 -> 6 | H32: =+R32 -> 5.67 | I32: =+S32 -> 27.989162 | L32: Orazul Energy Perú S.A. | M32: C.H. CAÑA BRAVA | N32: PRIMERA | O32: COES | P32: Agua | Q32: 6 | R32: 5.67 | S32: 27.989162
B33: =IF(L33<>"",L33,"") | C33: =IF(M33<>"",M33,"") -> C.H. CARHUAQUERO IV | D33: =IF(N33<>"",N33,"") -> PRIMERA | E33: =IF(O33<>"",O33,"") -> COES | G33: =+Q33 -> 10 | H33: =+R33 -> 9.983 | I33: =+S33 -> 71.382055 | M33: C.H. CARHUAQUERO IV | N33: PRIMERA | O33: COES | P33: Agua | Q33: 10 | R33: 9.983 | S33: 71.382055
B34: =IF(L34<>"",L34,"") -> Orygen Perú S.A.A. | C34: =IF(M34<>"",M34,"") -> C.H. HER 1 | D34: =IF(N34<>"",N34,"") -> CUARTA | E34: =IF(O34<>"",O34,"") -> COES | G34: =+Q34 -> 0.7 | H34: =+R34 -> 0.678 | I34: =+S34 -> 2.267619 | L34: Orygen Perú S.A.A. | M34: C.H. HER 1 | N34: CUARTA | O34: COES | P34: Agua | Q34: 0.7 | R34: 0.678 | S34: 2.267619
B35: =IF(L35<>"",L35,"") -> Peruana de Inversiones en Energía Renovables S.A. | C35: =IF(M35<>"",M35,"") -> C.H. MANTA I | D35: =IF(N35<>"",N35,"") -> SEGUNDA | E35: =IF(O35<>"",O35,"") -> COES | G35: =+Q35 -> 20.828 | H35: =+R35 -> 20.763 | I35: =+S35 -> 90.910986 | L35: Peruana de Inversiones en Energía Renovables S.A. | M35: C.H. MANTA I | N35: SEGUNDA | O35: COES | P35: Agua | Q35: 20.828 | R35: 20.763 | S35: 90.910986
B36: =IF(L36<>"",L36,"") -> Sindicato Energético S.A. | C36: =IF(M36<>"",M36,"") -> C.H. CHANCAY | D36: =IF(N36<>"",N36,"") -> PRIMERA | E36: =IF(O36<>"",O36,"") -> COES | G36: =+Q36 -> 20 | H36: =+R36 -> 20 | I36: =+S36 -> 161.09749 | L36: Sindicato Energético S.A. | M36: C.H. CHANCAY | N36: PRIMERA | O36: COES | P36: Agua | Q36: 20 | R36: 20 | S36: 161.09749
B37: =IF(L37<>"",L37,"") | C37: =IF(M37<>"",M37,"") -> C.H. POECHOS I | D37: =IF(N37<>"",N37,"") -> - | E37: =IF(O37<>"",O37,"") -> NO COES | G37: =+Q37 -> 16.4 | H37: =+R37 -> 16 | I37: =+S37 -> 58.4079 | M37: C.H. POECHOS I | N37: - | O37: NO COES | P37: Agua | Q37: 16.4 | R37: 16 | S37: 58.4079
B38: =IF(L38<>"",L38,"") | C38: =IF(M38<>"",M38,"") -> C.H. POECHOS II | D38: =IF(N38<>"",N38,"") -> PRIMERA | E38: =IF(O38<>"",O38,"") -> COES | G38: =+Q38 -> 10.2 | H38: =+R38 -> 10 | I38: =+S38 -> 41.524 | M38: C.H. POECHOS II | N38: PRIMERA | O38: COES | P38: Agua | Q38: 10.2 | R38: 10 | S38: 41.524
B39: Subtotal Hidráulicas RER | G39: =SUM(G6:G35) -> 385.257 | H39: =SUM(H6:H35) -> 382.451 | I39: =SUM(I6:I35) -> 2177.6824 | L39: Enel Generación Perú S.A.A. | M39: C.H. HER 1 | N39: CUARTA | O39: COES | P39: Agua | Q39: 0 | R39: 0 | S39: 2.397626
K40: Total Hidráulico | Q40: 431.857 | R40: 428.451 | S40: 2438.7118
B41: Biomasa y Biogas | K41: Térmico | L41: Agro Industrial Paramonga S.A.A. | M41: C.T. PARAMONGA | N41: PRIMERA | O41: COES | P41: Bagazo | Q41: 23 | R41: 14.733 | S41: 116.0846
B42: =IF(L41<>"",L41,"") -> Agro Industrial Paramonga S.A.A. | C42: =IF(M41<>"",M41,"") -> C.T. PARAMONGA | D42: =IF(N41<>"",N41,"") -> PRIMERA | E42: =IF(O41<>"",O41,"") -> COES | F42: =IF(P41<>"",P41,"") -> Bagazo | G42: =IF(Q41<>"",Q41,"") -> 23 | H42: =IF(R41<>"",R41,"") -> 14.733 | I42: =IF(S41<>"",S41,"") -> 116.0846 | L42: Agroaurora S.A.C. | M42: C.T. AGROAURORA | N42: - | O42: COES | P42: Bagazo | Q42: 37.5 | R42: 20.389 | S42: 59.476196
B43: =IF(L42<>"",L42,"") -> Agroaurora S.A.C. | C43: =IF(M42<>"",M42,"") -> C.T. AGROAURORA | D43: =IF(N42<>"",N42,"") -> - | E43: =IF(O42<>"",O42,"") -> COES | F43: =IF(P42<>"",P42,"") -> Bagazo | G43: =IF(Q42<>"",Q42,"") -> 37.5 | H43: =IF(R42<>"",R42,"") -> 20.389 | I43: =IF(S42<>"",S42,"") -> 59.476196 | L43: Agroindustrias San Jacinto S.A.A. | M43: C.T. SAN JACINTO | N43: - | O43: COES | P43: Bagazo | Q43: 21.71 | R43: 8.15 | S43: 50.674052
B44: =IF(L43<>"",L43,"") -> Agroindustrias San Jacinto S.A.A. | C44: =IF(M43<>"",M43,"") -> C.T. SAN JACINTO | D44: =IF(N43<>"",N43,"") -> - | E44: =IF(O43<>"",O43,"") -> COES | F44: =IF(P43<>"",P43,"") -> Bagazo | G44: =IF(Q43<>"",Q43,"") -> 21.71 | H44: =IF(R43<>"",R43,"") -> 8.15 | I44: =IF(S43<>"",S43,"") -> 50.674052 | L44: Bioenergía del Chira S.A. | M44: C.T. CAÑA BRAVA | N44: - | O44: COES | P44: Bagazo | Q44: 14 | R44: 14 | S44: 76.136758
B45: =IF(L44<>"",L44,"") -> Bioenergía del Chira S.A. | C45: =IF(M44<>"",M44,"") -> C.T. CAÑA BRAVA | D45: =IF(N44<>"",N44,"") -> - | E45: =IF(O44<>"",O44,"") -> COES | F45: =IF(P44<>"",P44,"") -> Bagazo | G45: =IF(Q44<>"",Q44,"") -> 14 | H45: =IF(R44<>"",R44,"") -> 14 | I45: =IF(S44<>"",S44,"") -> 76.136758 | L45: Petramas S.A.C. | M45: C.T. CALLAO | N45: CUARTA | O45: COES | P45: Biogas | Q45: 2.4 | R45: 1.957 | S45: 14.862424
B46: =IF(L45<>"",L45,"") -> Petramas S.A.C. | C46: =IF(M45<>"",M45,"") -> C.T. CALLAO | D46: =IF(N45<>"",N45,"") -> CUARTA | E46: =IF(O45<>"",O45,"") -> COES | F46: =IF(P45<>"",P45,"") -> Biogas | G46: =IF(Q45<>"",Q45,"") -> 2.4 | H46: =IF(R45<>"",R45,"") -> 1.957 | I46: =IF(S45<>"",S45,"") -> 14.862424 | M46: C.T. HUAYCOLORO | N46: PRIMERA | O46: COES | P46: Biogas | Q46: 4.8 | R46: 4.453 | S46: 30.473456
B47: =IF(L46<>"",L46,"") | C47: =IF(M46<>"",M46,"") -> C.T. HUAYCOLORO | D47: =IF(N46<>"",N46,"") -> PRIMERA | E47: =IF(O46<>"",O46,"") -> COES | F47: =IF(P46<>"",P46,"") -> Biogas | G47: =IF(Q46<>"",Q46,"") -> 4.8 | H47: =IF(R46<>"",R46,"") -> 4.453 | I47: =IF(S46<>"",S46,"") -> 30.473456 | M47: C.T. LA GRINGA V | N47: SEGUNDA | O47: COES | P47: Biogas | Q47: 3.2 | R47: 2.917 | S47: 14.362917
B48: =IF(L47<>"",L47,"") | C48: =IF(M47<>"",M47,"") -> C.T. LA GRINGA V | D48: =IF(N47<>"",N47,"") -> SEGUNDA | E48: =IF(O47<>"",O47,"") -> COES | F48: =IF(P47<>"",P47,"") -> Biogas | G48: =IF(Q47<>"",Q47,"") -> 3.2 | H48: =IF(R47<>"",R47,"") -> 2.917 | I48: =IF(S47<>"",S47,"") -> 14.362917 | M48: C.T. DOÑA CATALINA | N48: CUARTA | O48: COES | P48: Biogas | Q48: 2.4 | R48: 1.928 | S48: 12.718795
B49: =IF(L48<>"",L48,"") | C49: =IF(M48<>"",M48,"") -> C.T. DOÑA CATALINA | D49: =IF(N48<>"",N48,"") -> CUARTA | E49: =IF(O48<>"",O48,"") -> COES | F49: =IF(P48<>"",P48,"") -> Biogas | G49: =IF(Q48<>"",Q48,"") -> 2.4 | H49: =IF(R48<>"",R48,"") -> 1.928 | I49: =IF(S48<>"",S48,"") -> 12.718795 | K49: Total Térmico | Q49: 109.01 | R49: 68.527 | S49: 374.7892
B50: Subtotal Biomasa y Biogas | G50: =SUM(G42:G49) -> 109.01 | H50: =SUM(H42:H49) -> 68.527 | I50: =SUM(I42:I49) -> 374.7892 | K50: Solar | L50: Amazonas Energía Solar S.A.C. | M50: C.S.F. SAN LORENZO | N50: 0 | O50: NO COES | P50: Radiación solar | Q50: 2.89 | R50: 2.89 | S50: 2.518078
M51: C.S.F. REQUENA | N51: 0 | O51: NO COES | P51: Radiación solar | Q51: 7.5 | R51: 7.5 | S51: 2.25283
B52: Solares | M52: C.S.F TAMSHIYACU | N52: 0 | O52: NO COES | P52: Radiación solar | Q52: 2.1 | R52: 2.1 | S52: 0.404223
B53: =IF(L50<>"",L50,"") -> Amazonas Energía Solar S.A.C. | C53: =IF(M50<>"",M50,"") -> C.S.F. SAN LORENZO | D53: - | E53: =IF(O50<>"",O50,"") -> NO COES | G53: =IF(Q50<>"",Q50,"") -> 2.89 | H53: =IF(R50<>"",R50,"") -> 2.89 | I53: =IF(S50<>"",S50,"") -> 2.518078 | L53: Colca Solar S.A.C. | M53: C.S. YARUCAYA | N53: TERCERA | O53: COES | P53: Radiación solar | Q53: 1.2 | R53: 0.012 | S53: 2.687075
B54: =IF(L51<>"",L51,"") | C54: =IF(M51<>"",M51,"") -> C.S.F. REQUENA | D54: - | E54: =IF(O51<>"",O51,"") -> NO COES | G54: =IF(Q51<>"",Q51,"") -> 7.5 | H54: =IF(R51<>"",R51,"") -> 7.5 | I54: =IF(S51<>"",S51,"") -> 2.25283 | L54: ENGIE EnergÍa Perú S.A. | M54: C.S. INTIPAMPA | N54: CUARTA | O54: COES | P54: Radiación solar | Q54: 44.541 | R54: 44.541 | S54: 111.35657
B55: =IF(L52<>"",L52,"") | C55: =IF(M52<>"",M52,"") -> C.S.F TAMSHIYACU | D55: - | E55: =IF(O52<>"",O52,"") -> NO COES | G55: =IF(Q52<>"",Q52,"") -> 2.1 | H55: =IF(R52<>"",R52,"") -> 2.1 | I55: =IF(S52<>"",S52,"") -> 0.404223 | L55: GR Cortarrama S.A.C. | M55: C.S. MATARANI | N55: 0 | O55: COES | P55: Radiación solar | Q55: 80 | R55: 80 | S55: 104.7905
B56: =IF(L53<>"",L53,"") -> Colca Solar S.A.C. | C56: =IF(M53<>"",M53,"") -> C.S. YARUCAYA | D56: =IF(N53<>"",N53,"") -> TERCERA | E56: =IF(O53<>"",O53,"") -> COES | G56: =IF(Q53<>"",Q53,"") -> 1.2 | H56: =IF(R53<>"",R53,"") -> 0.012 | I56: =IF(S53<>"",S53,"") -> 2.687075 | L56: Majes Arcus S.A.C. | M56: C.S. MAJES | N56: PRIMERA | O56: COES | P56: Radiación solar | Q56: 20 | R56: 20 | S56: 45.821268
B57: =IF(L54<>"",L54,"") -> ENGIE EnergÍa Perú S.A. | C57: =IF(M54<>"",M54,"") -> C.S. INTIPAMPA | D57: =IF(N54<>"",N54,"") -> CUARTA | E57: =IF(O54<>"",O54,"") -> COES | G57: =IF(Q54<>"",Q54,"") -> 44.541 | H57: =IF(R54<>"",R54,"") -> 44.541 | I57: =IF(S54<>"",S54,"") -> 111.35657 | L57: Moquegua FV S.A.C. | M57: C.S. MOQUEGUA FV | N57: SEGUNDA | O57: COES | P57: Radiación solar | Q57: 16 | R57: 16 | S57: 46.940327
B58: =IF(L55<>"",L55,"") -> GR Cortarrama S.A.C. | C58: =IF(M55<>"",M55,"") -> C.S. MATARANI | D58: - | E58: =IF(O55<>"",O55,"") -> COES | G58: =IF(Q55<>"",Q55,"") -> 80 | H58: =IF(R55<>"",R55,"") -> 80 | I58: =IF(S55<>"",S55,"") -> 104.7905 | L58: Orygen Perú S.A.A. | M58: C.S. RUBI | N58: CUARTA | O58: COES | P58: Radiación solar | Q58: 144.484 | R58: 144.484 | S58: 209.54204
B59: =IF(L56<>"",L56,"") -> Majes Arcus S.A.C. | C59: =IF(M56<>"",M56,"") -> C.S. MAJES | D59: =IF(N56<>"",N56,"") -> PRIMERA | E59: =IF(O56<>"",O56,"") -> COES | G59: =IF(Q56<>"",Q56,"") -> 20 | H59: =IF(R56<>"",R56,"") -> 20 | I59: =IF(S56<>"",S56,"") -> 45.821268 | M59: C.S. CLEMESI | N59: 0 | O59: COES | P59: Radiación solar | Q59: 114.931 | R59: 114.931 | S59: 158.19398
B60: =IF(L57<>"",L57,"") -> Moquegua FV S.A.C. | C60: =IF(M57<>"",M57,"") -> C.S. MOQUEGUA FV | D60: =IF(N57<>"",N57,"") -> SEGUNDA | E60: =IF(O57<>"",O57,"") -> COES | G60: =IF(Q57<>"",Q57,"") -> 16 | H60: =IF(R57<>"",R57,"") -> 16 | I60: =IF(S57<>"",S57,"") -> 46.940327 | L60: Panamericana Solar S.A.C. | M60: C.S. PANAMERICANA SOLAR | N60: PRIMERA | O60: COES | P60: Radiación solar | Q60: 20 | R60: 20 | S60: 57.413202
B61: =IF(L58<>"",L58,"") -> Orygen Perú S.A.A. | C61: =IF(M58<>"",M58,"") -> C.S. RUBI | D61: =IF(N58<>"",N58,"") -> CUARTA | E61: =IF(O58<>"",O58,"") -> COES | G61: =IF(Q58<>"",Q58,"") -> 144.484 | H61: =IF(R58<>"",R58,"") -> 144.484 | I61: =+S58+S63 -> 455.0121 | L61: Repartición Arcus S.A.C. | M61: C.S. REPARTICION | N61: PRIMERA | O61: COES | P61: Radiación solar | Q61: 20 | R61: 20 | S61: 44.849501
B62: =IF(L59<>"",L59,"") | C62: =IF(M59<>"",M59,"") -> C.S. CLEMESI | D62: - | E62: =IF(O59<>"",O59,"") -> COES | G62: =IF(Q59<>"",Q59,"") -> 114.931 | H62: =IF(R59<>"",R59,"") -> 114.931 | I62: =+S59+S64 -> 388.86648 | L62: Tacna Solar S.A.C. | M62: C.S. TACNA SOLAR | N62: PRIMERA | O62: COES | P62: Radiación solar | Q62: 20 | R62: 20 | S62: 52.700455
B63: =IF(L60<>"",L60,"") -> Panamericana Solar S.A.C. | C63: =IF(M60<>"",M60,"") -> C.S. PANAMERICANA SOLAR | D63: =IF(N60<>"",N60,"") -> PRIMERA | E63: =IF(O60<>"",O60,"") -> COES | G63: =IF(Q60<>"",Q60,"") -> 20 | H63: =IF(R60<>"",R60,"") -> 20 | I63: =IF(S60<>"",S60,"") -> 57.413202 | L63: Enel Generación Perú S.A.A. | M63: C.S. RUBI | N63: CUARTA | O63: COES | P63: Radiación solar | Q63: 0 | R63: 0 | S63: 245.47006
B64: =IF(L61<>"",L61,"") -> Repartición Arcus S.A.C. | C64: =IF(M61<>"",M61,"") -> C.S. REPARTICION | D64: =IF(N61<>"",N61,"") -> PRIMERA | E64: =IF(O61<>"",O61,"") -> COES | G64: =IF(Q61<>"",Q61,"") -> 20 | H64: =IF(R61<>"",R61,"") -> 20 | I64: =IF(S61<>"",S61,"") -> 44.849501 | M64: C.S. CLEMESI | N64: 0 | O64: COES | P64: Radiación solar | Q64: 0 | R64: 0 | S64: 230.6725
B65: =IF(L62<>"",L62,"") -> Tacna Solar S.A.C. | C65: =IF(M62<>"",M62,"") -> C.S. TACNA SOLAR | D65: =IF(N62<>"",N62,"") -> PRIMERA | E65: =IF(O62<>"",O62,"") -> COES | G65: =IF(Q62<>"",Q62,"") -> 20 | H65: =IF(R62<>"",R62,"") -> 20 | I65: =IF(S62<>"",S62,"") -> 52.700455 | K65: Total Solar | Q65: 493.646 | R65: 492.458 | S65: 1315.6126
B66: Subtotal Solares | G66: =SUM(G53:G65) -> 493.646 | H66: =SUM(H53:H65) -> 492.458 | I66: =SUM(I53:I65) -> 1315.6126 | K66: Eólico | L66: Energía Eólica S.A. | M66: C.E. CUPISNIQUE | N66: PRIMERA | O66: COES | P66: Viento | Q66: 80 | R66: 80 | S66: 332.69445
M68: C.E. TALARA | N68: PRIMERA | O68: COES | P68: Viento | Q68: 30 | R68: 30 | S68: 124.98379
B70: Eólicas | L70: Energía Renovable del Sur S.A. | M70: C.E. SAN JUAN | N70: 0 | O70: COES | P70: Viento | Q70: 135.7 | R70: 135.7 | S70: 614.92665
B71: =IF(L66<>"",L66,"") -> Energía Eólica S.A. | C71: =IF(M66<>"",M66,"") -> C.E. CUPISNIQUE | D71: =IF(N66<>"",N66,"") -> PRIMERA | E71: =IF(O66<>"",O66,"") -> COES | G71: =IF(Q66<>"",Q66,"") -> 80 | H71: =IF(R66<>"",R66,"") -> 80 | I71: =IF(S66<>"",S66,"") -> 332.69445 | L71: ENGIE EnergÍa Perú S.A. | M71: C.E. PUNTA LOMITAS | N71: 0 | O71: COES | P71: Viento | Q71: 294 | R71: 294 | S71: 1063.4885
B72: =IF(L68<>"",L68,"") | C72: =IF(M68<>"",M68,"") -> C.E. TALARA | D72: =IF(N68<>"",N68,"") -> PRIMERA | E72: =IF(O68<>"",O68,"") -> COES | G72: =IF(Q68<>"",Q68,"") -> 30 | H72: =IF(R68<>"",R68,"") -> 30 | I72: =IF(S68<>"",S68,"") -> 124.98379 | L72: GR Paino S.A.C. | M72: C.E. HUAMBOS | N72: CUARTA | O72: COES | P72: Viento | Q72: 18.37 | R72: 18.37 | S72: 65.644132
B73: =IF(L70<>"",L70,"") -> Energía Renovable del Sur S.A. | C73: =IF(M70<>"",M70,"") -> C.E. SAN JUAN | D73: - | E73: =IF(O70<>"",O70,"") -> COES | G73: =IF(Q70<>"",Q70,"") -> 135.7 | H73: =IF(R70<>"",R70,"") -> 135.7 | I73: =IF(S70<>"",S70,"") -> 614.92665 | L73: GR Taruca S.A.C. | M73: C.E. DUNA | N73: CUARTA | O73: COES | P73: Viento | Q73: 18.37 | R73: 18.37 | S73: 82.394667
B74: =IF(L71<>"",L71,"") -> ENGIE EnergÍa Perú S.A. | C74: =IF(M71<>"",M71,"") -> C.E. PUNTA LOMITAS | D74: - | E74: =IF(O71<>"",O71,"") -> COES | G74: =IF(Q71<>"",Q71,"") -> 294 | H74: =IF(R71<>"",R71,"") -> 294 | I74: =IF(S71<>"",S71,"") -> 1063.4885 | L74: Orygen Perú S.A.A. | M74: C.E. WAYRA | N74: CUARTA | O74: COES | P74: Viento | Q74: 132.3 | R74: 132.3 | S74: 250.33705
B75: =IF(L72<>"",L72,"") -> GR Paino S.A.C. | C75: =IF(M72<>"",M72,"") -> C.E. HUAMBOS | D75: =IF(N72<>"",N72,"") -> CUARTA | E75: =IF(O72<>"",O72,"") -> COES | G75: =IF(Q72<>"",Q72,"") -> 18.37 | H75: =IF(R72<>"",R72,"") -> 18.37 | I75: =IF(S72<>"",S72,"") -> 65.644132 | M75: C.E. WAYRA EXTENSIÓN | N75: 0 | O75: COES | P75: Viento | Q75: 177 | R75: 177 | S75: 247.64723
B76: =IF(L73<>"",L73,"") -> GR Taruca S.A.C. | C76: =IF(M73<>"",M73,"") -> C.E. DUNA | D76: =IF(N73<>"",N73,"") -> CUARTA | E76: =IF(O73<>"",O73,"") -> COES | G76: =IF(Q73<>"",Q73,"") -> 18.37 | H76: =IF(R73<>"",R73,"") -> 18.37 | I76: =IF(S73<>"",S73,"") -> 82.394667 | L76: Parque Eolico Marcona S.A.C. | M76: C.E. PARQUE EÓLICO MARCONA | N76: PRIMERA | O76: COES | P76: Viento | Q76: 32.1 | R76: 32.1 | S76: 162.58015
B77: =IF(L74<>"",L74,"") -> Orygen Perú S.A.A. | C77: =IF(M74<>"",M74,"") -> C.E. WAYRA | D77: =IF(N74<>"",N74,"") -> CUARTA | E77: =IF(O74<>"",O74,"") -> COES | G77: =IF(Q74<>"",Q74,"") -> 132.3 | H77: =IF(R74<>"",R74,"") -> 132.3 | I77: =+S74+S78 -> 509.82907 | L77: Parque Eolico Tres Hermanas S.A.C. | M77: C.E. TRES HERMANAS | N77: SEGUNDA | O77: COES | P77: Viento | Q77: 97.15 | R77: 97.15 | S77: 481.84308
B78: =IF(L75<>"",L75,"") | C78: =IF(M75<>"",M75,"") -> C.E. WAYRA EXTENSIÓN | D78: - | E78: =IF(O75<>"",O75,"") -> COES | G78: =IF(Q75<>"",Q75,"") -> 177 | H78: =IF(R75<>"",R75,"") -> 177 | I78: =+S75+S79 -> 426.34777 | L78: Enel Generación Perú S.A.A. | M78: C.E. WAYRA | N78: CUARTA | O78: COES | P78: Viento | Q78: 0 | R78: 0 | S78: 259.49202
B79: =IF(L76<>"",L76,"") -> Parque Eolico Marcona S.A.C. | C79: =IF(M76<>"",M76,"") -> C.E. PARQUE EÓLICO MARCONA | D79: =IF(N76<>"",N76,"") -> PRIMERA | E79: =IF(O76<>"",O76,"") -> COES | G79: =IF(Q76<>"",Q76,"") -> 32.1 | H79: =IF(R76<>"",R76,"") -> 32.1 | I79: =IF(S76<>"",S76,"") -> 162.58015 | M79: C.E. WAYRA EXTENSIÓN | N79: 0 | O79: COES | P79: Viento | Q79: 0 | R79: 0 | S79: 178.70055
B80: =IF(L77<>"",L77,"") -> Parque Eolico Tres Hermanas S.A.C. | C80: =IF(M77<>"",M77,"") -> C.E. TRES HERMANAS | D80: =IF(N77<>"",N77,"") -> SEGUNDA | E80: =IF(O77<>"",O77,"") -> COES | G80: =IF(Q77<>"",Q77,"") -> 97.15 | H80: =IF(R77<>"",R77,"") -> 97.15 | I80: =IF(S77<>"",S77,"") -> 481.84308 | K80: Total Eólico | Q80: 1014.99 | R80: 1014.99 | S80: 3864.7323
B81: Subtotal Eólicas | G81: =SUM(G71:G80) -> 1014.99 | H81: =SUM(H71:H80) -> 1014.99 | I81: =SUM(I71:I80) -> 3864.7323 | K81: Total general | Q81: 2049.503 | R81: 2004.426 | S81: 7993.8459
B83: Total RER | G83: =SUM(G39,G50,G66,G81) -> 2002.903 | H83: =SUM(H39,H50,H66,H81) -> 1958.426 | I83: =SUM(I39,I50,I66,I81) -> 7732.8165
B84: % del total nacional | G84: =+G83/'3.3.1 (PI)'!G13 -> 0.12116051 | H84: =+H83/'3.4.1 (PE)'!G14 -> 0.12533452 | I84: =+I83/'3.5.1'!G13 -> 0.12121374
B85: (*) Centrales que poseen concesión RER, de acuerdo al registro de la Dirección de Concesiones Eléctricas (DCE) de la DGE - MEM.

Sheet 3.2.3.1
A1: 3.2.3. Modificaciones en el parque generador | L1: Filtro | M1: Cambio de razon social | R1: Tipo de Mercado A | S1: MERCADO ELÉCTRICO
A2: 3.2.3.1. Modificaciones del parque generador para el mercado eléctrico | R2: Informa_A | S2: Informante
B3: A) Incremento y decremento de potencia instalada | L3: Empresa Anuario | M3: Central_A | N3: Nom Gru A | O3: Suma de Suma de PI 2024 OK | P3: Suma de Suma de PI 2023 OK | R3: FILTRO | S3: (en blanco)
B4: A.1) A nivel de empresas: | L4: Cogeneración Oquendo S.A.C. | M4: C.T. OQUENDO | N4: TG1 | O4: 0 | P4: 31
C5: Nuevos Ingresos de empresas | N5: TV1 | O5: 0 | P5: 5.42 | R5: Empresa Anuario | S5: Central_A | T5: Nom Gru A | U5: Estado de Grupo A | V5: Suma de PI 2023 OK | W5: Suma de PI 2024 OK | X5: Suma de Producción 2024 MW.h | Y5: Filtro
N6: TV2 | O6: 0 | P6: 2.52 | R6: Agro Industrial Paramonga S.A.A. | S6: C.T. PARAMONGA | T6: TV01 | U6: Operativo | V6: 23 | W6: 23 | X6: 116084.6 | Z6: 0
C7: Nº | D7: Nombre de la empresa | E7: Central | F7: Unidad / Grupo | G7: Tipo de Unididad/Grupo | H7: Potencia Instalada (MW) | I7: Desde | L7: Enel Distribución Perú S.A.A. | M7: C.H. ACOS | N7: FRANCIS Nº 1 | O7: 0 | P7: 0.14 | R7: Agroaurora S.A.C. | S7: C.T. AGROAURORA | T7: G1 | U7: Operativo | V7: 37.5 | W7: 37.5 | X7: 59476.196 | Z7: 0
C8: 1 | D8: Amazonas Energía Solar S.A.C. | E8: C.S.F. SAN LORENZO | F8: Total Central | G8: Solar Fotovoltaica | H8: 2.89 | I8: Enero | N8: FRANCIS Nº 2 | O8: 0 | P8: 0.14 | R8: Agroindustrias San Jacinto S.A.A. | S8: C.T. SAN JACINTO | T8: TV1 | U8: Operativo | V8: 21.71 | W8: 21.71 | X8: 50674.052 | Z8: 0
E9: C.S.F. REQUENA | F9: Total Central | G9: Solar Fotovoltaica | H9: 7.5 | I9: Agosto | M9: C.H. CANTA | N9: PELTON Nº 1 | O9: 0 | P9: 0.5 | R9: Amazonas Energía Solar S.A.C. | S9: C.S.F. SAN LORENZO | T9: Total Central | U9: Operativo | W9: 2.89 | X9: 2518.078 | Y9: Nueva empresa | Z9: 2.89
E10: C.S.F TAMSHIYACU | F10: Total Central | G10: Solar Fotovoltaica | H10: 2.1 | I10: Agosto | N10: PELTON Nº 2 | O10: 0 | P10: 0.5 | R10: Amazonas Energía Solar S.A.C. | S10: C.S.F. REQUENA | T10: Total Central | U10: Operativo | W10: 7.5 | X10: 2252.83 | Y10: Nueva empresa | Z10: 7.5
C11: 2 | D11: GR Cortarrama S.A.C. | E11: C.S. MATARANI | F11: Circuito 1 | G11: Solar Fotovoltaica | H11: 80 | I11: Julio | M11: C.H. NAVA | N11: Turgo Nº 1 | O11: 0 | P11: 0.25 | R11: Amazonas Energía Solar S.A.C. | S11: C.S.F TAMSHIYACU | T11: Total Central | U11: Operativo | W11: 2.1 | X11: 404.223 | Y11: Nueva empresa | Z11: 2.1
C12: 3 | D12: Kondu S.A.C. | E12: C.S. CARHUAQUERO | F12: Circuito unico | G12: Solar Fotovoltaica | H12: 0.565 | I12: Enero | N12: Turgo Nº 2 | O12: 0 | P12: 0.277 | R12: Andean Power S.A.C. | S12: C.H. CARHUAC | T12: G-01 | U12: Operativo | V12: 10 | W12: 10 | X12: 63689.342 | Z12: 0
M13: C.H. RAVIRA-PACARAOS | N13: FRANCIS 3 | O13: 0 | P13: 0.075 | R13: Andean Power S.A.C. | S13: C.H. CARHUAC | T13: G-02 | U13: Operativo | V13: 10 | W13: 10 | X13: 62830.022 | Z13: 0
C14: Total | H14: =+SUM(H8:H13) -> 93.055 | N14: FRANCIS 4 | O14: 0 | P14: 0.075 | R14: Asociación Santa Lucia de Chacas | S14: C.H. HUALLÍN I | T14: G1 | U14: Operativo | V14: 3 | W14: 3 | X14: 13838.081 | Z14: 0
N15: MODASA 515kW | O15: 0 | P15: 0.463 | R15: Bioenergía del Chira S.A. | S15: C.T. CAÑA BRAVA | T15: TM5000 | U15: Operativo | V15: 10 | W15: 10 | X15: 71793.858 | Z15: 0
C16: Retiro de empresas | N16: COMMINS C900 | O16: 0 | P16: 0.925 | R16: Bioenergía del Chira S.A. | S16: C.T. CAÑA BRAVA | T16: TMC5000 | U16: Operativo | V16: 4 | W16: 4 | X16: 4342.9 | Z16: 0
N17: COMMINS 925kW | O17: 0 | P17: 0.925 | R17: Celepsa Renovables S.R.L. | S17: C.H. MARAÑON | T17: FRANCIS 1 | U17: Operativo | V17: 6.62 | W17: 6.62 | X17: 48827.233 | Z17: 0
C18: Nº | D18: Nombre de la empresa | E18: Central | F18: Unidad / Grupo | G18: Tipo de Unididad/Grupo | H18: Potencia Instalada (MW) | I18: Desde | L18: Enel Generación Perú S.A.A. | M18: C.E. WAYRA | N18: Circuito 1 | O18: 0 | P18: 15.75 | R18: Celepsa Renovables S.R.L. | S18: C.H. MARAÑON | T18: FRANCIS 2 | U18: Operativo | V18: 6.62 | W18: 6.62 | X18: 31872.624 | Z18: 0
N19: Circuito 3 | O19: 0 | P19: 18.9 | R19: Central Hidroeléctrica de Langui S.A. | S19: C.H. LANGUI | T19: Grupo 1 | U19: Operativo | V19: 0.77 | W19: 0.77 | X19: 2105.038 | Z19: 0
C20: Total | H20: =SUM(H19:H19) -> 0 | N20: Circuito 4 | O20: 0 | P20: 18.9 | R20: Central Hidroeléctrica de Langui S.A. | S20: C.H. LANGUI | T20: Grupo 2 | U20: Operativo | V20: 2.5 | W20: 2.5 | X20: 7132.468 | Z20: 0
N21: Circuito 5 | O21: 0 | P21: 22.05 | R21: Central Hidroeléctrica de Langui S.A. | S21: C.H. LANGUI | T21: Grupo 3 | U21: Operativo | V21: 3.15 | W21: 3.15 | X21: 19767.233 | Z21: 0
B22: A.2) A nivel de centrales de generación: | N22: Circuito 6 | O22: 0 | P22: 15.75 | R22: Centrales Santa Rosa S.A.C. | S22: C.H. SANTA ROSA I | T22: G-1 | U22: Operativo | V22: 1.2 | W22: 1.2 | X22: 5984.336 | Z22: 0
N23: Circuito 7 | O23: 0 | P23: 22.05 | R23: Centrales Santa Rosa S.A.C. | S23: C.H. SANTA ROSA II | T23: G-1 | U23: Operativo | V23: 1.7 | W23: 1.7 | X23: 10507.474 | Z23: 0
C24: Nuevos Ingresos de centrales | M24: C.H. CALLAHUANCA | N24: GR-1 | O24: 0 | P24: 15.889 | R24: Chinango S.A.C | S24: C.H. CHIMAY | T24: GR-1 | U24: Operativo | V24: 76.5 | W24: 76.5 | X24: 415054.32 | Z24: 0
N25: GR-2 | O25: 0 | P25: 15.889 | R25: Chinango S.A.C | S25: C.H. CHIMAY | T25: GR-2 | U25: Operativo | V25: 76.5 | W25: 76.5 | X25: 355126.63 | Z25: 0
C26: Nº | D26: Nombre de la empresa | E26: Central | F26: Unidad / Grupo | G26: Tipo de Unididad/Grupo | H26: Potencia Instalada (MW) | I26: Desde | N26: GR-3 | O26: 0 | P26: 15.889 | R26: Chinango S.A.C | S26: C.H. YANANGO | T26: GR-1 | U26: Operativo | V26: 42.3 | W26: 42.3 | X26: 214731.44 | Z26: 0
C27: 1 | D27: Electro Dunas S.A.A. | E27: C.T. NASCA | F27: G1 | G27: EL | H27: 3.428 | I27: Octubre | N27: GR-4 | O27: 0 | P27: 34.97 | R27: Cía Hidroeléctrica San Hilarión S.A.C. | S27: C.H. SAN HILARION | T27: G1 | U27: Operativo | V27: 0.6 | W27: 0.6 | X27: 354.589 | Z27: 0
F28: G2 | G28: EL | H28: 3.428 | I28: Octubre | M28: C.H. HER 1 | N28: GR-1 | O28: 0 | P28: 0.35 | R28: Cogeneración Oquendo S.A.C. | S28: C.T. OQUENDO | T28: TG1 | U28: Operativo | V28: 31 | W28: 0 | X28: 1685.777 | Y28: Cambio de razon social | Z28: -31
F29: G3 | G29: EL | H29: 3.428 | I29: Octubre | N29: GR-2 | O29: 0 | P29: 0.35 | R29: Cogeneración Oquendo S.A.C. | S29: C.T. OQUENDO | T29: TV1 | U29: Operativo | V29: 5.42 | W29: 0 | X29: 7356.987 | Y29: Cambio de razon social | Z29: -5.42
C30: 2 | D30: Hidrandina S.A. | E30: C.T. DE EMERGENCIA CHAO | F30: Grupo 1-12 | G30: EL | H30: 17.88 | I30: Mayo | M30: C.H. HUAMPANÍ | N30: GR-1 | O30: 0 | P30: 15.7 | R30: Cogeneración Oquendo S.A.C. | S30: C.T. OQUENDO | T30: TV2 | U30: Operativo | V30: 2.52 | W30: 0 | X30: 1970.86 | Y30: Cambio de razon social | Z30: -2.52
N31: GR-2 | O31: 0 | P31: 15.7 | R31: Colca Solar S.A.C. | S31: C.S. YARUCAYA | T31: Circuito 1 | U31: Operativo | V31: 1.2 | W31: 1.2 | X31: 2687.075 | Z31: 0
C32: Total | H32: =+SUM(H27:H31) -> 28.164 | N32: Circuito 4 | O32: 0 | P32: 14.096 | R32: Electro Dunas S.A.A. | S32: C.H. LARAMATE | T32: DRESS 2 | U32: Operativo | V32: 0.11 | W32: 0.11 | X32: 722.271 | Z32: 0
C33: (*) Comenzó a informar al Minem. | N33: Circuito 5 | O33: 0 | P33: 14.096 | R33: Electro Dunas S.A.A. | S33: C.T. LUREN | T33: G1 | U33: Operativo | V33: 9.6 | W33: 9.6 | X33: 53677.028 | Z33: 0
N34: Circuito 6 | O34: 0 | P34: 14.096 | R34: Electro Dunas S.A.A. | S34: C.T. LUREN | T34: G2 | U34: Operativo | V34: 9.6 | W34: 9.6 | X34: 58065.345 | Z34: 0
C35: Retiro o baja de centrales | N35: Circuito 7 | O35: 0 | P35: 14.096 | R35: Electro Dunas S.A.A. | S35: C.T. EL PEDREGAL | T35: G1 | U35: Operativo | V35: 9.6 | W35: 9.6 | X35: 58763.376 | Z35: 0
N36: Circuito 8 | O36: 0 | P36: 14.096 | R36: Electro Dunas S.A.A. | S36: C.T. EL PEDREGAL | T36: G2 | U36: Operativo | V36: 9.6 | W36: 9.6 | X36: 58735.406 | Z36: 0
C37: Nº | D37: Nombre de la empresa | E37: Central | F37: Unidad / Grupo | G37: Tipo de Unididad/Grupo | H37: Potencia Instalada (MW) | I37: Desde | N37: Circuito 9 | O37: 0 | P37: 17.62 | R37: Electro Dunas S.A.A. | S37: C.T. NASCA | T37: G1 | U37: Operativo | V37: 0 | W37: 3.428 | X37: 5555.814 | Y37: Nueva central | Z37: 3.428
N38: TG-4 | O38: 0 | P38: 170 | R38: Electro Oriente S. A. | S38: C.H. CACLIC | T38: Turbina 4 | U38: Operativo | V38: 1.253 | W38: 1.253 | X38: 7100.294 | Z38: 0
C39: Total | H39: =SUM(H38:H38) -> 0 | N39: TV-7 | O39: 0 | P39: 184 | R39: Electro Oriente S. A. | S39: C.H. EL GERA | T39: Grupo 1 | U39: Operativo | V39: 3.3 | W39: 3.3 | X39: 14212.261 | Z39: 0
M40: C.S. CLEMESI | N40: Circuito 1 | O40: 0 | P40: 18.147 | R40: Electro Oriente S. A. | S40: C.H. EL GERA | T40: Grupo 2 | U40: Operativo | V40: 3.3 | W40: 3.3 | X40: 14601.392 | Z40: 0
B41: A.3) | C41: A nivel de unidades (grupos) de centrales de generación: | N41: Circuito 2 | O41: 0 | P41: 18.147 | R41: Electro Oriente S. A. | S41: C.H. EL GERA | T41: Grupo 3 | U41: Operativo | V41: 2.5 | W41: 2.5 | X41: 7380.348 | Z41: 0
N42: Circuito 3 | O42: 0 | P42: 18.147 | R42: Electro Oriente S. A. | S42: C.H. EL MUYO | T42: Turbina 1 | U42: Operativo | V42: 2.837 | W42: 2.837 | X42: 12494.958 | Z42: 0
C43: Nuevos ingresos de unidades / grupos | N43: Circuito 4 | O43: 0 | P43: 18.147 | R43: Electro Oriente S. A. | S43: C.H. EL MUYO | T43: Turbina 2 | U43: Operativo | V43: 2.837 | W43: 2.837 | X43: 12765.174 | Z43: 0
N44: Circuito 5 | O44: 0 | P44: 18.147 | R44: Electro Oriente S. A. | S44: C.H. LA PELOTA | T44: Turbina 1 | U44: Operativo | V44: 1.59 | W44: 1.59 | X44: 8174.568 | Z44: 0
C45: Nº | D45: Nombre de la empresa | E45: En la central: | F45: Unidad / Grupo | G45: Tipo de Unididad/Grupo | H45: Potencia Instalada (MW) | I45: Desde | N45: Circuito 6 | O45: 0 | P45: 12.098 | R45: Electro Oriente S. A. | S45: C.H. LA PELOTA | T45: Turbina 2 | U45: Operativo | V45: 1.59 | W45: 1.59 | X45: 10329.801 | Z45: 0
C46: 1 | D46: Electro Oriente S. A. | E46: C.T. CABALLOCOCHA | F46: Perkins 1 2800 | G46: EL | H46: 0.61 | N46: Circuito 7 | O46: 0 | P46: 12.098 | R46: Electro Oriente S. A. | S46: C.H. POMAHUACA | T46: T-1 | U46: Operativo | V46: 0.16 | W46: 0.16 | X46: 0 | Z46: 0
F47: Perkins 2 2800 | G47: EL | H47: 0.61 | M47: C.E. WAYRA EXTENSIÓN | N47: Circuito 1 | O47: 0 | P47: 11.8 | R47: Electro Oriente S. A. | S47: C.H. PUCARÁ | T47: T-1 | U47: Operativo | V47: 0.2 | W47: 0.2 | X47: 0 | Z47: 0
E48: C.T. CONTAMANA | F48: MITSUBISHI | G48: EL | H48: 0.89 | N48: Circuito 10 | O48: 0 | P48: 17.7 | R48: Electro Oriente S. A. | S48: C.H. PUCARÁ | T48: T-2 | U48: Operativo | V48: 0.2 | W48: 0.2 | X48: 1648.573 | Z48: 0
F49: Cat 09 3516 | G49: EL | H49: 1 | N49: Circuito 2 | O49: 0 | P49: 17.7 | R49: Electro Oriente S. A. | S49: C.H. QUANDA | T49: Turbina 1 | U49: Operativo | V49: 1.438 | W49: 1.438 | X49: 8256.44 | Z49: 0
E50: C.T. EL ESTRECHO | F50: Jolucava J0452 | G50: EL | H50: 0.45 | N50: Circuito 3 | O50: 0 | P50: 11.8 | R50: Electro Oriente S. A. | S50: C.H. QUANDA | T50: Turbina 2 | U50: Operativo | V50: 1.438 | W50: 1.438 | X50: 121.372 | Z50: 0
E51: C.T. INDIANA | F51: Jolucava J0451 | G51: EL | H51: 0.45 | N51: Circuito 4 | O51: 0 | P51: 17.7 | R51: Electro Oriente S. A. | S51: C.H. SHITARAYACU | T51: G1 | U51: Inoperativo | V51: 0.4 | W51: 0.4 | X51: 0 | Z51: 0
E52: C.T. LAGUNAS | F52: CAT 2 3512 <G4> | G52: EL | H52: 0.5 | N52: Circuito 5 | O52: 0 | P52: 17.7 | R52: Electro Oriente S. A. | S52: C.H. SHITARAYACU | T52: G2 | U52: Operativo | V52: 0.4 | W52: 0.4 | X52: 386.978 | Z52: 0
E53: C.T. NAUTA | F53: Volvo NV560 | G53: EL | H53: 0.604 | N53: Circuito 6 | O53: 0 | P53: 17.7 | R53: Electro Oriente S. A. | S53: C.H. TABACONAS | T53: Grupo 1 | U53: Operativo | V53: 0.06 | W53: 0.06 | X53: 0 | Z53: 0
F54: VolvoRVS615 | G54: EL | H54: 0.58 | N54: Circuito 7 | O54: 0 | P54: 11.8 | R54: Electro Oriente S. A. | S54: C.H. TABACONAS | T54: Grupo 2 | U54: Operativo | V54: 0.06 | W54: 0.06 | X54: 0 | Z54: 0
E55: C.T. REQUENA | F55: Volvo A 1250 | G55: EL | H55: 0.56 | N55: Circuito 8 | O55: 0 | P55: 17.7 | R55: Electro Oriente S. A. | S55: C.T. BAGUA GRANDE | T55: Cat-1_3512 | U55: Operativo | V55: 0.5 | W55: 0.5 | X55: 105.095 | Z55: 0
E56: C.T. YURIMAGUAS | F56: CUMMINS (G5) | G56: EL | H56: 1.5 | N56: Circuito 9 | O56: 0 | P56: 17.7 | R56: Electro Oriente S. A. | S56: C.T. BAGUA GRANDE | T56: Cat-2_3512 | U56: Operativo | V56: 0.5 | W56: 0.5 | X56: 47.163 | Z56: 0
E57: C.T. ISLANDIA | F57: VolvoP FFDL250GF | G57: EL | H57: 0.275 | N57: Circuito 11 | O57: 0 | P57: 17.7 | R57: Electro Oriente S. A. | S57: C.T. BAGUA GRANDE | T57: CAT3_3516 | U57: Operativo | V57: 2 | W57: 2 | X57: 695.04 | Z57: 0
C58: 2 | D58: Electronoroeste S. A. | E58: C.T. SECHURA | F58: SKODA 2 | G58: EL | H58: 1 | L58: Orygen Perú S.A.A. | M58: C.E. WAYRA | N58: Circuito 1 | O58: 15.75 | R58: Electro Oriente S. A. | S58: C.T. BAGUA GRANDE | T58: Detroit | U58: Operativo | V58: 0.45 | W58: 0.45 | X58: 5.226 | Z58: 0
C59: 3 | D59: Hidrandina S.A. | E59: C.T. CHIQUIÁN | F59: Grupo 4 | G59: EL | H59: 0.5 | N59: Circuito 2 | O59: 18.9 | R59: Electro Oriente S. A. | S59: C.T. BELLAVISTA | T59: EMD | U59: Operativo | V59: 2.5 | W59: 2.5 | X59: 0 | Z59: 0
N60: Circuito 3 | O60: 18.9 | R60: Electro Oriente S. A. | S60: C.T. CABALLOCOCHA | T60: Cat 2. 3512 Dita | U60: Operativo | V60: 0.5 | W60: 0 | X60: 0 | Y60: Retiro de grupo | Z60: -0.5
C61: Total | H61: =SUM(H46:H60) -> 9.529 | N61: Circuito 4 | O61: 18.9 | R61: Electro Oriente S. A. | S61: C.T. CABALLOCOCHA | T61: Cat. 3512 Dito | U61: Operativo | V61: 0.5 | W61: 0 | X61: 0 | Y61: Retiro de grupo | Z61: -0.5
N62: Circuito 6 | O62: 15.75 | R62: Electro Oriente S. A. | S62: C.T. CABALLOCOCHA | T62: AKSA1 Perk 8151G | U62: Operativo | V62: 0.681 | W62: 0.681 | X62: 2136.813 | Z62: 0
C63: Retiro o baja de grupos | N63: Circuito 7 | O63: 22.05 | R63: Electro Oriente S. A. | S63: C.T. CABALLOCOCHA | T63: AKSA2 Perk 8164G | U63: Operativo | V63: 0.681 | W63: 0.681 | X63: 159.726 | Z63: 0
M64: C.H. CALLAHUANCA | N64: GR-1 | O64: 15.889 | R64: Electro Oriente S. A. | S64: C.T. CABALLOCOCHA | T64: Perkins 1 2800 | U64: Operativo | W64: 0.61 | X64: 232.987 | Y64: Nuevo grupo | Z64: 0.61
C65: Nº | D65: Nombre de la empresa | E65: Central | F65: Unidad / Grupo | G65: Tipo de Unididad/Grupo | H65: Potencia Instalada (MW) | I65: Desde | N65: GR-2 | O65: 15.889 | R65: Electro Oriente S. A. | S65: C.T. CABALLOCOCHA | T65: Perkins 2 2800 | U65: Operativo | W65: 0.61 | X65: 530.922 | Y65: Nuevo grupo | Z65: 0.61
C66: 1 | D66: Electro Oriente S. A. | E66: C.T. CABALLOCOCHA | F66: Cat 2. 3512 Dita | G66: EL | H66: 0.5 | N66: GR-3 | O66: 15.889 | R66: Electro Oriente S. A. | S66: C.T. CABALLOCOCHA | T66: Perkins 2500 | U66: Operativo | V66: 0.49 | W66: 0 | X66: 407.101 | Y66: Retiro de grupo | Z66: -0.49
F67: Cat. 3512 Dito | G67: EL | H67: 0.5 | N67: GR-4 | O67: 34.97 | R67: Electro Oriente S. A. | S67: C.T. CABALLOCOCHA | T67: Caterpillar C27 | U67: Operativo | V67: 0.56 | W67: 0.56 | X67: 3008.557 | Z67: 0
F68: Perkins 2500 | G68: EL | H68: 0.49 | M68: C.H. HER 1 | N68: GR-1 | O68: 0.35 | R68: Electro Oriente S. A. | S68: C.T. CONTAMANA | T68: Cat.2.3512 Dita | U68: Operativo | V68: 0.5 | W68: 0.5 | X68: 349.84 | Z68: 0
E69: C.T. CONTAMANA | F69: Cat.5-C15-07183 | G69: EL | H69: 0.455 | N69: GR-2 | O69: 0.35 | R69: Electro Oriente S. A. | S69: C.T. CONTAMANA | T69: Cat.3512 Dita | U69: Operativo | V69: 0.5 | W69: 0.5 | X69: 458.326 | Z69: 0
E70: C.T. EL ESTRECHO | F70: Cat-1 3406 | G70: EL | H70: 0.275 | M70: C.H. HUAMPANÍ | N70: GR-1 | O70: 15.7 | R70: Electro Oriente S. A. | S70: C.T. CONTAMANA | T70: Cat.5-C15-07183 | U70: Operativo | V70: 0.455 | W70: 0 | X70: 0 | Y70: Retiro de grupo | Z70: -0.455
F71: Cat-2 3306 | G71: EL | H71: 0.225 | N71: GR-2 | O71: 15.7 | R71: Electro Oriente S. A. | S71: C.T. CONTAMANA | T71: MITSUBISHI | U71: Operativo | W71: 0.89 | X71: 1287.254 | Y71: Nuevo grupo | Z71: 0.89
E72: C.T. INDIANA | F72: Perkins 2506C | G72: EL | H72: 0.54 | M72: C.H. HUINCO | N72: GR-1 | O72: 64.6 | R72: Electro Oriente S. A. | S72: C.T. CONTAMANA | T72: Cat.6 3516B 0141 | U72: Operativo | V72: 2 | W72: 2 | X72: 1700.116 | Z72: 0
E73: C.T. NAUTA | F73: MTU-1 1200DS Detroi | G73: EL | H73: 1.225 | N73: GR-2 | O73: 64.6 | R73: Electro Oriente S. A. | S73: C.T. CONTAMANA | T73: Cat83516BJYA00139 | U73: Operativo | V73: 2 | W73: 2 | X73: 1434.205 | Z73: 0
F74: Cat C27 | G74: EL | H74: 1 | N74: GR-3 | O74: 64.6 | R74: Electro Oriente S. A. | S74: C.T. CONTAMANA | T74: Cat 09 3516 | U74: Operativo | W74: 1 | X74: 3236.148 | Y74: Nuevo grupo | Z74: 1
E75: C.T. YURIMAGUAS | F75: AGGREKO (G5) | G75: EL | H75: 4.4 | N75: GR-2 | O75: 60 | R75: Electro Oriente S. A. | S75: C.T. EL ESTRECHO | T75: Volvo 03 | U75: Operativo | V75: 0.364 | W75: 0.364 | X75: 33.027 | Z75: 0
E76: C.T. ISLANDIA | F76: Olympian OLY 1091 | G76: EL | H76: 0.132 | M76: C.H. MOYOPAMPA | N76: GR-1 | O76: 25.417 | R76: Electro Oriente S. A. | S76: C.T. EL ESTRECHO | T76: Volvo 350 | U76: Operativo | V76: 0.35 | W76: 0.35 | X76: 901.678 | Z76: 0
F77: Cat 3512 81Z19618 | G77: EL | H77: 0.25 | N77: GR-2 | O77: 25.417 | R77: Electro Oriente S. A. | S77: C.T. EL ESTRECHO | T77: Jolucava J0452 | U77: Operativo | W77: 0.45 | X77: 313.557 | Y77: Nuevo grupo | Z77: 0.45
C78: 2 | D78: Electronoroeste S. A. | E78: C.T. SECHURA | F78: CAT | G78: EL | H78: 0.32 | N78: GR-3 | O78: 24.58 | R78: Electro Oriente S. A. | S78: C.T. GRAN PERÚ | T78: OLYMPIAN | U78: Operativo | V78: 0.04 | W78: 0.04 | X78: 21.627 | Z78: 0
C80: Total | H80: =SUM(H66:H78) -> 10.312 | M80: C.S. RUBI | N80: Circuito 1 | O80: 14.096 | R80: Electro Oriente S. A. | S80: C.T. INDIANA | T80: Volvo Penta RVM364 | U80: Operativo | V80: 0.364 | W80: 0.364 | X80: 562.706 | Z80: 0
N81: Circuito 10 | O81: 14.096 | R81: Electro Oriente S. A. | S81: C.T. INDIANA | T81: VolvoPenta TWD1643G | U81: Operativo | V81: 0.6 | W81: 0.6 | X81: 266.725 | Z81: 0
B82: B) Modificación de Datos y Transferencias | N82: Circuito 2 | O82: 14.096 | R82: Electro Oriente S. A. | S82: C.T. INDIANA | T82: Vol.3 Pent TWD1643G | U82: Operativo | V82: 0.6 | W82: 0.6 | X82: 773.204 | Z82: 0
C83: Cambio de Razón Social de empresas y/o nombre de centrales | N83: Circuito 3 | O83: 14.096 | R83: Electro Oriente S. A. | S83: C.T. INDIANA | T83: Perkins 2506C | U83: Operativo | V83: 0.54 | W83: 0 | X83: 250.444 | Y83: Retiro de grupo | Z83: -0.54
B84: B.1) | N84: Circuito 4 | O84: 14.096 | R84: Electro Oriente S. A. | S84: C.T. INDIANA | T84: Perkins C18 | U84: Operativo | V84: 0.6 | W84: 0.6 | X84: 822.682 | Z84: 0
C85: Nº | D85: Razón Social Anterior | E85: Nueva Razón Social | F85: Central | G85: Unidad / Grupo | H85: Potencia Instalada (MW) | I85: Desde | N85: Circuito 5 | O85: 14.096 | R85: Electro Oriente S. A. | S85: C.T. INDIANA | T85: Jolucava J0451 | U85: Operativo | W85: 0.45 | X85: 313.918 | Y85: Nuevo grupo | Z85: 0.45
C86: 1 | D86: Enel Generación Perú S.A.A. | E86: Orygen Perú S.A.A. | F86: C.E. WAYRA | G86: Circuito 1 | H86: 15.75 | I86: Agosto | N86: Circuito 6 | O86: 14.096 | R86: Electro Oriente S. A. | S86: C.T. IQT. DIESEL - DIESEL | T86: Cat 3512 C | U86: Operativo | V86: 0.725 | W86: 0.725 | X86: 0 | Z86: 0
G87: Circuito 2 | H87: 18.9 | I87: Agosto | N87: Circuito 7 | O87: 14.096 | R87: Electro Oriente S. A. | S87: C.T. IQUITOS DIESEL WARTSILA | T87: CAT.1-16CM32C | U87: Inoperativo | V87: 7.518 | W87: 7.518 | X87: 0 | Z87: 0
G88: Circuito 3 | H88: 18.9 | I88: Agosto | N88: Circuito 8 | O88: 14.096 | R88: Electro Oriente S. A. | S88: C.T. IQUITOS DIESEL WARTSILA | T88: CAT.2-16CM32C | U88: Inoperativo | V88: 7.518 | W88: 7.518 | X88: 0 | Z88: 0
G89: Circuito 4 | H89: 18.9 | I89: Agosto | N89: Circuito 9 | O89: 17.62 | R89: Electro Oriente S. A. | S89: C.T. IQUITOS DIESEL WARTSILA | T89: CAT-16CM32 | U89: Operativo | V89: 7.4 | W89: 7.4 | X89: 9.242 | Z89: 0
G90: Circuito 5 | H90: 22.05 | I90: Agosto | M90: C.T. SANTA ROSA | N90: TG-2 | O90: 0 | R90: Electro Oriente S. A. | S90: C.T. IQUITOS DIESEL WARTSILA | T90: WARTSILA 1 | U90: Operativo | V90: 6.4 | W90: 6.4 | X90: 35.309 | Z90: 0
G91: Circuito 6 | H91: 15.75 | I91: Agosto | N91: TG-3 | O91: 0 | R91: Electro Oriente S. A. | S91: C.T. IQUITOS DIESEL WARTSILA | T91: WARTSILA 2 | U91: Operativo | V91: 6.4 | W91: 6.4 | X91: 0 | Z91: 0
G92: Circuito 7 | H92: 22.05 | I92: Agosto | N92: TG-4 | O92: 0 | R92: Electro Oriente S. A. | S92: C.T. IQUITOS DIESEL WARTSILA | T92: WARTSILA 3 | U92: Operativo | V92: 6.4 | W92: 6.4 | X92: 0 | Z92: 0
F93: C.H. CALLAHUANCA | G93: GR-1 | H93: 15.889 | I93: Agosto | N93: TG-5 | O93: 59.6 | R93: Electro Oriente S. A. | S93: C.T. IQUITOS DIESEL WARTSILA | T93: WARTSILA 4 | U93: Operativo | V93: 6.4 | W93: 6.4 | X93: 177.931 | Z93: 0
G94: GR-2 | H94: 15.889 | I94: Agosto | N94: TG-6 | O94: 59.6 | R94: Electro Oriente S. A. | S94: C.T. IQUITOS DIESEL WARTSILA | T94: WARTSILA 5 | U94: Operativo | V94: 8.1 | W94: 8.1 | X94: 2822.784 | Z94: 0
G95: GR-3 | H95: 15.889 | I95: Agosto | N95: TG-7 | O95: 127.5 | R95: Electro Oriente S. A. | S95: C.T. IQUITOS DIESEL WARTSILA | T95: WARTSILA 6 | U95: Operativo | V95: 8.1 | W95: 8.1 | X95: 8633.376 | Z95: 0
G96: GR-4 | H96: 34.97 | I96: Agosto | N96: TG-8 | O96: 200 | R96: Electro Oriente S. A. | S96: C.T. IQUITOS DIESEL WARTSILA | T96: WARTSILA 7 | U96: Operativo | V96: 8.1 | W96: 8.1 | X96: 6454.517 | Z96: 0
F97: C.H. HER 1 | G97: GR-1 | H97: 0.35 | I97: Agosto | M97: C.T. VENTANILLA | N97: TG-3 | O97: 170 | R97: Electro Oriente S. A. | S97: C.T. ISLA SANTA ROSA | T97: Cat.5-C15 7925 | U97: Operativo | V97: 0.43 | W97: 0.43 | X97: 714.879 | Z97: 0
G98: GR-2 | H98: 0.35 | I98: Agosto | N98: TG-4 | O98: 170 | R98: Electro Oriente S. A. | S98: C.T. ISLA SANTA ROSA | T98: Perkins 1800RPM | U98: Operativo | V98: 0.365 | W98: 0.365 | X98: 179.997 | Z98: 0
F99: C.H. HUAMPANÍ | G99: GR-1 | H99: 15.7 | I99: Agosto | N99: TV-7 | O99: 184 | R99: Electro Oriente S. A. | S99: C.T. JENARO HERRERA | T99: CUM.1 25450043 | U99: Operativo | V99: 0.324 | W99: 0.324 | X99: 117.725 | Z99: 0
G100: GR-2 | H100: 15.7 | I100: Agosto | M100: C.S. CLEMESI | N100: Circuito 1 | O100: 18.147 | R100: Electro Oriente S. A. | S100: C.T. JENARO HERRERA | T100: CUM.2 25449701 | U100: Operativo | V100: 0.324 | W100: 0.324 | X100: 161.43 | Z100: 0
F101: C.H. HUINCO | G101: GR-1 | H101: 64.6 | I101: Agosto | N101: Circuito 2 | O101: 18.147 | R101: Electro Oriente S. A. | S101: C.T. JENARO HERRERA | T101: CUM.3 25449964 | U101: Operativo | V101: 0.324 | W101: 0.324 | X101: 77.662 | Z101: 0
...

Sheet 3.2.3.2
A1: 3.2.3.2. Modificaciones del parque generador para uso propio | L1: Filtro | M1: Pasó a informantes | S1: Tipo de Mercado A | T1: USO PROPIO
B2: A) Incremento y decremento de potencia instalada | S2: Informa_A | T2: Informante
C3: A.1) A nivel de empresas: | L3: Empresa Anuario | M3: Central_A | N3: Nom Gru A | O3: Suma de Suma de PI 2024 OK | P3: Suma de Suma de PI 2023 OK | S3: FILTRO | T3: (en blanco)
D4: Nuevos Ingresos de empresas | L4: Cerámica Lima S.A. | M4: C.T. CELIMA 01 | N4: 0 | O4: 2.57
M5: C.T. CELIMA 02 | N5: 0 | O5: 1.09 | S5: Empresa Anuario | T5: Central_A | U5: Nom Gru A | V5: Estado de Grupo A | W5: Suma de PI 2023 OK | X5: Suma de PI 2024 OK | Y5: Suma de Producción 2024 GWh | Z5: Filtro
D6: Nº | E6: Nombre de la empresa | F6: Central | G6: Tipo de Unidad | H6: Potencia (MW) | I6: Desde | L6: Corporación Pesquera Inca S.A.C. | M6: C.T. COPEINCA CHANCAY | N6: 0 | O6: 2.35 | S6: Agroindustrial Laredo S.A.A. | T6: C.T. TURBO GENERADOR 1 | U6: 0 | V6: Operativo | W6: 1.25 | X6: 1.25 | Y6: 4e-05 | AA6: 0
D7: 1 | E7: Agrolmos S.A. | F7: C.T. AGROLMOS | G7: EL | H7: 29.8 | I7: Enero | M7: C.T. COPEINCA SUPE | N7: 0 | O7: 4.01 | S7: Agroindustrial Laredo S.A.A. | T7: C.T. TURBO GENERADOR 2 | U7: 0 | V7: Operativo | W7: 1.25 | X7: 1.25 | Y7: 0.001175 | AA7: 0
D8: 2 | E8: Aris Indsutrial S.A. | F8: C.T. ARIS LURIN | G8: EL | H8: 1.429 | I8: Enero | L8: Tecnológica de Alimentos S.A. | M8: C.T. CALLAO | N8: 0 | O8: 1.135 | S8: Agroindustrial Laredo S.A.A. | T8: C.T. TURBO GENERADOR 3 | U8: 0 | V8: Operativo | W8: 3 | X8: 3 | Y8: 0.00302 | AA8: 0
F9: C.T. ARIS LIMA | G9: EL | H9: 1.429 | I9: Enero | M9: C.T. MALABRIGO | N9: 0 | O9: 6.79 | S9: Agroindustrial Laredo S.A.A. | T9: C.T. TURBO GENERADOR 4 | U9: 0 | V9: Operativo | W9: 3 | X9: 3 | Y9: 0 | AA9: 0
D10: 3 | E10: Flesan Indutrial Power S.A.C | F10: C.T. INDUSTRIAS SAN MIGUEL PET | G10: EL | H10: 13.344 | I10: Enero | M10: C.T. PISCO SUR | N10: 0 | O10: 5.11 | S10: Agroindustrial Laredo S.A.A. | T10: C.T. TURBO GENERADOR 5 | U10: 0 | V10: Operativo | W10: 10 | X10: 10 | Y10: 35.97784 | AA10: 0
D11: 4 | E11: OIG Perú S.A.C. | F11: C.T. PLANTA ELÉCTRICA EL ALTO | G11: EL | H11: 8.55 | I11: Mayo | M11: C.T. SAMANCO | N11: 0 | O11: 2.625 | S11: Agroindustrial Laredo S.A.A. | T11: C.T. UNIDAD DIESEL | U11: 0 | V11: Operativo | W11: 0.8 | X11: 0.8 | Y11: 0.384325 | AA11: 0
F12: C.T. EQUIPOS MÓVILES | G12: EL | H12: 1 | I12: Mayo | M12: C.T. SUPE | N12: 0 | O12: 2.325 | S12: Aguaytia Energy del Peru S.R.L. | T12: C.T. GAS | U12: 0 | V12: Operativo | W12: 1 | X12: 1 | Y12: 1.653942 | AA12: 0
D13: 5 | E13: Progenere S.A.C. | F13: C.T. LA GRINGA VI | G13: EL | H13: 11.65 | I13: Enero | M13: C.T. CHIMBOTE | N13: 0 | O13: 5.705 | S13: Alicorp S.A.A. | T13: C.T. AREQUIPA | U13: 0 | V13: Operativo | W13: 1.06 | X13: 1.06 | Y13: 0 | AA13: 0
M14: C.T. VEGUETA | N14: 0 | O14: 3.38 | S14: Alicorp S.A.A. | T14: C.T. MOLINOS CALLAO | U14: 0 | V14: Inoperativo | W14: 3 | X14: 3 | Y14: 0 | AA14: 0
D15: Total | H15: =+SUM(H7:H14) -> 67.202 | L15: Total general | O15: 40.39 | S15: Alicorp S.A.A. | T15: C.T. MOLINOS SANTA ROSA | U15: 0 | V15: Operativo | W15: 1.89 | X15: 1.89 | Y15: 0 | AA15: 0
S16: Alicorp S.A.A. | T16: C.T. NICOVITA TRUJILLO | U16: 0 | V16: Operativo | W16: 0.8 | X16: 0.8 | Y16: 0 | AA16: 0
D17: Retiro de empresas * | S17: Alicorp S.A.A. | T17: C.T. OLEAGINOSA CALLAO | U17: 0 | V17: Operativo | W17: 2.4 | X17: 2.4 | Y17: 2.151647 | AA17: 0
S18: Anabi S.A.C. | T18: C.T. ANABI | U18: 0 | V18: Operativo | W18: 3.36 | X18: 3.36 | Y18: 0.323067 | AA18: 0
D19: Nº | E19: Nombre de la empresa | F19: Central | G19: Tipo de Unidad | H19: Potencia (MW) | I19: Desde | S19: Anabi S.A.C. | T19: C.T. ANAMA | U19: 0 | V19: Operativo | W19: 3.36 | X19: 3.36 | Y19: 0.027701 | AA19: 0
D20: 1 | E20: CNPC Perú S.A. | F20: C.T. LOTE X | G20: EL | H20: 8.55 | I20: Mayo | S20: Anglo American Quellaveco S.A. | T20: C.T. SALVIANI | U20: 0 | V20: Operativo | W20: 5 | X20: 5 | Y20: 0 | AA20: 0
S21: Anglo American Quellaveco S.A. | T21: C.T. CORTADERA | U21: 0 | V21: Operativo | W21: 1.64 | X21: 1.64 | Y21: 2.176906 | AA21: 0
D22: Total | H22: =SUM(H20:H20) -> 8.55 | S22: Anglo American Quellaveco S.A. | T22: C.T. DRENAJE SECTOR MINA | U22: 0 | V22: Operativo | W22: 4.08 | X22: 4.08 | Y22: 0 | AA22: 0
D23: (*) Empresas que dejan de integrar el parque generar y/o se integran al grupo de empresas No Informantes. | S23: Anglo American Quellaveco S.A. | T23: C.T. PLANTA PAPUJUNE | U23: 0 | V23: Operativo | W23: 9.6 | X23: 9.6 | Y23: 0 | AA23: 0
S24: Apumayo S.A.C. | T24: C.T. APUMAYO | U24: 0 | V24: Operativo | W24: 4 | X24: 4 | Y24: 0 | AA24: 0
C25: A.2) A nivel de centrales de generación: | S25: Aruntani S.A.C. | T25: C.T. JESICA | U25: 0 | V25: Operativo | W25: 1.85 | X25: 1.85 | Y25: 0 | AA25: 0
S26: Aruntani S.A.C. | T26: C.T. TUCARI | U26: 0 | V26: Operativo | W26: 5.143 | X26: 5.143 | Y26: 0.006611 | AA26: 0
D27: Nuevos Ingresos de centrales | S27: Austral Group S.A.A | T27: C.T. PLANTA CHANCAY | U27: 0 | V27: Operativo | W27: 3.03 | X27: 3.03 | Y27: 0.002517 | AA27: 0
S28: Austral Group S.A.A | T28: C.T. PLANTA PISCO | U28: 0 | V28: Operativo | W28: 4.05 | X28: 4.05 | Y28: 0.049083 | AA28: 0
D29: Nº | E29: Nombre de la empresa | F29: Central | G29: Tipo de Unidad | H29: Potencia (MW) | I29: Desde | S29: Cartavio S.A.A. | T29: C.T. CARTAVIO | U29: 0 | V29: Operativo | W29: 9.8 | X29: 9.8 | Y29: 73.287952 | AA29: 0
S30: Casa Grande S.A.A. | T30: C.T. CASA GRANDE | U30: 0 | V30: Operativo | W30: 37 | X30: 37 | Y30: 87.659289 | AA30: 0
D31: Total | H31: =+SUM(H30:H30) -> 0 | S31: Cementos Pacasmayo S.A.A. | T31: C.T. PACASMAYO | U31: 0 | V31: Operativo | W31: 6.6 | X31: 6.6 | Y31: 0 | AA31: 0
S32: Cementos Selva S.A. | T32: C.T. CEMENTOS RIOJA | U32: 0 | V32: Inoperativo | W32: 2 | X32: 2 | Y32: 0 | AA32: 0
D33: Retiro o baja de centrales | S33: Cerámica Lima S.A. | T33: C.T. CELIMA 01 | U33: 0 | V33: Operativo | X33: 2.57 | Y33: 0.03036 | Z33: Pasó a informantes | AA33: 2.57
S34: Cerámica Lima S.A. | T34: C.T. CELIMA 02 | U34: 0 | V34: Operativo | X34: 1.09 | Y34: 0.00428 | Z34: Pasó a informantes | AA34: 1.09
D35: Nº | E35: Nombre de la empresa | F35: Central | G35: Tipo de Unidad | H35: Potencia (MW) | I35: Desde | S35: Cervecería San Juan S.A. | T35: C.T. SAN JUAN | U35: 0 | V35: Operativo | W35: 2.6 | X35: 2.6 | Y35: 0 | AA35: 0
S36: Cia Minera Poderosa S.A. | T36: C.H. EL TINGO | U36: 0 | V36: Operativo | W36: 1.72 | X36: 1.72 | Y36: 5.432127 | AA36: 0
D37: Total | H37: =SUM(#REF!) -> #REF! | S37: Cia Minera Poderosa S.A. | T37: C.T. J.A. SAMANIEGO ALC | U37: 0 | V37: Operativo | W37: 6.915 | X37: 6.915 | Y37: 3.340236 | AA37: 0
S38: Cia Minera Poderosa S.A. | T38: C.T. PATAZ | U38: 0 | V38: Operativo | W38: 1.45 | X38: 4.37 | Y38: 27.10133 | AA38: 2.92
C39: A.3) A nivel de unidades (grupos) de centrales de generación: | S39: Cia Minera Raura S.A. | T39: C.H. CASHAUCRO | U39: 0 | V39: Operativo | W39: 4.14 | X39: 4.14 | Y39: 25.069585 | AA39: 0
S40: Cia Minera Santa Luisa S.A. | T40: C.H. HUALLANCA NUEVA | U40: 0 | V40: Operativo | W40: 4.3 | X40: 4.3 | Y40: 27.11251 | AA40: 0
D41: Nuevos ingresos de unidades / grupos | S41: Cia Minera Santa Luisa S.A. | T41: C.H. PALLCA | U41: 0 | V41: Operativo | W41: 1 | X41: 1 | Y41: 3.95514 | AA41: 0
S42: Cia Minera Santa Luisa S.A. | T42: C.T. ATALAYA | U42: 0 | V42: Operativo | W42: 0.545 | X42: 0.545 | Y42: 0.171152 | AA42: 0
D43: Nº | E43: Nombre de la empresa | F43: En la central: | G43: Tipo de Unidad | H43: Potencia (MW) | I43: Desde | S43: Cia Minera Santa Luisa S.A. | T43: C.T. HUANZALÁ | U43: 0 | V43: Operativo | W43: 2.19 | X43: 2.19 | Y43: 0 | AA43: 0
S44: Cia Minera Santa Luisa S.A. | T44: C.T. PALLCA | U44: 0 | V44: Operativo | W44: 4.565 | X44: 4.565 | Y44: 1.1035 | AA44: 0
D45: Total | H45: =SUM(H44:H44) -> 0 | S45: CNPC Perú S.A. | T45: C.T. LOTE X | U45: 0 | V45: Operativo | W45: 8.55 | X45: 0 | Y45: 11.846758 | Z45: retiro de empresa | AA45: -8.55
S46: Compañía Minera Antapaccay S.A. | T46: C.T. TINTAYA | U46: 0 | V46: Operativo | W46: 17.96 | X46: 17.96 | Y46: 0.085435 | AA46: 0
D47: Retiro o baja de grupos | S47: Compañía Minera Ares S.A.C. | T47: C.T. ARCATA | U47: 0 | V47: Operativo | W47: 9.6 | X47: 9.6 | Y47: 0 | AA47: 0
S48: Compañía Minera Ares S.A.C. | T48: C.T. ARES | U48: 0 | V48: Operativo | W48: 2.544 | X48: 2.544 | Y48: 0 | AA48: 0
D49: Nº | E49: Nombre de la empresa | F49: Central | G49: Tipo de Unidad | H49: Potencia (MW) | I49: Desde | S49: Compañía Minera Ares S.A.C. | T49: C.T. PALLANCATA | U49: 0 | V49: Operativo | W49: 1.2 | X49: 1.2 | Y49: 0.010617 | AA49: 0
S50: Compañía Minera Ares S.A.C. | T50: C.T. SELENE | U50: 0 | V50: Operativo | W50: 6 | X50: 6 | Y50: 0.015249 | AA50: 0
D51: Total | H51: =SUM(H50:H50) -> 0 | S51: Compañía Minera Ares S.A.C. | T51: C.T. SIPÁN | U51: 0 | V51: Operativo | W51: 0.58 | X51: 0.58 | Y51: 0.064607 | AA51: 0
S52: Compañía Minera Ares S.A.C. | T52: C.T. INMACULADA | U52: 0 | V52: Operativo | W52: 6 | X52: 6 | Y52: 0.183524 | AA52: 0
S53: Compañía Minera Caraveli S.A.C. | T53: C.T. MINA | U53: 0 | V53: Operativo | W53: 1.089 | X53: 1.089 | Y53: 5.888254 | AA53: 0
B54: B) Modificación de Datos y Transferencias | S54: Compañía Minera Caraveli S.A.C. | T54: C.T. PLANTA | U54: 0 | V54: Operativo | W54: 2.345 | X54: 2.345 | Y54: 0.358793 | AA54: 0
S55: Compañía Minera Chungar S.A.C. | T55: C.H. BAÑOS I | U55: 0 | V55: Operativo | W55: 1.2 | X55: 1.2 | Y55: 6.987061 | AA55: 0
C56: B.1) Cambio de Razón Social de empresas y/o nombre de centrales | S56: Compañía Minera Chungar S.A.C. | T56: C.H. BAÑOS II | U56: 0 | V56: Operativo | W56: 0.94 | X56: 0.94 | Y56: 6.654264 | AA56: 0
S57: Compañía Minera Chungar S.A.C. | T57: C.H. BAÑOS III | U57: 0 | V57: Operativo | W57: 0.976 | X57: 0.976 | Y57: 7.428288 | AA57: 0
D58: Nº | E58: Razón Social Anterior | F58: Nueva Razón Social | G58: Central | H58: Potencia (MW) | I58: Desde | S58: Compañía Minera Chungar S.A.C. | T58: C.H. BAÑOS IV | U58: 0 | V58: Operativo | W58: 4.9 | X58: 4.9 | Y58: 35.584357 | AA58: 0
S59: Compañía Minera Chungar S.A.C. | T59: C.T. TAJO DON PABLO | U59: 0 | V59: Operativo | W59: 0.204 | X59: 0.204 | Y59: 0 | AA59: 0
D60: Total | H60: =SUM(H59:H59) -> 0 | S60: Compañia Minera Kolpa S.A. | T60: C.T. KOLPA | U60: 0 | V60: Operativo | W60: 0.499 | X60: 0.499 | Y60: 0.43215 | AA60: 0
S61: Compañía Minera San Ignacio de Morococha S.A.A. | T61: C.H. MONOBAMBA | U61: 0 | V61: Operativo | W61: 11.5 | X61: 11.5 | Y61: 43.55634 | AA61: 0
C62: B.2) Transferencia de unidades (grupos) entre Centrales de la misma empresa | S62: Compañía Minera San Ignacio de Morococha S.A.A. | T62: C.T. SAN VICENTE | U62: 0 | V62: Operativo | W62: 12 | X62: 12 | Y62: 0.004485 | AA62: 0
S63: Compañía Minera San Valentin S.A. | T63: C.H. LLAPAY | U63: 0 | V63: Operativo | W63: 3.78 | X63: 3.78 | Y63: 14.329696 | AA63: 0
D64: Nº | E64: Nombre de la empresa | F64: De Central | G64: A Central | H64: Potencia (MW) | I64: Desde | S64: Compañía Pesquera del Pacifico Centro S.A. | T64: C.T. PLANTA CHIMBOTE | U64: 0 | V64: Operativo | W64: 1.8 | X64: 1.8 | Y64: 0.489371 | AA64: 0
S65: Consorcio Minero Horizonte S.A. | T65: C.H. PÍAS 1 | U65: 0 | V65: Operativo | W65: 12.6 | X65: 12.6 | Y65: 64.61377 | AA65: 0
D66: Total | S66: Consorcio Minero Horizonte S.A. | T66: C.T. PARCOY | U66: 0 | V66: Operativo | W66: 5.987 | X66: 5.987 | Y66: 0.22501 | AA66: 0
S67: Corporación Aceros Arequipa S.A. | T67: C.T. ACEROS | U67: 0 | V67: Operativo | W67: 1.25 | X67: 1.25 | Y67: 0 | AA67: 0
C68: B.3) Transferencia de unidades (grupos o centrales) entre diferentes empresas | S68: Corporación Pesquera Inca S.A.C. | T68: C.T. COPEINCA CHANCAY | U68: 0 | V68: Operativo | X68: 2.35 | Y68: 0 | Z68: Pasó a informantes | AA68: 2.35
S69: Corporación Pesquera Inca S.A.C. | T69: C.T. COPEINCA SUPE | U69: 0 | V69: Operativo | X69: 4.01 | Y69: 0.79517 | Z69: Pasó a informantes | AA69: 4.01
D70: Nº | E70: De empresa | F70: Central | G70: A Empresa | I70: Potencia (MW) | S70: Empresa Minera los Quenuales S.A. | T70: C.H. RAPAZ II | U70: 0 | V70: Operativo | W70: 1.7 | X70: 1.7 | Y70: 3.187187 | AA70: 0
S71: Empresa Minera los Quenuales S.A. | T71: C.T. ISCAYCRUZ | U71: 0 | V71: Operativo | W71: 5.56 | X71: 5.56 | Y71: 0 | AA71: 0
D72: Total | I72: =SUM(I71:I71) -> 0 | S72: Empresa Minera los Quenuales S.A. | T72: C.T. LAGSAURA | U72: 0 | V72: Operativo | W72: 0.37 | X72: 0.37 | Y72: 0 | AA72: 0
S73: Freno S.A. | T73: C.T. FRENOSA | U73: 0 | V73: Operativo | W73: 0.6 | X73: 0.6 | Y73: 0 | AA73: 0
S74: ICM Pachapaqui S.A.C. | T74: C.H. SAN JUDAS TADEO | U74: 0 | V74: Operativo | W74: 0.94 | X74: 0.94 | Y74: 0.780952 | AA74: 0
B75: C) Incorporados a informantes | S75: ICM Pachapaqui S.A.C. | T75: C.H. SAN MARTÍN DE PORRES | U75: 0 | V75: Operativo | W75: 1.6 | X75: 1.6 | Y75: 0.463299 | AA75: 0
S76: Illapu Energy S.A. | T76: C.T. PLANTA HUACHIPA | U76: 0 | V76: Operativo | W76: 13.6 | X76: 13.6 | Y76: 89.905581 | AA76: 0
D77: Nº | E77: Nombre de la empresa | F77: Central | G77: Tipo de Unidad | H77: Potencia (MW) | I77: Desde | S77: Inca Tops S.A. | T77: C.T. PLANTA 1 | U77: 0 | V77: Operativo | W77: 0.375 | X77: 0.375 | Y77: 0.0018 | AA77: 0
D78: 1 | E78: Cerámica Lima S.A. | F78: C.T. CELIMA 01 | G78: EL | H78: 2.57 | I78: Enero | S78: Inca Tops S.A. | T78: C.T. PLANTA 2 | U78: 0 | V78: Operativo | W78: 0.377 | X78: 0.377 | Y78: 0.00124 | AA78: 0
F79: C.T. CELIMA 02 | G79: EL | H79: 1.09 | I79: Enero | S79: Inca Tops S.A. | T79: C.T. PLANTA 04-1 | U79: 0 | V79: Operativo | W79: 0.93 | X79: 0.93 | Y79: 0.000846 | AA79: 0
D80: 2 | E80: Corporación Pesquera Inca S.A.C. | F80: C.T. COPEINCA CHANCAY | G80: EL | H80: 2.35 | I80: Enero | S80: Inca Tops S.A. | T80: C.T. PLANTA 04-2 | U80: 0 | V80: Operativo | W80: 0.5 | X80: 0.5 | Y80: 0.000385 | AA80: 0
F81: C.T. COPEINCA SUPE | G81: EL | H81: 4.01 | I81: Enero | S81: Indeco S.A. | T81: C.T. INDECO | U81: 0 | V81: Operativo | W81: 0.425 | X81: 0.425 | Y81: 0.00014 | AA81: 0
D82: 3 | E82: Tecnológica de Alimentos S.A. | F82: C.T. CALLAO | G82: EL | H82: 1.135 | I82: Enero | S82: Industrias Electroquimicas S. A. | T82: C.T. IEQSA | U82: 0 | V82: Operativo | W82: 2.45 | X82: 2.45 | Y82: 0.012307 | AA82: 0
F83: C.T. MALABRIGO | G83: EL | H83: 6.79 | I83: Enero | S83: Inkabor S.A.C. | T83: C.T. RIO SECO | U83: 0 | V83: Operativo | W83: 0.91 | X83: 0.91 | Y83: 0.003132 | AA83: 0
F84: C.T. PISCO SUR | G84: EL | H84: 5.11 | I84: Enero | S84: Inkabor S.A.C. | T84: C.T. UBINAS | U84: 0 | V84: Operativo | W84: 1.13 | X84: 1.13 | Y84: 0.295303 | AA84: 0
F85: C.T. SAMANCO | G85: EL | H85: 2.625 | I85: Enero | S85: Minera Aurífera Retamas S.A. | T85: C.T. SAN ANDRES | U85: 0 | V85: Operativo | W85: 13.735 | X85: 13.735 | Y85: 0.194843 | AA85: 0
F86: C.T. SUPE | G86: EL | H86: 2.325 | I86: Enero | S86: Minera Bateas S.A.C. | T86: C.T. BATEAS | U86: 0 | V86: Operativo | W86: 4.9 | X86: 4.9 | Y86: 0.174109 | AA86: 0
F87: C.T. CHIMBOTE | G87: EL | H87: 5.705 | I87: Enero | S87: Minera La Zanja S.R.L. | T87: C.T. LA ZANJA | U87: 0 | V87: Operativo | W87: 3.67 | X87: 3.67 | Y87: 0 | AA87: 0
F88: C.T. MATARANI | G88: EL | H88: 3.3 | I88: Enero | S88: Minera Yanacocha S.R.L. | T88: C.T. CHINA LINDA | U88: 0 | V88: Operativo | W88: 0.675 | X88: 0.675 | Y88: 0 | AA88: 0
F89: C.T. VEGUETA | G89: EL | H89: 3.38 | I89: Enero | S89: Minera Yanacocha S.R.L. | T89: C.T. GOLD MILL | U89: 0 | V89: Operativo | W89: 4.08 | X89: 4.08 | Y89: 0.004143 | AA89: 0
S90: Minera Yanacocha S.R.L. | T90: C.T. LA PLAJUELA | U90: 0 | V90: Operativo | W90: 10.95 | X90: 10.95 | Y90: 0.005387 | AA90: 0
D91: Total | H91: =+SUM(H78:H90) -> 40.39 | S91: Minera Yanacocha S.R.L. | T91: C.T. MAQUI MAQUI | U91: 0 | V91: Operativo | W91: 3.18 | X91: 3.18 | Y91: 0.00097 | AA91: 0
S92: Minera Yanacocha S.R.L. | T92: C.T. PAMPA LARGA | U92: 0 | V92: Operativo | W92: 5.46 | X92: 5.46 | Y92: 0.00372 | AA92: 0
D93: Nota : | S93: Minera Yanacocha S.R.L. | T93: C.T. POND. DE CARACHUGO | U93: 0 | V93: Inoperativo | W93: 1.82 | X93: 1.82 | Y93: 0 | AA93: 0
S94: Minera Yanacocha S.R.L. | T94: C.T. QUINUA | U94: 0 | V94: Operativo | W94: 8.65 | X94: 8.65 | Y94: 0.000472 | AA94: 0
D95: HI : | E95: Turbina hidráulica | S95: Minera Yanacocha S.R.L. | T95: C.T. YANACOCHA NORTE | U95: 0 | V95: Operativo | W95: 5.425 | X95: 5.425 | Y95: 0 | AA95: 0
D96: EL: | E96: Electrógeno | S96: Minera Yanaquihua S.A.C. | T96: C.T. YANAQUIHUA | U96: 0 | V96: Operativo | W96: 1.285 | X96: 1.285 | Y96: 0.174911 | AA96: 0
D97: TV : | E97: Turbo Vapor | S97: Minsur S.A. | T97: C.T. FUNDICIÓN DIESEL | U97: 0 | V97: Operativo | W97: 3.99 | X97: 3.99 | Y97: 0.159023 | AA97: 0
D98: TG : | E98: Turbo Gas | S98: Minsur S.A. | T98: C.T. FUNDICIÓN GAS NATURAL | U98: 0 | V98: Operativo | W98: 6.165 | X98: 6.165 | Y98: 5.963046 | AA98: 0
S99: Minsur S.A. | T99: C.T. PUCAMARCA | U99: 0 | V99: Operativo | W99: 3.65 | X99: 3.65 | Y99: 0.070334 | AA99: 0
S100: Minsur S.A. | T100: C.T. SAN RAFAEL | U100: 0 | V100: Operativo | W100: 8.5 | X100: 8.5 | Y100: 0.33078 | AA100: 0
...

Sheet 3.3.1 (PI)
A1: 3.3.1. Potencia instalada a nivel nacional
B3: a - Potencia instalada según tipo de servicio y origen (MW) | L3: Informa_A | M3: (Todas)
L4: FILTRO | M4: (en blanco)
B5: Origen | C5: Hidráulica | D5: Térmica | E5: Solar | F5: Eólica | G5: Total
B6: Servicio | L6: Suma de PI 2024 OK | M6: Etiquetas de columna
L7: Etiquetas de fila | M7: Hidráulico | N7: Térmico | O7: Solar | P7: Eólico | Q7: Total general
B8: Para mercado eléctrico | C8: =+M8 -> 5414.232 | D8: =+N8 -> 8022.99 | E8: =+O8 -> 494.496 | F8: =+P8 -> 1015.69 | G8: =SUM(C8:F8) -> 14947.408 | L8: MERCADO ELÉCTRICO | M8: 5414.232 | N8: 8022.99 | O8: 494.496 | P8: 1015.69 | Q8: 14947.408
G9: =G8/G13 -> 0.90420531 | L9: USO PROPIO | M9: 129.903 | N9: 1453.678 | Q9: 1583.581
L10: Total general | M10: 5544.135 | N10: 9476.668 | O10: 494.496 | P10: 1015.69 | Q10: 16530.989
B11: Para uso propio | C11: =+M9 -> 129.903 | D11: =+N9 -> 1453.678 | G11: =SUM(C11:F11) -> 1583.581
G12: =G11/G13 -> 0.095794692
B13: TOTAL | C13: =SUM(C8,C11) -> 5544.135 | D13: =SUM(D8,D11) -> 9476.668 | E13: =SUM(E8,E11) -> 494.496 | F13: =SUM(F8,F11) -> 1015.69 | G13: =SUM(G8,G11) -> 16530.989
C14: =C13/G13 -> 0.3353783 | D14: =D13/G13 -> 0.57326685 | E14: =E13/G13 -> 0.029913274 | F14: =F13/G13 -> 0.061441575
L28: Informa_A | M28: (Todas)
B29: b - Potencia instalada según sistema y origen (MW) | L29: FILTRO | M29: (en blanco)
B31: Origen | C31: Hidráulica | D31: Térmica | E31: Solar | F31: Eólica | G31: Total | L31: Suma de PI 2024 OK | M31: Etiquetas de columna
B32: Sistema | L32: Etiquetas de fila | M32: Hidráulico | N32: Térmico | O32: Solar | P32: Eólico | Q32: Total general
L33: SEIN | M33: 5436.497 | N33: 8033.341 | O33: 481.996 | P33: 1014.99 | Q33: 14966.824
B34: SEIN | C34: =+M33 -> 5436.497 | D34: =+N33 -> 8033.341 | E34: =+O33 -> 481.996 | F34: =+P33 -> 1014.99 | G34: =SUM(C34:F34) -> 14966.824 | L34: SA | M34: 107.638 | N34: 1443.327 | O34: 12.5 | P34: 0.7 | Q34: 1564.165
G35: =G34/G39 -> 0.90537983 | L35: Total general | M35: 5544.135 | N35: 9476.668 | O35: 494.496 | P35: 1015.69 | Q35: 16530.989
B37: SS AA | C37: =+M34 -> 107.638 | D37: =+N34 -> 1443.327 | E37: =+O34 -> 12.5 | F37: =+P34 -> 0.7 | G37: =SUM(C37:F37) -> 1564.165
G38: =G37/G39 -> 0.094620171
B39: TOTAL | C39: =SUM(C34,C37) -> 5544.135 | D39: =SUM(D34,D37) -> 9476.668 | E39: =SUM(E34,E37) -> 494.496 | F39: =SUM(F34,F37) -> 1015.69 | G39: =SUM(C39:F39) -> 16530.989
C40: =C39/G39 -> 0.3353783 | D40: =D39/G39 -> 0.57326685 | E40: =E39/G39 -> 0.029913274 | F40: =F39/G39 -> 0.061441575
L54: Informa_A | M54: (Todas)
L55: Origen_A | M55: (Todas)
B56: c - Potencia instalada según tipo de servicio y sistema (MW) | L56: FILTRO | M56: (en blanco)
B58: Sistema | C58: SEIN | D58: SS AA | F58: Total | L58: Suma de PI 2024 OK | M58: Etiquetas de columna
B59: Servicio | L59: Etiquetas de fila | M59: SEIN | N59: SA | O59: Total general
L60: MERCADO ELÉCTRICO | M60: 14696.207 | N60: 251.201 | O60: 14947.408
B61: Para mercado eléctrico | C61: =+M60 -> 14696.207 | D61: =+N60 -> 251.201 | F61: =SUM(C61:E61) -> 14947.408 | L61: USO PROPIO | M61: 270.617 | N61: 1312.964 | O61: 1583.581
F62: =F61/F66 -> 0.90420531 | L62: Total general | M62: 14966.824 | N62: 1564.165 | O62: 16530.989
B64: Para uso propio | C64: =+M61 -> 270.617 | D64: =+N61 -> 1312.964 | F64: =SUM(C64:D64) -> 1583.581 | L64: 0.98319434 | M64: 0.016805656
F65: =F64/F66 -> 0.095794692 | L65: 0.17088927 | M65: 0.82911073
B66: TOTAL | C66: =SUM(C61,C64) -> 14966.824 | D66: =SUM(D61,D64) -> 1564.165 | F66: =SUM(F61,F64) -> 16530.989
C67: =C66/F66 -> 0.90537983 | D67: =D66/F66 -> 0.094620171

Sheet 3.3.2.1
A1: 3.3.2. Potencia instalada por empresa al mes de diciembre | Q1: Informa A | R1: (Todas)
Q2: Tipo de Mercado A | R2: Mercado Eléctrico
B3: 3.3.2.1. Potencia instalada para el mercado eléctrico (MW) | Q3: FILTRO | R3: (en blanco)
B5: N° | C5: Nombre de la empresa | D5: SEIN | H5: SS AA | K5: Total por origen | O5: Total | Q5: Suma de PI OK | R5: Etiquetas de columna
D6: Hidráulica | E6: Térmica | F6: Solar | G6: Eólica | H6: Hidráulica | I6: Térmica | J6: Eólica | K6: Hidráulica | L6: Térmica | M6: Solar | N6: Eólica | O6: empresa | R6: SEIN | V6: SA | Z6: Total general
B7: 1 | C7: =+Q8 -> Agro Industrial Paramonga S.A.A. | D7: =+IF(R8<>0,R8,"") | E7: =+IF(S8<>0,S8,"") -> 23 | F7: =+IF(T8<>0,T8,"") | G7: =+IF(U8<>0,U8,"") | H7: =+IF(V8<>0,V8,"") | I7: =+IF(W8<>0,W8,"") | J7: =+IF(X8<>0,X8,"") | K7: =+IF((R8+V8)<>0,R8+V8,"") | L7: =+IF((S8+W8)<>0,S8+W8,"") -> 23 | M7: =+IF((T8+X8)<>0,T8+X8,"") | N7: =+IF((U8+Y8)<>0,U8+Y8,"") | O7: =SUM(K7:N7) -> 23 | Q7: Etiquetas de fila | R7: Hidráulico | S7: Térmico | T7: Solar | U7: Eólico | V7: Hidráulico | W7: Térmico | X7: Solar | Y7: Eólico
B8: =+B7+1 -> 2 | C8: =+Q9 -> Agroaurora S.A.C. | D8: =+IF(R9<>0,R9,"") | E8: =+IF(S9<>0,S9,"") -> 37.5 | F8: =+IF(T9<>0,T9,"") | G8: =+IF(U9<>0,U9,"") | H8: =+IF(V9<>0,V9,"") | I8: =+IF(W9<>0,W9,"") | J8: =+IF(X9<>0,X9,"") | K8: =+IF((R9+V9)<>0,R9+V9,"") | L8: =+IF((S9+W9)<>0,S9+W9,"") -> 37.5 | M8: =+IF((T9+X9)<>0,T9+X9,"") | N8: =+IF((U9+Y9)<>0,U9+Y9,"") | O8: =SUM(K8:N8) -> 37.5 | Q8: Agro Industrial Paramonga S.A.A. | S8: 23 | Z8: 23
B9: =+B8+1 -> 3 | C9: =+Q10 -> Agroindustrias San Jacinto S.A.A. | D9: =+IF(R10<>0,R10,"") | E9: =+IF(S10<>0,S10,"") -> 21.71 | F9: =+IF(T10<>0,T10,"") | G9: =+IF(U10<>0,U10,"") | H9: =+IF(V10<>0,V10,"") | I9: =+IF(W10<>0,W10,"") | J9: =+IF(X10<>0,X10,"") | K9: =+IF((R10+V10)<>0,R10+V10,"") | L9: =+IF((S10+W10)<>0,S10+W10,"") -> 21.71 | M9: =+IF((T10+X10)<>0,T10+X10,"") | N9: =+IF((U10+Y10)<>0,U10+Y10,"") | O9: =SUM(K9:N9) -> 21.71 | Q9: Agroaurora S.A.C. | S9: 37.5 | Z9: 37.5
B10: =+B9+1 -> 4 | C10: =+Q11 -> Amazonas Energía Solar S.A.C. | D10: =+IF(R11<>0,R11,"") | E10: =+IF(S11<>0,S11,"") | F10: =+IF(T11<>0,T11,"") | G10: =+IF(U11<>0,U11,"") | H10: =+IF(V11<>0,V11,"") | I10: =+IF(W11<>0,W11,"") | J10: =+IF(X11<>0,X11,"") -> 12.49 | K10: =+IF((R11+V11)<>0,R11+V11,"") | L10: =+IF((S11+W11)<>0,S11+W11,"") | M10: =+IF((T11+X11)<>0,T11+X11,"") -> 12.49 | N10: =+IF((U11+Y11)<>0,U11+Y11,"") | O10: =SUM(K10:N10) -> 12.49 | Q10: Agroindustrias San Jacinto S.A.A. | S10: 21.71 | Z10: 21.71
B11: =+B10+1 -> 5 | C11: =+Q12 -> Andean Power S.A.C. | D11: =+IF(R12<>0,R12,"") -> 20 | E11: =+IF(S12<>0,S12,"") | F11: =+IF(T12<>0,T12,"") | G11: =+IF(U12<>0,U12,"") | H11: =+IF(V12<>0,V12,"") | I11: =+IF(W12<>0,W12,"") | J11: =+IF(X12<>0,X12,"") | K11: =+IF((R12+V12)<>0,R12+V12,"") -> 20 | L11: =+IF((S12+W12)<>0,S12+W12,"") | M11: =+IF((T12+X12)<>0,T12+X12,"") | N11: =+IF((U12+Y12)<>0,U12+Y12,"") | O11: =SUM(K11:N11) -> 20 | Q11: Amazonas Energía Solar S.A.C. | X11: 12.49 | Z11: 12.49
B12: =+B11+1 -> 6 | C12: =+Q13 -> Asociación Santa Lucia de Chacas | D12: =+IF(R13<>0,R13,"") -> 3 | E12: =+IF(S13<>0,S13,"") | F12: =+IF(T13<>0,T13,"") | G12: =+IF(U13<>0,U13,"") | H12: =+IF(V13<>0,V13,"") | I12: =+IF(W13<>0,W13,"") | J12: =+IF(X13<>0,X13,"") | K12: =+IF((R13+V13)<>0,R13+V13,"") -> 3 | L12: =+IF((S13+W13)<>0,S13+W13,"") | M12: =+IF((T13+X13)<>0,T13+X13,"") | N12: =+IF((U13+Y13)<>0,U13+Y13,"") | O12: =SUM(K12:N12) -> 3 | Q12: Andean Power S.A.C. | R12: 20 | Z12: 20
B13: =+B12+1 -> 7 | C13: =+Q14 -> Atria Energía S.A.C. | D13: =+IF(R14<>0,R14,"") -> 1.8 | E13: =+IF(S14<>0,S14,"") | F13: =+IF(T14<>0,T14,"") | G13: =+IF(U14<>0,U14,"") | H13: =+IF(V14<>0,V14,"") | I13: =+IF(W14<>0,W14,"") | J13: =+IF(X14<>0,X14,"") | K13: =+IF((R14+V14)<>0,R14+V14,"") -> 1.8 | L13: =+IF((S14+W14)<>0,S14+W14,"") | M13: =+IF((T14+X14)<>0,T14+X14,"") | N13: =+IF((U14+Y14)<>0,U14+Y14,"") | O13: =SUM(K13:N13) -> 1.8 | Q13: Asociación Santa Lucia de Chacas | R13: 3 | Z13: 3
B14: =+B13+1 -> 8 | C14: =+Q15 -> Bioenergía del Chira S.A. | D14: =+IF(R15<>0,R15,"") | E14: =+IF(S15<>0,S15,"") -> 14 | F14: =+IF(T15<>0,T15,"") | G14: =+IF(U15<>0,U15,"") | H14: =+IF(V15<>0,V15,"") | I14: =+IF(W15<>0,W15,"") | J14: =+IF(X15<>0,X15,"") | K14: =+IF((R15+V15)<>0,R15+V15,"") | L14: =+IF((S15+W15)<>0,S15+W15,"") -> 14 | M14: =+IF((T15+X15)<>0,T15+X15,"") | N14: =+IF((U15+Y15)<>0,U15+Y15,"") | O14: =SUM(K14:N14) -> 14 | Q14: Atria Energía S.A.C. | R14: 1.8 | Z14: 1.8
B15: =+B14+1 -> 9 | C15: =+Q16 -> Celepsa Renovables S.R.L. | D15: =+IF(R16<>0,R16,"") -> 19.86 | E15: =+IF(S16<>0,S16,"") | F15: =+IF(T16<>0,T16,"") | G15: =+IF(U16<>0,U16,"") | H15: =+IF(V16<>0,V16,"") | I15: =+IF(W16<>0,W16,"") | J15: =+IF(X16<>0,X16,"") | K15: =+IF((R16+V16)<>0,R16+V16,"") -> 19.86 | L15: =+IF((S16+W16)<>0,S16+W16,"") | M15: =+IF((T16+X16)<>0,T16+X16,"") | N15: =+IF((U16+Y16)<>0,U16+Y16,"") | O15: =SUM(K15:N15) -> 19.86 | Q15: Bioenergía del Chira S.A. | S15: 14 | Z15: 14
B16: =+B15+1 -> 10 | C16: =+Q17 -> Central Hidroeléctrica de Langui S.A. | D16: =+IF(R17<>0,R17,"") -> 6.42 | E16: =+IF(S17<>0,S17,"") | F16: =+IF(T17<>0,T17,"") | G16: =+IF(U17<>0,U17,"") | H16: =+IF(V17<>0,V17,"") | I16: =+IF(W17<>0,W17,"") | J16: =+IF(X17<>0,X17,"") | K16: =+IF((R17+V17)<>0,R17+V17,"") -> 6.42 | L16: =+IF((S17+W17)<>0,S17+W17,"") | M16: =+IF((T17+X17)<>0,T17+X17,"") | N16: =+IF((U17+Y17)<>0,U17+Y17,"") | O16: =SUM(K16:N16) -> 6.42 | Q16: Celepsa Renovables S.R.L. | R16: 19.86 | Z16: 19.86
B17: =+B16+1 -> 11 | C17: =+Q18 -> Centrales Santa Rosa S.A.C. | D17: =+IF(R18<>0,R18,"") -> 2.9 | E17: =+IF(S18<>0,S18,"") | F17: =+IF(T18<>0,T18,"") | G17: =+IF(U18<>0,U18,"") | H17: =+IF(V18<>0,V18,"") | I17: =+IF(W18<>0,W18,"") | J17: =+IF(X18<>0,X18,"") | K17: =+IF((R18+V18)<>0,R18+V18,"") -> 2.9 | L17: =+IF((S18+W18)<>0,S18+W18,"") | M17: =+IF((T18+X18)<>0,T18+X18,"") | N17: =+IF((U18+Y18)<>0,U18+Y18,"") | O17: =SUM(K17:N17) -> 2.9 | Q17: Central Hidroeléctrica de Langui S.A. | R17: 6.42 | Z17: 6.42
B18: =+B17+1 -> 12 | C18: =+Q19 -> Chinango S.A.C | D18: =+IF(R19<>0,R19,"") -> 195.3 | E18: =+IF(S19<>0,S19,"") | F18: =+IF(T19<>0,T19,"") | G18: =+IF(U19<>0,U19,"") | H18: =+IF(V19<>0,V19,"") | I18: =+IF(W19<>0,W19,"") | J18: =+IF(X19<>0,X19,"") | K18: =+IF((R19+V19)<>0,R19+V19,"") -> 195.3 | L18: =+IF((S19+W19)<>0,S19+W19,"") | M18: =+IF((T19+X19)<>0,T19+X19,"") | N18: =+IF((U19+Y19)<>0,U19+Y19,"") | O18: =SUM(K18:N18) -> 195.3 | Q18: Centrales Santa Rosa S.A.C. | R18: 2.9 | Z18: 2.9
B19: =+B18+1 -> 13 | C19: =+Q20 -> Cía Hidroeléctrica San Hilarión S.A.C. | D19: =+IF(R20<>0,R20,"") | E19: =+IF(S20<>0,S20,"") | F19: =+IF(T20<>0,T20,"") | G19: =+IF(U20<>0,U20,"") | H19: =+IF(V20<>0,V20,"") -> 0.6 | I19: =+IF(W20<>0,W20,"") | J19: =+IF(X20<>0,X20,"") | K19: =+IF((R20+V20)<>0,R20+V20,"") -> 0.6 | L19: =+IF((S20+W20)<>0,S20+W20,"") | M19: =+IF((T20+X20)<>0,T20+X20,"") | N19: =+IF((U20+Y20)<>0,U20+Y20,"") | O19: =SUM(K19:N19) -> 0.6 | Q19: Chinango S.A.C | R19: 195.3 | Z19: 195.3
B20: =+B19+1 -> 14 | C20: =+Q21 -> Cogeneración Oquendo S.A.C. | D20: =+IF(R21<>0,R21,"") | E20: =+IF(S21<>0,S21,"") | F20: =+IF(T21<>0,T21,"") | G20: =+IF(U21<>0,U21,"") | H20: =+IF(V21<>0,V21,"") | I20: =+IF(W21<>0,W21,"") | J20: =+IF(X21<>0,X21,"") | K20: =+IF((R21+V21)<>0,R21+V21,"") | L20: =+IF((S21+W21)<>0,S21+W21,"") | M20: =+IF((T21+X21)<>0,T21+X21,"") | N20: =+IF((U21+Y21)<>0,U21+Y21,"") | O20: =SUM(K20:N20) -> 0 | Q20: Cía Hidroeléctrica San Hilarión S.A.C. | V20: 0.6 | Z20: 0.6
B21: =+B20+1 -> 15 | C21: =+Q22 -> Colca Solar S.A.C. | D21: =+IF(R22<>0,R22,"") | E21: =+IF(S22<>0,S22,"") | F21: =+IF(T22<>0,T22,"") -> 1.2 | G21: =+IF(U22<>0,U22,"") | H21: =+IF(V22<>0,V22,"") | I21: =+IF(W22<>0,W22,"") | J21: =+IF(X22<>0,X22,"") | K21: =+IF((R22+V22)<>0,R22+V22,"") | L21: =+IF((S22+W22)<>0,S22+W22,"") | M21: =+IF((T22+X22)<>0,T22+X22,"") -> 1.2 | N21: =+IF((U22+Y22)<>0,U22+Y22,"") | O21: =SUM(K21:N21) -> 1.2 | Q21: Cogeneración Oquendo S.A.C. | S21: 0 | Z21: 0
B22: =+B21+1 -> 16 | C22: =+Q23 -> Compañia Eléctrica El Platanal S.A. | D22: =+IF(R23<>0,R23,"") -> 220 | E22: =+IF(S23<>0,S23,"") | F22: =+IF(T23<>0,T23,"") | G22: =+IF(U23<>0,U23,"") | H22: =+IF(V23<>0,V23,"") | I22: =+IF(W23<>0,W23,"") | J22: =+IF(X23<>0,X23,"") | K22: =+IF((R23+V23)<>0,R23+V23,"") -> 220 | L22: =+IF((S23+W23)<>0,S23+W23,"") | M22: =+IF((T23+X23)<>0,T23+X23,"") | N22: =+IF((U23+Y23)<>0,U23+Y23,"") | O22: =SUM(K22:N22) -> 220 | Q22: Colca Solar S.A.C. | T22: 1.2 | Z22: 1.2
B23: =+B22+1 -> 17 | C23: =+Q24 -> Compañia Hidroeléctrica Tingo S.A. | D23: =+IF(R24<>0,R24,"") -> 1.65 | E23: =+IF(S24<>0,S24,"") | F23: =+IF(T24<>0,T24,"") | G23: =+IF(U24<>0,U24,"") | H23: =+IF(V24<>0,V24,"") | I23: =+IF(W24<>0,W24,"") | J23: =+IF(X24<>0,X24,"") | K23: =+IF((R24+V24)<>0,R24+V24,"") -> 1.65 | L23: =+IF((S24+W24)<>0,S24+W24,"") | M23: =+IF((T24+X24)<>0,T24+X24,"") | N23: =+IF((U24+Y24)<>0,U24+Y24,"") | O23: =SUM(K23:N23) -> 1.65 | Q23: Compañia Eléctrica El Platanal S.A. | R23: 220 | Z23: 220
B24: =+B23+1 -> 18 | C24: =+Q25 -> Consorcio Eléctrico Villacurí S.A.C. | D24: =+IF(R25<>0,R25,"") -> 1.67 | E24: =+IF(S25<>0,S25,"") -> 19.85 | F24: =+IF(T25<>0,T25,"") | G24: =+IF(U25<>0,U25,"") | H24: =+IF(V25<>0,V25,"") | I24: =+IF(W25<>0,W25,"") | J24: =+IF(X25<>0,X25,"") | K24: =+IF((R25+V25)<>0,R25+V25,"") -> 1.67 | L24: =+IF((S25+W25)<>0,S25+W25,"") -> 19.85 | M24: =+IF((T25+X25)<>0,T25+X25,"") | N24: =+IF((U25+Y25)<>0,U25+Y25,"") | O24: =SUM(K24:N24) -> 21.52 | Q24: Compañia Hidroeléctrica Tingo S.A. | R24: 1.65 | Z24: 1.65
B25: =+B24+1 -> 19 | C25: =+Q26 -> E.A.W. Muller S.A. | D25: =+IF(R26<>0,R26,"") -> 0.592 | E25: =+IF(S26<>0,S26,"") | F25: =+IF(T26<>0,T26,"") | G25: =+IF(U26<>0,U26,"") | H25: =+IF(V26<>0,V26,"") | I25: =+IF(W26<>0,W26,"") | J25: =+IF(X26<>0,X26,"") | K25: =+IF((R26+V26)<>0,R26+V26,"") -> 0.592 | L25: =+IF((S26+W26)<>0,S26+W26,"") | M25: =+IF((T26+X26)<>0,T26+X26,"") | N25: =+IF((U26+Y26)<>0,U26+Y26,"") | O25: =SUM(K25:N25) -> 0.592 | Q25: Consorcio Eléctrico Villacurí S.A.C. | R25: 1.67 | S25: 19.85 | Z25: 21.52
B26: =+B25+1 -> 20 | C26: =+Q27 -> Eléctrica Yanapampa S.A.C. | D26: =+IF(R27<>0,R27,"") -> 4.155 | E26: =+IF(S27<>0,S27,"") | F26: =+IF(T27<>0,T27,"") | G26: =+IF(U27<>0,U27,"") | H26: =+IF(V27<>0,V27,"") | I26: =+IF(W27<>0,W27,"") | J26: =+IF(X27<>0,X27,"") | K26: =+IF((R27+V27)<>0,R27+V27,"") -> 4.155 | L26: =+IF((S27+W27)<>0,S27+W27,"") | M26: =+IF((T27+X27)<>0,T27+X27,"") | N26: =+IF((U27+Y27)<>0,U27+Y27,"") | O26: =SUM(K26:N26) -> 4.155 | Q26: E.A.W. Muller S.A. | R26: 0.592 | Z26: 0.592
B27: =+B26+1 -> 21 | C27: =+Q28 -> Electro Dunas S.A.A. | D27: =+IF(R28<>0,R28,"") -> 0.22 | E27: =+IF(S28<>0,S28,"") -> 48.684 | F27: =+IF(T28<>0,T28,"") | G27: =+IF(U28<>0,U28,"") | H27: =+IF(V28<>0,V28,"") | I27: =+IF(W28<>0,W28,"") | J27: =+IF(X28<>0,X28,"") | K27: =+IF((R28+V28)<>0,R28+V28,"") -> 0.22 | L27: =+IF((S28+W28)<>0,S28+W28,"") -> 48.684 | M27: =+IF((T28+X28)<>0,T28+X28,"") | N27: =+IF((U28+Y28)<>0,U28+Y28,"") | O27: =SUM(K27:N27) -> 48.904 | Q27: Eléctrica Yanapampa S.A.C. | R27: 4.155 | Z27: 4.155
B28: =+B27+1 -> 22 | C28: =+Q29 -> Electro Oriente S. A. | D28: =+IF(R29<>0,R29,"") -> 27.404 | E28: =+IF(S29<>0,S29,"") -> 29.035 | F28: =+IF(T29<>0,T29,"") | G28: =+IF(U29<>0,U29,"") | H28: =+IF(V29<>0,V29,"") | I28: =+IF(W29<>0,W29,"") -> 110.195 | J28: =+IF(X29<>0,X29,"") | K28: =+IF((R29+V29)<>0,R29+V29,"") -> 27.404 | L28: =+IF((S29+W29)<>0,S29+W29,"") -> 139.23 | M28: =+IF((T29+X29)<>0,T29+X29,"") | N28: =+IF((U29+Y29)<>0,U29+Y29,"") | O28: =SUM(K28:N28) -> 166.634 | Q28: Electro Dunas S.A.A. | R28: 0.22 | S28: 48.684 | Z28: 48.904
B29: =+B28+1 -> 23 | C29: =+Q30 -> Electro Puno S.A.A. | D29: =+IF(R30<>0,R30,"") -> 4.5 | E29: =+IF(S30<>0,S30,"") -> 0.25 | F29: =+IF(T30<>0,T30,"") -> 0.275 | G29: =+IF(U30<>0,U30,"") | H29: =+IF(V30<>0,V30,"") | I29: =+IF(W30<>0,W30,"") | J29: =+IF(X30<>0,X30,"") | K29: =+IF((R30+V30)<>0,R30+V30,"") -> 4.5 | L29: =+IF((S30+W30)<>0,S30+W30,"") -> 0.25 | M29: =+IF((T30+X30)<>0,T30+X30,"") -> 0.275 | N29: =+IF((U30+Y30)<>0,U30+Y30,"") | O29: =SUM(K29:N29) -> 5.025 | Q29: Electro Oriente S. A. | R29: 27.404 | S29: 29.035 | W29: 110.195 | Z29: 166.634
B30: =+B29+1 -> 24 | C30: =+Q31 -> Electro Sur Este S.A.A. | D30: =+IF(R31<>0,R31,"") -> 10.256 | E30: =+IF(S31<>0,S31,"") -> 5.7 | F30: =+IF(T31<>0,T31,"") | G30: =+IF(U31<>0,U31,"") | H30: =+IF(V31<>0,V31,"") | I30: =+IF(W31<>0,W31,"") | J30: =+IF(X31<>0,X31,"") | K30: =+IF((R31+V31)<>0,R31+V31,"") -> 10.256 | L30: =+IF((S31+W31)<>0,S31+W31,"") -> 5.7 | M30: =+IF((T31+X31)<>0,T31+X31,"") | N30: =+IF((U31+Y31)<>0,U31+Y31,"") | O30: =SUM(K30:N30) -> 15.956 | Q30: Electro Puno S.A.A. | R30: 4.5 | S30: 0.25 | T30: 0.275 | Z30: 5.025
B31: =+B30+1 -> 25 | C31: =+Q32 -> Electro Ucayali S.A. | D31: =+IF(R32<>0,R32,"") | E31: =+IF(S32<>0,S32,"") | F31: =+IF(T32<>0,T32,"") | G31: =+IF(U32<>0,U32,"") | H31: =+IF(V32<>0,V32,"") -> 0.87 | I31: =+IF(W32<>0,W32,"") -> 3.818 | J31: =+IF(X32<>0,X32,"") -> 0.01 | K31: =+IF((R32+V32)<>0,R32+V32,"") -> 0.87 | L31: =+IF((S32+W32)<>0,S32+W32,"") -> 3.818 | M31: =+IF((T32+X32)<>0,T32+X32,"") -> 0.01 | N31: =+IF((U32+Y32)<>0,U32+Y32,"") | O31: =SUM(K31:N31) -> 4.698 | Q31: Electro Sur Este S.A.A. | R31: 10.256 | S31: 5.7 | Z31: 15.956
B32: =+B31+1 -> 26 | C32: =+Q33 -> Electro Zaña S.A.C. | D32: =+IF(R33<>0,R33,"") -> 13.2 | E32: =+IF(S33<>0,S33,"") | F32: =+IF(T33<>0,T33,"") | G32: =+IF(U33<>0,U33,"") | H32: =+IF(V33<>0,V33,"") | I32: =+IF(W33<>0,W33,"") | J32: =+IF(X33<>0,X33,"") | K32: =+IF((R33+V33)<>0,R33+V33,"") -> 13.2 | L32: =+IF((S33+W33)<>0,S33+W33,"") | M32: =+IF((T33+X33)<>0,T33+X33,"") | N32: =+IF((U33+Y33)<>0,U33+Y33,"") | O32: =SUM(K32:N32) -> 13.2 | Q32: Electro Ucayali S.A. | V32: 0.87 | W32: 3.818 | X32: 0.01 | Z32: 4.698
B33: =+B32+1 -> 27 | C33: =+Q34 -> Electrocentro S.A. | D33: =+IF(R34<>0,R34,"") -> 21.206 | E33: =+IF(S34<>0,S34,"") -> 4.1 | F33: =+IF(T34<>0,T34,"") | G33: =+IF(U34<>0,U34,"") | H33: =+IF(V34<>0,V34,"") | I33: =+IF(W34<>0,W34,"") | J33: =+IF(X34<>0,X34,"") | K33: =+IF((R34+V34)<>0,R34+V34,"") -> 21.206 | L33: =+IF((S34+W34)<>0,S34+W34,"") -> 4.1 | M33: =+IF((T34+X34)<>0,T34+X34,"") | N33: =+IF((U34+Y34)<>0,U34+Y34,"") | O33: =SUM(K33:N33) -> 25.306 | Q33: Electro Zaña S.A.C. | R33: 13.2 | Z33: 13.2
